Workbook

Sheet DESP_JANEIRO
A1: PREENCHER APENAS CÉLULAS COM FUNDO AZUL | D1: JANEIRO | E1: 2026 | F1: DIAS MÊS >>> | G1: =DAY(A256) -> 31 | I1: =IF(I256>$I258,"",WEEKDAY(I256)) -> 5 | J1: =IF(J256>$I258,"",WEEKDAY(J256)) -> 6 | K1: =IF(K256>$I258,"",WEEKDAY(K256)) -> 7 | L1: =IF(L256>$I258,"",WEEKDAY(L256)) -> 1 | M1: =IF(M256>$I258,"",WEEKDAY(M256)) -> 2 | N1: =IF(N256>$I258,"",WEEKDAY(N256)) -> 3 | O1: =IF(O256>$I258,"",WEEKDAY(O256)) -> 4 | P1: =IF(P256>$I258,"",WEEKDAY(P256)) -> 5 | ... AM1: =IF(AM256>$I258,"",WEEKDAY(AM256)) -> 7 | AN1: JUROS E MULTA | AQ1: O RESUMO MENSAL | AS1: O RESUMO MENSAL | AU1: O RESUMO MENSAL | AW1: O RESUMO MENSAL | AY1: O RESUMO MENSAL | BA1: O RESUMO MENSAL | BC1: O RESUMO MENSAL
A2: DESCRIÇÃO | B2: DESPESAS | D2: PAGAMENTOS | F2: HOJE >>>>>>> | G2: =DAY(TODAY()) -> 13 | I2: 1 | J2: =I2+1 -> 2 | K2: =J2+1 -> 3 | L2: =K2+1 -> 4 | M2: =L2+1 -> 5 | N2: =M2+1 -> 6 | O2: =N2+1 -> 7 | P2: =O2+1 -> 8 | Q2: =P2+1 -> 9 | ... AM2: =AL2+1 -> 31 | AN2: BOLETOS VENC. | AQ2: =+I2 -> 1 | AS2: =+J2 -> 2 | AU2: =+K2 -> 3 | AW2: =+L2 -> 4 | AY2: =+M2 -> 5 | BA2: =+N2 -> 6 | BC2: =+O2 -> 7
A3: PESSOAL | B3: A PAGAR | C3: DIA | D3: PAGO | E3: DIA | F3: ATRASO | G3: P/AP | AQ3: =+I1 -> 5 | AS3: =+J1 -> 6 | AU3: =+K1 -> 7 | AW3: =+L1 -> 1 | AY3: =+M1 -> 2 | BA3: =+N1 -> 3 | BC3: =+O1 -> 4
F4: e acumulado
A5: Sulamerica | B5: 6650 | C5: 2 | D5: 6650 | E5: 2 | F5: =+IF(TODAY()<DATEVALUE(1&D$1&E$1),0,IF(C5>0,IF(C5-SUM(I$255:AM$255)<0,B5-SUM(I5:AM5,0),0),0))+IF(C5=-1,B5-SUM(J5:AM5)) -> 0 | G5: =+IF(B5<1,"-",D5/B5) -> 1 | I5: =IF(I$2=$E5,$D5,IF(I$2>I$257,0,IF($C5=I$2,"PAGAR"&" "&TEXT($B5," #.##0,00"),IF($C5=-1,"PAGAR"&" "&TEXT($B5," #.##0,00"),0)))) -> 0 | J5: =+IF(J$2=$E5,$D5,IF(J$2>J$257,0,IF($C5=J$2,"PAGAR"&" "&TEXT($B5," #.##0,00"),0))) -> 6650 | K5: =+IF(K$2=$E5,$D5,IF(K$2>K$257,0,IF($C5=K$2,"PAGAR"&" "&TEXT($B5," #.##0,00"),0))) -> 0 | L5: =+IF(L$2=$E5,$D5,IF(L$2>L$257,0,IF($C5=L$2,"PAGAR"&" "&TEXT($B5," #.##0,00"),0))) -> 0 | M5: =+IF(M$2=$E5,$D5,IF(M$2>M$257,0,IF($C5=M$2,"PAGAR"&" "&TEXT($B5," #.##0,00"),0))) -> 0 | N5: =+IF(N$2=$E5,$D5,IF(N$2>N$257,0,IF($C5=N$2,"PAGAR"&" "&TEXT($B5," #.##0,00"),0))) -> 0 | O5: =+IF(O$2=$E5,$D5,IF(O$2>O$257,0,IF($C5=O$2,"PAGAR"&" "&TEXT($B5," #.##0,00"),0))) -> 0 | P5: =+IF(P$2=$E5,$D5,IF(P$2>P$257,0,IF($C5=P$2,"PAGAR"&" "&TEXT($B5," #.##0,00"),0))) -> 0 | Q5: =+IF(Q$2=$E5,$D5,IF(Q$2>Q$257,0,IF($C5=Q$2,"PAGAR"&" "&TEXT($B5," #.##0,00"),0))) -> 0 | ... AM5: =+IF(AM$2=$E5,$D5,IF(AM$2>AM$257,0,IF($C5=AM$2,"PAGAR"&" "&TEXT($B5," #.##0,00"),0))) -> 0 | AN5: =+IF(F5<0,-F5,0) -> 0 | AO5: =+IF(AND(C5=0,B5>0),B5,0) -> 0 | AQ5: {=_xlfn._xlws.FILTER($A$5:$A$152,$C$5:$C$152=AQ2,"livre")} -> Condomínio Sta Rita | AR5: {=_xlfn._xlws.FILTER($B$5:$B$152,$C$5:$C$152=AQ2,"livre")} -> 300 | AS5: {=_xlfn._xlws.FILTER($A$5:$A$152,$C$5:$C$152=AS2,"livre")} -> Sulamerica | AT5: {=_xlfn._xlws.FILTER($B$5:$B$152,$C$5:$C$152=AS2,"livre")} -> 6650 | AU5: {=_xlfn._xlws.FILTER($A$5:$A$152,$C$5:$C$152=AU2,"livre")} -> Apple - Cartão | AV5: {=_xlfn._xlws.FILTER($B$5:$B$152,$C$5:$C$152=AU2,"livre")} -> 5.9 | AW5: {=_xlfn._xlws.FILTER($A$5:$A$152,$C$5:$C$152=AW2,"livre")} -> Google Adobe - Cartão | AX5: {=_xlfn._xlws.FILTER($B$5:$B$152,$C$5:$C$152=AW2,"livre")} -> 22.99 | AY5: {=_xlfn._xlws.FILTER($A$5:$A$152,$C$5:$C$152=AY2,"livre")} -> Apple.com - Cartão | AZ5: {=_xlfn._xlws.FILTER($B$5:$B$152,$C$5:$C$152=AY2,"livre")} -> 5.9 | BA5: {=_xlfn._xlws.FILTER($A$5:$A$152,$C$5:$C$152=BA2,"livre")} -> Francisca | BB5: {=_xlfn._xlws.FILTER($B$5:$B$152,$C$5:$C$152=BA2,"livre")} -> 1080 | BC5: {=_xlfn._xlws.FILTER($A$5:$A$152,$C$5:$C$152=BC2,"livre")} -> Sulamerica | BD5: {=_xlfn._xlws.FILTER($B$5:$B$152,$C$5:$C$152=BC2,"livre")} -> 6359.51
A6: Sulamerica | B6: 6359.51 | C6: 7 | F6: =+IF(TODAY()<DATEVALUE(1&D$1&E$1),0,IF(C6>0,IF(C6-SUM(I$255:AM$255)<0,B6-SUM(I6:AM6,0),0),0))+IF(C6=-1,B6-SUM(J6:AM6)) -> 6359.51 | G6: =+IF(B6<1,"-",D6/B6) -> 0 | I6: =IF(I$2=$E6,$D6,IF(I$2>I$257,0,IF($C6=I$2,"PAGAR"&" "&TEXT($B6," #.##0,00"),IF($C6=-1,"PAGAR"&" "&TEXT($B6," #.##0,00"),0)))) -> 0 | J6: =+IF(J$2=$E6,$D6,IF(J$2>J$257,0,IF($C6=J$2,"PAGAR"&" "&TEXT($B6," #.##0,00"),0))) -> 0 | K6: =+IF(K$2=$E6,$D6,IF(K$2>K$257,0,IF($C6=K$2,"PAGAR"&" "&TEXT($B6," #.##0,00"),0))) -> 0 | L6: =+IF(L$2=$E6,$D6,IF(L$2>L$257,0,IF($C6=L$2,"PAGAR"&" "&TEXT($B6," #.##0,00"),0))) -> 0 | M6: =+IF(M$2=$E6,$D6,IF(M$2>M$257,0,IF($C6=M$2,"PAGAR"&" "&TEXT($B6," #.##0,00"),0))) -> 0 | N6: =+IF(N$2=$E6,$D6,IF(N$2>N$257,0,IF($C6=N$2,"PAGAR"&" "&TEXT($B6," #.##0,00"),0))) -> 0 | O6: =+IF(O$2=$E6,$D6,IF(O$2>O$257,0,IF($C6=O$2,"PAGAR"&" "&TEXT($B6," #.##0,00"),0))) -> PAGAR 6.359,51 | P6: =+IF(P$2=$E6,$D6,IF(P$2>P$257,0,IF($C6=P$2,"PAGAR"&" "&TEXT($B6," #.##0,00"),0))) -> 0 | Q6: =+IF(Q$2=$E6,$D6,IF(Q$2>Q$257,0,IF($C6=Q$2,"PAGAR"&" "&TEXT($B6," #.##0,00"),0))) -> 0 | ... AM6: =+IF(AM$2=$E6,$D6,IF(AM$2>AM$257,0,IF($C6=AM$2,"PAGAR"&" "&TEXT($B6," #.##0,00"),0))) -> 0 | AN6: =+IF(F6<0,-F6,0) -> 0 | AO6: =+IF(AND(C6=0,B6>0),B6,0) -> 0 | AQ6: Letízio mensal | AR6: 1750 | AS6: Clayton manutenção | AT6: 1000 | AU6: Microsoft Office - Cartão | AV6: 60 | AY6: Claro Reserva | AZ6: 288.06 | BA6: CPFL Ágata | BB6: 173.49 | BC6: Netflix - cartão | BD6: 44.9
A7: Seguro Vida Presente 16 | B7: 770.07 | C7: 0 | D7: 770.07 | E7: 12 | F7: =+IF(TODAY()<DATEVALUE(1&D$1&E$1),0,IF(C7>0,IF(C7-SUM(I$255:AM$255)<0,B7-SUM(I7:AM7,0),0),0))+IF(C7=-1,B7-SUM(J7:AM7)) -> 0 | G7: =+IF(B7<1,"-",D7/B7) -> 1 | I7: =IF(I$2=$E7,$D7,IF(I$2>I$257,0,IF($C7=I$2,"PAGAR"&" "&TEXT($B7," #.##0,00"),IF($C7=-1,"PAGAR"&" "&TEXT($B7," #.##0,00"),0)))) -> 0 | J7: =+IF(J$2=$E7,$D7,IF(J$2>J$257,0,IF($C7=J$2,"PAGAR"&" "&TEXT($B7," #.##0,00"),0))) -> 0 | K7: =+IF(K$2=$E7,$D7,IF(K$2>K$257,0,IF($C7=K$2,"PAGAR"&" "&TEXT($B7," #.##0,00"),0))) -> 0 | L7: =+IF(L$2=$E7,$D7,IF(L$2>L$257,0,IF($C7=L$2,"PAGAR"&" "&TEXT($B7," #.##0,00"),0))) -> 0 | M7: =+IF(M$2=$E7,$D7,IF(M$2>M$257,0,IF($C7=M$2,"PAGAR"&" "&TEXT($B7," #.##0,00"),0))) -> 0 | N7: =+IF(N$2=$E7,$D7,IF(N$2>N$257,0,IF($C7=N$2,"PAGAR"&" "&TEXT($B7," #.##0,00"),0))) -> 0 | O7: =+IF(O$2=$E7,$D7,IF(O$2>O$257,0,IF($C7=O$2,"PAGAR"&" "&TEXT($B7," #.##0,00"),0))) -> 0 | P7: =+IF(P$2=$E7,$D7,IF(P$2>P$257,0,IF($C7=P$2,"PAGAR"&" "&TEXT($B7," #.##0,00"),0))) -> 0 | Q7: =+IF(Q$2=$E7,$D7,IF(Q$2>Q$257,0,IF($C7=Q$2,"PAGAR"&" "&TEXT($B7," #.##0,00"),0))) -> 0 | ... AM7: =+IF(AM$2=$E7,$D7,IF(AM$2>AM$257,0,IF($C7=AM$2,"PAGAR"&" "&TEXT($B7," #.##0,00"),0))) -> 0 | AN7: =+IF(F7<0,-F7,0) -> 0 | AO7: =+IF(AND(C7=0,B7>0),B7,0) -> 770.07 | AS7: VT | AT7: 500 | AU7: VA 5 anos | AV7: 1890 | AY7: Itaú - pron. débito auto (6/24x) 1,6% 150k | AZ7: 5188 | BA7: AGDES Reserva | BB7: 291.1
A8: Seguro Vida Presente 21 | B8: 770.07 | C8: 25 | D8: 770.07 | E8: 10 | F8: =+IF(TODAY()<DATEVALUE(1&D$1&E$1),0,IF(C8>0,IF(C8-SUM(I$255:AM$255)<0,B8-SUM(I8:AM8,0),0),0))+IF(C8=-1,B8-SUM(J8:AM8)) -> 0 | G8: =+IF(B8<1,"-",D8/B8) -> 1 | I8: =IF(I$2=$E8,$D8,IF(I$2>I$257,0,IF($C8=I$2,"PAGAR"&" "&TEXT($B8," #.##0,00"),IF($C8=-1,"PAGAR"&" "&TEXT($B8," #.##0,00"),0)))) -> 0 | J8: =+IF(J$2=$E8,$D8,IF(J$2>J$257,0,IF($C8=J$2,"PAGAR"&" "&TEXT($B8," #.##0,00"),0))) -> 0 | K8: =+IF(K$2=$E8,$D8,IF(K$2>K$257,0,IF($C8=K$2,"PAGAR"&" "&TEXT($B8," #.##0,00"),0))) -> 0 | L8: =+IF(L$2=$E8,$D8,IF(L$2>L$257,0,IF($C8=L$2,"PAGAR"&" "&TEXT($B8," #.##0,00"),0))) -> 0 | M8: =+IF(M$2=$E8,$D8,IF(M$2>M$257,0,IF($C8=M$2,"PAGAR"&" "&TEXT($B8," #.##0,00"),0))) -> 0 | N8: =+IF(N$2=$E8,$D8,IF(N$2>N$257,0,IF($C8=N$2,"PAGAR"&" "&TEXT($B8," #.##0,00"),0))) -> 0 | O8: =+IF(O$2=$E8,$D8,IF(O$2>O$257,0,IF($C8=O$2,"PAGAR"&" "&TEXT($B8," #.##0,00"),0))) -> 0 | P8: =+IF(P$2=$E8,$D8,IF(P$2>P$257,0,IF($C8=P$2,"PAGAR"&" "&TEXT($B8," #.##0,00"),0))) -> 0 | Q8: =+IF(Q$2=$E8,$D8,IF(Q$2>Q$257,0,IF($C8=Q$2,"PAGAR"&" "&TEXT($B8," #.##0,00"),0))) -> 0 | ... AM8: =+IF(AM$2=$E8,$D8,IF(AM$2>AM$257,0,IF($C8=AM$2,"PAGAR"&" "&TEXT($B8," #.##0,00"),0))) -> 0 | AN8: =+IF(F8<0,-F8,0) -> 0 | AO8: =+IF(AND(C8=0,B8>0),B8,0) -> 0 | AU8: Lucas VA 5 anos e normal | AV8: 420 | AY8: Frees + R$400 Josiane | AZ8: 6900 | BA8: 4 Lock -- folha | BB8: 12000
A9: Seguro Previdência VGBL 21 | B9: 675.52 | C9: 25 | F9: =+IF(TODAY()<DATEVALUE(1&D$1&E$1),0,IF(C9>0,IF(C9-SUM(I$255:AM$255)<0,B9-SUM(I9:AM9,0),0),0))+IF(C9=-1,B9-SUM(J9:AM9)) -> 0 | G9: =+IF(B9=0,"-",D9/B9) -> 0 | I9: =IF(I$2=$E9,$D9,IF(I$2>I$257,0,IF($C9=I$2,"PAGAR"&" "&TEXT($B9," #.##0,00"),IF($C9=-1,"PAGAR"&" "&TEXT($B9," #.##0,00"),0)))) -> 0 | J9: =+IF(J$2=$E9,$D9,IF(J$2>J$257,0,IF($C9=J$2,"PAGAR"&" "&TEXT($B9," #.##0,00"),0))) -> 0 | K9: =+IF(K$2=$E9,$D9,IF(K$2>K$257,0,IF($C9=K$2,"PAGAR"&" "&TEXT($B9," #.##0,00"),0))) -> 0 | L9: =+IF(L$2=$E9,$D9,IF(L$2>L$257,0,IF($C9=L$2,"PAGAR"&" "&TEXT($B9," #.##0,00"),0))) -> 0 | M9: =+IF(M$2=$E9,$D9,IF(M$2>M$257,0,IF($C9=M$2,"PAGAR"&" "&TEXT($B9," #.##0,00"),0))) -> 0 | N9: =+IF(N$2=$E9,$D9,IF(N$2>N$257,0,IF($C9=N$2,"PAGAR"&" "&TEXT($B9," #.##0,00"),0))) -> 0 | O9: =+IF(O$2=$E9,$D9,IF(O$2>O$257,0,IF($C9=O$2,"PAGAR"&" "&TEXT($B9," #.##0,00"),0))) -> 0 | P9: =+IF(P$2=$E9,$D9,IF(P$2>P$257,0,IF($C9=P$2,"PAGAR"&" "&TEXT($B9," #.##0,00"),0))) -> 0 | Q9: =+IF(Q$2=$E9,$D9,IF(Q$2>Q$257,0,IF($C9=Q$2,"PAGAR"&" "&TEXT($B9," #.##0,00"),0))) -> 0 | ... AM9: =+IF(AM$2=$E9,$D9,IF(AM$2>AM$257,0,IF($C9=AM$2,"PAGAR"&" "&TEXT($B9," #.##0,00"),0))) -> 0 | AN9: =+IF(F9<0,-F9,0) -> 0 | AO9: =+IF(AND(C9=0,B9>0),B9,0) -> 0 | BA9: Perfecto -- folha | BB9: 1500
A10: Cartão | B10: 1928.17 | C10: 28 | F10: =+IF(TODAY()<DATEVALUE(1&D$1&E$1),0,IF(C10>0,IF(C10-SUM(I$255:AM$255)<0,B10-SUM(I10:AM10,0),0),0))+IF(C10=-1,B10-SUM(J10:AM10)) -> 0 | G10: =+IF(B10=0,"-",D10/B10) -> 0 | I10: =IF(I$2=$E10,$D10,IF(I$2>I$257,0,IF($C10=I$2,"PAGAR"&" "&TEXT($B10," #.##0,00"),IF($C10=-1,"PAGAR"&" "&TEXT($B10," #.##0,00"),0)))) -> 0 | J10: =+IF(J$2=$E10,$D10,IF(J$2>J$257,0,IF($C10=J$2,"PAGAR"&" "&TEXT($B10," #.##0,00"),0))) -> 0 | K10: =+IF(K$2=$E10,$D10,IF(K$2>K$257,0,IF($C10=K$2,"PAGAR"&" "&TEXT($B10," #.##0,00"),0))) -> 0 | L10: =+IF(L$2=$E10,$D10,IF(L$2>L$257,0,IF($C10=L$2,"PAGAR"&" "&TEXT($B10," #.##0,00"),0))) -> 0 | M10: =+IF(M$2=$E10,$D10,IF(M$2>M$257,0,IF($C10=M$2,"PAGAR"&" "&TEXT($B10," #.##0,00"),0))) -> 0 | N10: =+IF(N$2=$E10,$D10,IF(N$2>N$257,0,IF($C10=N$2,"PAGAR"&" "&TEXT($B10," #.##0,00"),0))) -> 0 | O10: =+IF(O$2=$E10,$D10,IF(O$2>O$257,0,IF($C10=O$2,"PAGAR"&" "&TEXT($B10," #.##0,00"),0))) -> 0 | P10: =+IF(P$2=$E10,$D10,IF(P$2>P$257,0,IF($C10=P$2,"PAGAR"&" "&TEXT($B10," #.##0,00"),0))) -> 0 | Q10: =+IF(Q$2=$E10,$D10,IF(Q$2>Q$257,0,IF($C10=Q$2,"PAGAR"&" "&TEXT($B10," #.##0,00"),0))) -> 0 | ... AM10: =+IF(AM$2=$E10,$D10,IF(AM$2>AM$257,0,IF($C10=AM$2,"PAGAR"&" "&TEXT($B10," #.##0,00"),0))) -> 0 | AN10: =+IF(F10<0,-F10,0) -> 0 | AO10: =+IF(AND(C10=0,B10>0),B10,0) -> 0
A11: Apple - Cartão | B11: 5.9 | C11: 3 | F11: =+IF(TODAY()<DATEVALUE(1&D$1&E$1),0,IF(C11>0,IF(C11-SUM(I$255:AM$255)<0,B11-SUM(I11:AM11,0),0),0))+IF(C11=-1,B11-SUM(J11:AM11)) -> 5.9 | G11: =+IF(B11=0,"-",D11/B11) -> 0 | I11: =IF(I$2=$E11,$D11,IF(I$2>I$257,0,IF($C11=I$2,"PAGAR"&" "&TEXT($B11," #.##0,00"),IF($C11=-1,"PAGAR"&" "&TEXT($B11," #.##0,00"),0)))) -> 0 | J11: =+IF(J$2=$E11,$D11,IF(J$2>J$257,0,IF($C11=J$2,"PAGAR"&" "&TEXT($B11," #.##0,00"),0))) -> 0 | K11: =+IF(K$2=$E11,$D11,IF(K$2>K$257,0,IF($C11=K$2,"PAGAR"&" "&TEXT($B11," #.##0,00"),0))) -> PAGAR 5,90 | L11: =+IF(L$2=$E11,$D11,IF(L$2>L$257,0,IF($C11=L$2,"PAGAR"&" "&TEXT($B11," #.##0,00"),0))) -> 0 | M11: =+IF(M$2=$E11,$D11,IF(M$2>M$257,0,IF($C11=M$2,"PAGAR"&" "&TEXT($B11," #.##0,00"),0))) -> 0 | N11: =+IF(N$2=$E11,$D11,IF(N$2>N$257,0,IF($C11=N$2,"PAGAR"&" "&TEXT($B11," #.##0,00"),0))) -> 0 | O11: =+IF(O$2=$E11,$D11,IF(O$2>O$257,0,IF($C11=O$2,"PAGAR"&" "&TEXT($B11," #.##0,00"),0))) -> 0 | P11: =+IF(P$2=$E11,$D11,IF(P$2>P$257,0,IF($C11=P$2,"PAGAR"&" "&TEXT($B11," #.##0,00"),0))) -> 0 | Q11: =+IF(Q$2=$E11,$D11,IF(Q$2>Q$257,0,IF($C11=Q$2,"PAGAR"&" "&TEXT($B11," #.##0,00"),0))) -> 0 | ... AM11: =+IF(AM$2=$E11,$D11,IF(AM$2>AM$257,0,IF($C11=AM$2,"PAGAR"&" "&TEXT($B11," #.##0,00"),0))) -> 0 | AN11: =+IF(F11<0,-F11,0) -> 0 | AO11: =+IF(AND(C11=0,B11>0),B11,0) -> 0
A12: Netflix - cartão | B12: 44.9 | C12: 7 | F12: =+IF(TODAY()<DATEVALUE(1&D$1&E$1),0,IF(C12>0,IF(C12-SUM(I$255:AM$255)<0,B12-SUM(I12:AM12,0),0),0))+IF(C12=-1,B12-SUM(J12:AM12)) -> 44.9 | G12: =+IF(B12=0,"-",D12/B12) -> 0 | I12: =IF(I$2=$E12,$D12,IF(I$2>I$257,0,IF($C12=I$2,"PAGAR"&" "&TEXT($B12," #.##0,00"),IF($C12=-1,"PAGAR"&" "&TEXT($B12," #.##0,00"),0)))) -> 0 | J12: =+IF(J$2=$E12,$D12,IF(J$2>J$257,0,IF($C12=J$2,"PAGAR"&" "&TEXT($B12," #.##0,00"),0))) -> 0 | K12: =+IF(K$2=$E12,$D12,IF(K$2>K$257,0,IF($C12=K$2,"PAGAR"&" "&TEXT($B12," #.##0,00"),0))) -> 0 | L12: =+IF(L$2=$E12,$D12,IF(L$2>L$257,0,IF($C12=L$2,"PAGAR"&" "&TEXT($B12," #.##0,00"),0))) -> 0 | M12: =+IF(M$2=$E12,$D12,IF(M$2>M$257,0,IF($C12=M$2,"PAGAR"&" "&TEXT($B12," #.##0,00"),0))) -> 0 | N12: =+IF(N$2=$E12,$D12,IF(N$2>N$257,0,IF($C12=N$2,"PAGAR"&" "&TEXT($B12," #.##0,00"),0))) -> 0 | O12: =+IF(O$2=$E12,$D12,IF(O$2>O$257,0,IF($C12=O$2,"PAGAR"&" "&TEXT($B12," #.##0,00"),0))) -> PAGAR 44,90 | P12: =+IF(P$2=$E12,$D12,IF(P$2>P$257,0,IF($C12=P$2,"PAGAR"&" "&TEXT($B12," #.##0,00"),0))) -> 0 | Q12: =+IF(Q$2=$E12,$D12,IF(Q$2>Q$257,0,IF($C12=Q$2,"PAGAR"&" "&TEXT($B12," #.##0,00"),0))) -> 0 | ... AM12: =+IF(AM$2=$E12,$D12,IF(AM$2>AM$257,0,IF($C12=AM$2,"PAGAR"&" "&TEXT($B12," #.##0,00"),0))) -> 0 | AN12: =+IF(F12<0,-F12,0) -> 0 | AO12: =+IF(AND(C12=0,B12>0),B12,0) -> 0
A13: Google One IA - Cartão | B13: 96.99 | C13: 22 | F13: =+IF(TODAY()<DATEVALUE(1&D$1&E$1),0,IF(C13>0,IF(C13-SUM(I$255:AM$255)<0,B13-SUM(I13:AM13,0),0),0))+IF(C13=-1,B13-SUM(J13:AM13)) -> 0 | G13: =+IF(B13=0,"-",D13/B13) -> 0 | I13: =IF(I$2=$E13,$D13,IF(I$2>I$257,0,IF($C13=I$2,"PAGAR"&" "&TEXT($B13," #.##0,00"),IF($C13=-1,"PAGAR"&" "&TEXT($B13," #.##0,00"),0)))) -> 0 | J13: =+IF(J$2=$E13,$D13,IF(J$2>J$257,0,IF($C13=J$2,"PAGAR"&" "&TEXT($B13," #.##0,00"),0))) -> 0 | K13: =+IF(K$2=$E13,$D13,IF(K$2>K$257,0,IF($C13=K$2,"PAGAR"&" "&TEXT($B13," #.##0,00"),0))) -> 0 | L13: =+IF(L$2=$E13,$D13,IF(L$2>L$257,0,IF($C13=L$2,"PAGAR"&" "&TEXT($B13," #.##0,00"),0))) -> 0 | M13: =+IF(M$2=$E13,$D13,IF(M$2>M$257,0,IF($C13=M$2,"PAGAR"&" "&TEXT($B13," #.##0,00"),0))) -> 0 | N13: =+IF(N$2=$E13,$D13,IF(N$2>N$257,0,IF($C13=N$2,"PAGAR"&" "&TEXT($B13," #.##0,00"),0))) -> 0 | O13: =+IF(O$2=$E13,$D13,IF(O$2>O$257,0,IF($C13=O$2,"PAGAR"&" "&TEXT($B13," #.##0,00"),0))) -> 0 | P13: =+IF(P$2=$E13,$D13,IF(P$2>P$257,0,IF($C13=P$2,"PAGAR"&" "&TEXT($B13," #.##0,00"),0))) -> 0 | Q13: =+IF(Q$2=$E13,$D13,IF(Q$2>Q$257,0,IF($C13=Q$2,"PAGAR"&" "&TEXT($B13," #.##0,00"),0))) -> 0 | ... AM13: =+IF(AM$2=$E13,$D13,IF(AM$2>AM$257,0,IF($C13=AM$2,"PAGAR"&" "&TEXT($B13," #.##0,00"),0))) -> 0 | AN13: =+IF(F13<0,-F13,0) -> 0 | AO13: =+IF(AND(C13=0,B13>0),B13,0) -> 0
A14: Yelum Seguro Civic - Cartão | B14: 286.78 | C14: 28 | F14: =+IF(TODAY()<DATEVALUE(1&D$1&E$1),0,IF(C14>0,IF(C14-SUM(I$255:AM$255)<0,B14-SUM(I14:AM14,0),0),0))+IF(C14=-1,B14-SUM(J14:AM14)) -> 0 | G14: =+IF(B14=0,"-",D14/B14) -> 0 | I14: =IF(I$2=$E14,$D14,IF(I$2>I$257,0,IF($C14=I$2,"PAGAR"&" "&TEXT($B14," #.##0,00"),IF($C14=-1,"PAGAR"&" "&TEXT($B14," #.##0,00"),0)))) -> 0 | J14: =+IF(J$2=$E14,$D14,IF(J$2>J$257,0,IF($C14=J$2,"PAGAR"&" "&TEXT($B14," #.##0,00"),0))) -> 0 | K14: =+IF(K$2=$E14,$D14,IF(K$2>K$257,0,IF($C14=K$2,"PAGAR"&" "&TEXT($B14," #.##0,00"),0))) -> 0 | L14: =+IF(L$2=$E14,$D14,IF(L$2>L$257,0,IF($C14=L$2,"PAGAR"&" "&TEXT($B14," #.##0,00"),0))) -> 0 | M14: =+IF(M$2=$E14,$D14,IF(M$2>M$257,0,IF($C14=M$2,"PAGAR"&" "&TEXT($B14," #.##0,00"),0))) -> 0 | N14: =+IF(N$2=$E14,$D14,IF(N$2>N$257,0,IF($C14=N$2,"PAGAR"&" "&TEXT($B14," #.##0,00"),0))) -> 0 | O14: =+IF(O$2=$E14,$D14,IF(O$2>O$257,0,IF($C14=O$2,"PAGAR"&" "&TEXT($B14," #.##0,00"),0))) -> 0 | P14: =+IF(P$2=$E14,$D14,IF(P$2>P$257,0,IF($C14=P$2,"PAGAR"&" "&TEXT($B14," #.##0,00"),0))) -> 0 | Q14: =+IF(Q$2=$E14,$D14,IF(Q$2>Q$257,0,IF($C14=Q$2,"PAGAR"&" "&TEXT($B14," #.##0,00"),0))) -> 0 | ... AM14: =+IF(AM$2=$E14,$D14,IF(AM$2>AM$257,0,IF($C14=AM$2,"PAGAR"&" "&TEXT($B14," #.##0,00"),0))) -> 0 | AN14: =+IF(F14<0,-F14,0) -> 0 | AO14: =+IF(AND(C14=0,B14>0),B14,0) -> 0
A15: Apple.com - Cartão | B15: 29.9 | C15: 28 | F15: =+IF(TODAY()<DATEVALUE(1&D$1&E$1),0,IF(C15>0,IF(C15-SUM(I$255:AM$255)<0,B15-SUM(I15:AM15,0),0),0))+IF(C15=-1,B15-SUM(J15:AM15)) -> 0 | G15: =+IF(B15=0,"-",D15/B15) -> 0 | I15: =IF(I$2=$E15,$D15,IF(I$2>I$257,0,IF($C15=I$2,"PAGAR"&" "&TEXT($B15," #.##0,00"),IF($C15=-1,"PAGAR"&" "&TEXT($B15," #.##0,00"),0)))) -> 0 | J15: =+IF(J$2=$E15,$D15,IF(J$2>J$257,0,IF($C15=J$2,"PAGAR"&" "&TEXT($B15," #.##0,00"),0))) -> 0 | K15: =+IF(K$2=$E15,$D15,IF(K$2>K$257,0,IF($C15=K$2,"PAGAR"&" "&TEXT($B15," #.##0,00"),0))) -> 0 | L15: =+IF(L$2=$E15,$D15,IF(L$2>L$257,0,IF($C15=L$2,"PAGAR"&" "&TEXT($B15," #.##0,00"),0))) -> 0 | M15: =+IF(M$2=$E15,$D15,IF(M$2>M$257,0,IF($C15=M$2,"PAGAR"&" "&TEXT($B15," #.##0,00"),0))) -> 0 | N15: =+IF(N$2=$E15,$D15,IF(N$2>N$257,0,IF($C15=N$2,"PAGAR"&" "&TEXT($B15," #.##0,00"),0))) -> 0 | O15: =+IF(O$2=$E15,$D15,IF(O$2>O$257,0,IF($C15=O$2,"PAGAR"&" "&TEXT($B15," #.##0,00"),0))) -> 0 | P15: =+IF(P$2=$E15,$D15,IF(P$2>P$257,0,IF($C15=P$2,"PAGAR"&" "&TEXT($B15," #.##0,00"),0))) -> 0 | Q15: =+IF(Q$2=$E15,$D15,IF(Q$2>Q$257,0,IF($C15=Q$2,"PAGAR"&" "&TEXT($B15," #.##0,00"),0))) -> 0 | ... AM15: =+IF(AM$2=$E15,$D15,IF(AM$2>AM$257,0,IF($C15=AM$2,"PAGAR"&" "&TEXT($B15," #.##0,00"),0))) -> 0 | AN15: =+IF(F15<0,-F15,0) -> 0 | AO15: =+IF(AND(C15=0,B15>0),B15,0) -> 0 | AQ15: =+P2 -> 8 | AS15: =+Q2 -> 9 | AU15: =+R2 -> 10 | AW15: =+S2 -> 11 | AY15: =+T2 -> 12 | BA15: =+U2 -> 13 | BC15: =+V2 -> 14
A16: Apple.com - Cartão | B16: 5.9 | C16: 5 | F16: =+IF(TODAY()<DATEVALUE(1&D$1&E$1),0,IF(C16>0,IF(C16-SUM(I$255:AM$255)<0,B16-SUM(I16:AM16,0),0),0))+IF(C16=-1,B16-SUM(J16:AM16)) -> 5.9 | G16: =+IF(B16=0,"-",D16/B16) -> 0 | I16: =IF(I$2=$E16,$D16,IF(I$2>I$257,0,IF($C16=I$2,"PAGAR"&" "&TEXT($B16," #.##0,00"),IF($C16=-1,"PAGAR"&" "&TEXT($B16," #.##0,00"),0)))) -> 0 | J16: =+IF(J$2=$E16,$D16,IF(J$2>J$257,0,IF($C16=J$2,"PAGAR"&" "&TEXT($B16," #.##0,00"),0))) -> 0 | K16: =+IF(K$2=$E16,$D16,IF(K$2>K$257,0,IF($C16=K$2,"PAGAR"&" "&TEXT($B16," #.##0,00"),0))) -> 0 | L16: =+IF(L$2=$E16,$D16,IF(L$2>L$257,0,IF($C16=L$2,"PAGAR"&" "&TEXT($B16," #.##0,00"),0))) -> 0 | M16: =+IF(M$2=$E16,$D16,IF(M$2>M$257,0,IF($C16=M$2,"PAGAR"&" "&TEXT($B16," #.##0,00"),0))) -> PAGAR 5,90 | N16: =+IF(N$2=$E16,$D16,IF(N$2>N$257,0,IF($C16=N$2,"PAGAR"&" "&TEXT($B16," #.##0,00"),0))) -> 0 | O16: =+IF(O$2=$E16,$D16,IF(O$2>O$257,0,IF($C16=O$2,"PAGAR"&" "&TEXT($B16," #.##0,00"),0))) -> 0 | P16: =+IF(P$2=$E16,$D16,IF(P$2>P$257,0,IF($C16=P$2,"PAGAR"&" "&TEXT($B16," #.##0,00"),0))) -> 0 | Q16: =+IF(Q$2=$E16,$D16,IF(Q$2>Q$257,0,IF($C16=Q$2,"PAGAR"&" "&TEXT($B16," #.##0,00"),0))) -> 0 | ... AM16: =+IF(AM$2=$E16,$D16,IF(AM$2>AM$257,0,IF($C16=AM$2,"PAGAR"&" "&TEXT($B16," #.##0,00"),0))) -> 0 | AN16: =+IF(F16<0,-F16,0) -> 0 | AO16: =+IF(AND(C16=0,B16>0),B16,0) -> 0 | AQ16: {=_xlfn._xlws.FILTER($A5:$A152,$C5:$C152=AQ15,"livre")} -> 5asec (22/22 parcelas) | AR16: {=_xlfn._xlws.FILTER($B5:$B152,$C5:$C152=AQ15,"livre")} -> 10606.05 | AS16: {=_xlfn._xlws.FILTER($A5:$A152,$C5:$C152=AS15,"livre")} -> ACGDES Barão | AT16: {=_xlfn._xlws.FILTER($B5:$B152,$C5:$C152=AS15,"livre")} -> 931.52 | AU16: {=_xlfn._xlws.FILTER($A5:$A152,$C5:$C152=AU15,"livre")} -> Condomínio Reserva (Nelson58@) | AV16: {=_xlfn._xlws.FILTER($B5:$B152,$C5:$C152=AU15,"livre")} -> 1504.62 | AW16: {=_xlfn._xlws.FILTER($A5:$A152,$C5:$C152=AW15,"livre")} -> Escritório Aluguel | AX16: {=_xlfn._xlws.FILTER($B5:$B152,$C5:$C152=AW15,"livre")} -> 2945.42 | AY16: {=_xlfn._xlws.FILTER($A5:$A152,$C5:$C152=AY15,"livre")} -> CPFL Reserva | AZ16: {=_xlfn._xlws.FILTER($B5:$B152,$C5:$C152=AY15,"livre")} -> 159.64 | BA16: {=_xlfn._xlws.FILTER($A5:$A152,$C5:$C152=BA15,"livre")} -> ACGDES Sunset | BB16: {=_xlfn._xlws.FILTER($B5:$B152,$C5:$C152=BA15,"livre")} -> 2221.74 | BC16: {=_xlfn._xlws.FILTER($A5:$A152,$C5:$C152=BC15,"livre")} -> livre | BD16: {=_xlfn._xlws.FILTER($B5:$B152,$C5:$C152=BC15,"livre")} -> livre
A17: Google Adobe - Cartão | B17: 22.99 | C17: 4 | F17: =+IF(TODAY()<DATEVALUE(1&D$1&E$1),0,IF(C17>0,IF(C17-SUM(I$255:AM$255)<0,B17-SUM(I17:AM17,0),0),0))+IF(C17=-1,B17-SUM(J17:AM17)) -> 22.99 | G17: =+IF(B17=0,"-",D17/B17) -> 0 | I17: =IF(I$2=$E17,$D17,IF(I$2>I$257,0,IF($C17=I$2,"PAGAR"&" "&TEXT($B17," #.##0,00"),IF($C17=-1,"PAGAR"&" "&TEXT($B17," #.##0,00"),0)))) -> 0 | J17: =+IF(J$2=$E17,$D17,IF(J$2>J$257,0,IF($C17=J$2,"PAGAR"&" "&TEXT($B17," #.##0,00"),0))) -> 0 | K17: =+IF(K$2=$E17,$D17,IF(K$2>K$257,0,IF($C17=K$2,"PAGAR"&" "&TEXT($B17," #.##0,00"),0))) -> 0 | L17: =+IF(L$2=$E17,$D17,IF(L$2>L$257,0,IF($C17=L$2,"PAGAR"&" "&TEXT($B17," #.##0,00"),0))) -> PAGAR 22,99 | M17: =+IF(M$2=$E17,$D17,IF(M$2>M$257,0,IF($C17=M$2,"PAGAR"&" "&TEXT($B17," #.##0,00"),0))) -> 0 | N17: =+IF(N$2=$E17,$D17,IF(N$2>N$257,0,IF($C17=N$2,"PAGAR"&" "&TEXT($B17," #.##0,00"),0))) -> 0 | O17: =+IF(O$2=$E17,$D17,IF(O$2>O$257,0,IF($C17=O$2,"PAGAR"&" "&TEXT($B17," #.##0,00"),0))) -> 0 | P17: =+IF(P$2=$E17,$D17,IF(P$2>P$257,0,IF($C17=P$2,"PAGAR"&" "&TEXT($B17," #.##0,00"),0))) -> 0 | Q17: =+IF(Q$2=$E17,$D17,IF(Q$2>Q$257,0,IF($C17=Q$2,"PAGAR"&" "&TEXT($B17," #.##0,00"),0))) -> 0 | ... AM17: =+IF(AM$2=$E17,$D17,IF(AM$2>AM$257,0,IF($C17=AM$2,"PAGAR"&" "&TEXT($B17," #.##0,00"),0))) -> 0 | AN17: =+IF(F17<0,-F17,0) -> 0 | AO17: =+IF(AND(C17=0,B17>0),B17,0) -> 0 | AS17: CPFL Barão | AT17: 8042.83 | AU17: Fernando | AV17: 1081 | AW17: 5asec advogados (22/22parcelas) | AX17: 3030.3 | AY17: Frees + R$400 Josiane | AZ17: 6900 | BA17: CPFL Sunset | BB17: 596.7
A18: Microsoft Office - Cartão | B18: 60 | C18: 3 | F18: =+IF(TODAY()<DATEVALUE(1&D$1&E$1),0,IF(C18>0,IF(C18-SUM(I$255:AM$255)<0,B18-SUM(I18:AM18,0),0),0))+IF(C18=-1,B18-SUM(J18:AM18)) -> 60 | G18: =+IF(B18=0,"-",D18/B18) -> 0 | I18: =IF(I$2=$E18,$D18,IF(I$2>I$257,0,IF($C18=I$2,"PAGAR"&" "&TEXT($B18," #.##0,00"),IF($C18=-1,"PAGAR"&" "&TEXT($B18," #.##0,00"),0)))) -> 0 | J18: =+IF(J$2=$E18,$D18,IF(J$2>J$257,0,IF($C18=J$2,"PAGAR"&" "&TEXT($B18," #.##0,00"),0))) -> 0 | K18: =+IF(K$2=$E18,$D18,IF(K$2>K$257,0,IF($C18=K$2,"PAGAR"&" "&TEXT($B18," #.##0,00"),0))) -> PAGAR 60,00 | L18: =+IF(L$2=$E18,$D18,IF(L$2>L$257,0,IF($C18=L$2,"PAGAR"&" "&TEXT($B18," #.##0,00"),0))) -> 0 | M18: =+IF(M$2=$E18,$D18,IF(M$2>M$257,0,IF($C18=M$2,"PAGAR"&" "&TEXT($B18," #.##0,00"),0))) -> 0 | N18: =+IF(N$2=$E18,$D18,IF(N$2>N$257,0,IF($C18=N$2,"PAGAR"&" "&TEXT($B18," #.##0,00"),0))) -> 0 | O18: =+IF(O$2=$E18,$D18,IF(O$2>O$257,0,IF($C18=O$2,"PAGAR"&" "&TEXT($B18," #.##0,00"),0))) -> 0 | P18: =+IF(P$2=$E18,$D18,IF(P$2>P$257,0,IF($C18=P$2,"PAGAR"&" "&TEXT($B18," #.##0,00"),0))) -> 0 | Q18: =+IF(Q$2=$E18,$D18,IF(Q$2>Q$257,0,IF($C18=Q$2,"PAGAR"&" "&TEXT($B18," #.##0,00"),0))) -> 0 | ... AM18: =+IF(AM$2=$E18,$D18,IF(AM$2>AM$257,0,IF($C18=AM$2,"PAGAR"&" "&TEXT($B18," #.##0,00"),0))) -> 0 | AN18: =+IF(F18<0,-F18,0) -> 0 | AO18: =+IF(AND(C18=0,B18>0),B18,0) -> 0 | AW18: Sunset Aluguel | AX18: 3624
F19: =+IF(TODAY()<DATEVALUE(1&D$1&E$1),0,IF(C19>0,IF(C19-SUM(I$255:AM$255)<0,B19-SUM(I19:AM19,0),0),0))+IF(C19=-1,B19-SUM(J19:AM19)) -> 0 | G19: =+IF(B19=0,"-",D19/B19) -> - | I19: =IF(I$2=$E19,$D19,IF(I$2>I$257,0,IF($C19=I$2,"PAGAR"&" "&TEXT($B19," #.##0,00"),IF($C19=-1,"PAGAR"&" "&TEXT($B19," #.##0,00"),0)))) -> 0 | J19: =+IF(J$2=$E19,$D19,IF(J$2>J$257,0,IF($C19=J$2,"PAGAR"&" "&TEXT($B19," #.##0,00"),0))) -> 0 | K19: =+IF(K$2=$E19,$D19,IF(K$2>K$257,0,IF($C19=K$2,"PAGAR"&" "&TEXT($B19," #.##0,00"),0))) -> 0 | L19: =+IF(L$2=$E19,$D19,IF(L$2>L$257,0,IF($C19=L$2,"PAGAR"&" "&TEXT($B19," #.##0,00"),0))) -> 0 | M19: =+IF(M$2=$E19,$D19,IF(M$2>M$257,0,IF($C19=M$2,"PAGAR"&" "&TEXT($B19," #.##0,00"),0))) -> 0 | N19: =+IF(N$2=$E19,$D19,IF(N$2>N$257,0,IF($C19=N$2,"PAGAR"&" "&TEXT($B19," #.##0,00"),0))) -> 0 | O19: =+IF(O$2=$E19,$D19,IF(O$2>O$257,0,IF($C19=O$2,"PAGAR"&" "&TEXT($B19," #.##0,00"),0))) -> 0 | P19: =+IF(P$2=$E19,$D19,IF(P$2>P$257,0,IF($C19=P$2,"PAGAR"&" "&TEXT($B19," #.##0,00"),0))) -> 0 | Q19: =+IF(Q$2=$E19,$D19,IF(Q$2>Q$257,0,IF($C19=Q$2,"PAGAR"&" "&TEXT($B19," #.##0,00"),0))) -> 0 | ... AM19: =+IF(AM$2=$E19,$D19,IF(AM$2>AM$257,0,IF($C19=AM$2,"PAGAR"&" "&TEXT($B19," #.##0,00"),0))) -> 0 | AN19: =+IF(F19<0,-F19,0) -> 0 | AO19: =+IF(AND(C19=0,B19>0),B19,0) -> 0
F20: =+IF(TODAY()<DATEVALUE(1&D$1&E$1),0,IF(C20>0,IF(C20-SUM(I$255:AM$255)<0,B20-SUM(I20:AM20,0),0),0))+IF(C20=-1,B20-SUM(J20:AM20)) -> 0 | G20: =+IF(B20=0,"-",D20/B20) -> - | I20: =IF(I$2=$E20,$D20,IF(I$2>I$257,0,IF($C20=I$2,"PAGAR"&" "&TEXT($B20," #.##0,00"),IF($C20=-1,"PAGAR"&" "&TEXT($B20," #.##0,00"),0)))) -> 0 | J20: =+IF(J$2=$E20,$D20,IF(J$2>J$257,0,IF($C20=J$2,"PAGAR"&" "&TEXT($B20," #.##0,00"),0))) -> 0 | K20: =+IF(K$2=$E20,$D20,IF(K$2>K$257,0,IF($C20=K$2,"PAGAR"&" "&TEXT($B20," #.##0,00"),0))) -> 0 | L20: =+IF(L$2=$E20,$D20,IF(L$2>L$257,0,IF($C20=L$2,"PAGAR"&" "&TEXT($B20," #.##0,00"),0))) -> 0 | M20: =+IF(M$2=$E20,$D20,IF(M$2>M$257,0,IF($C20=M$2,"PAGAR"&" "&TEXT($B20," #.##0,00"),0))) -> 0 | N20: =+IF(N$2=$E20,$D20,IF(N$2>N$257,0,IF($C20=N$2,"PAGAR"&" "&TEXT($B20," #.##0,00"),0))) -> 0 | O20: =+IF(O$2=$E20,$D20,IF(O$2>O$257,0,IF($C20=O$2,"PAGAR"&" "&TEXT($B20," #.##0,00"),0))) -> 0 | P20: =+IF(P$2=$E20,$D20,IF(P$2>P$257,0,IF($C20=P$2,"PAGAR"&" "&TEXT($B20," #.##0,00"),0))) -> 0 | Q20: =+IF(Q$2=$E20,$D20,IF(Q$2>Q$257,0,IF($C20=Q$2,"PAGAR"&" "&TEXT($B20," #.##0,00"),0))) -> 0 | ... AM20: =+IF(AM$2=$E20,$D20,IF(AM$2>AM$257,0,IF($C20=AM$2,"PAGAR"&" "&TEXT($B20," #.##0,00"),0))) -> 0 | AN20: =+IF(F20<0,-F20,0) -> 0 | AO20: =+IF(AND(C20=0,B20>0),B20,0) -> 0
F21: =+IF(TODAY()<DATEVALUE(1&D$1&E$1),0,IF(C21>0,IF(C21-SUM(I$255:AM$255)<0,B21-SUM(I21:AM21,0),0),0))+IF(C21=-1,B21-SUM(J21:AM21)) -> 0 | G21: =+IF(B21=0,"-",D21/B21) -> - | I21: =IF(I$2=$E21,$D21,IF(I$2>I$257,0,IF($C21=I$2,"PAGAR"&" "&TEXT($B21," #.##0,00"),IF($C21=-1,"PAGAR"&" "&TEXT($B21," #.##0,00"),0)))) -> 0 | J21: =+IF(J$2=$E21,$D21,IF(J$2>J$257,0,IF($C21=J$2,"PAGAR"&" "&TEXT($B21," #.##0,00"),0))) -> 0 | K21: =+IF(K$2=$E21,$D21,IF(K$2>K$257,0,IF($C21=K$2,"PAGAR"&" "&TEXT($B21," #.##0,00"),0))) -> 0 | L21: =+IF(L$2=$E21,$D21,IF(L$2>L$257,0,IF($C21=L$2,"PAGAR"&" "&TEXT($B21," #.##0,00"),0))) -> 0 | M21: =+IF(M$2=$E21,$D21,IF(M$2>M$257,0,IF($C21=M$2,"PAGAR"&" "&TEXT($B21," #.##0,00"),0))) -> 0 | N21: =+IF(N$2=$E21,$D21,IF(N$2>N$257,0,IF($C21=N$2,"PAGAR"&" "&TEXT($B21," #.##0,00"),0))) -> 0 | O21: =+IF(O$2=$E21,$D21,IF(O$2>O$257,0,IF($C21=O$2,"PAGAR"&" "&TEXT($B21," #.##0,00"),0))) -> 0 | P21: =+IF(P$2=$E21,$D21,IF(P$2>P$257,0,IF($C21=P$2,"PAGAR"&" "&TEXT($B21," #.##0,00"),0))) -> 0 | Q21: =+IF(Q$2=$E21,$D21,IF(Q$2>Q$257,0,IF($C21=Q$2,"PAGAR"&" "&TEXT($B21," #.##0,00"),0))) -> 0 | ... AM21: =+IF(AM$2=$E21,$D21,IF(AM$2>AM$257,0,IF($C21=AM$2,"PAGAR"&" "&TEXT($B21," #.##0,00"),0))) -> 0 | AN21: =+IF(F21<0,-F21,0) -> 0 | AO21: =+IF(AND(C21=0,B21>0),B21,0) -> 0
F22: =+IF(TODAY()<DATEVALUE(1&D$1&E$1),0,IF(C22>0,IF(C22-SUM(I$255:AM$255)<0,B22-SUM(I22:AM22,0),0),0))+IF(C22=-1,B22-SUM(J22:AM22)) -> 0 | G22: =+IF(B22=0,"-",D22/B22) -> - | I22: =IF(I$2=$E22,$D22,IF(I$2>I$257,0,IF($C22=I$2,"PAGAR"&" "&TEXT($B22," #.##0,00"),IF($C22=-1,"PAGAR"&" "&TEXT($B22," #.##0,00"),0)))) -> 0 | J22: =+IF(J$2=$E22,$D22,IF(J$2>J$257,0,IF($C22=J$2,"PAGAR"&" "&TEXT($B22," #.##0,00"),0))) -> 0 | K22: =+IF(K$2=$E22,$D22,IF(K$2>K$257,0,IF($C22=K$2,"PAGAR"&" "&TEXT($B22," #.##0,00"),0))) -> 0 | L22: =+IF(L$2=$E22,$D22,IF(L$2>L$257,0,IF($C22=L$2,"PAGAR"&" "&TEXT($B22," #.##0,00"),0))) -> 0 | M22: =+IF(M$2=$E22,$D22,IF(M$2>M$257,0,IF($C22=M$2,"PAGAR"&" "&TEXT($B22," #.##0,00"),0))) -> 0 | N22: =+IF(N$2=$E22,$D22,IF(N$2>N$257,0,IF($C22=N$2,"PAGAR"&" "&TEXT($B22," #.##0,00"),0))) -> 0 | O22: =+IF(O$2=$E22,$D22,IF(O$2>O$257,0,IF($C22=O$2,"PAGAR"&" "&TEXT($B22," #.##0,00"),0))) -> 0 | P22: =+IF(P$2=$E22,$D22,IF(P$2>P$257,0,IF($C22=P$2,"PAGAR"&" "&TEXT($B22," #.##0,00"),0))) -> 0 | Q22: =+IF(Q$2=$E22,$D22,IF(Q$2>Q$257,0,IF($C22=Q$2,"PAGAR"&" "&TEXT($B22," #.##0,00"),0))) -> 0 | ... AM22: =+IF(AM$2=$E22,$D22,IF(AM$2>AM$257,0,IF($C22=AM$2,"PAGAR"&" "&TEXT($B22," #.##0,00"),0))) -> 0 | AN22: =+IF(F22<0,-F22,0) -> 0 | AO22: =+IF(AND(C22=0,B22>0),B22,0) -> 0
F23: =+IF(TODAY()<DATEVALUE(1&D$1&E$1),0,IF(C23>0,IF(C23-SUM(I$255:AM$255)<0,B23-SUM(I23:AM23,0),0),0))+IF(C23=-1,B23-SUM(J23:AM23)) -> 0 | G23: =+IF(B23=0,"-",D23/B23) -> - | I23: =IF(I$2=$E23,$D23,IF(I$2>I$257,0,IF($C23=I$2,"PAGAR"&" "&TEXT($B23," #.##0,00"),IF($C23=-1,"PAGAR"&" "&TEXT($B23," #.##0,00"),0)))) -> 0 | J23: =+IF(J$2=$E23,$D23,IF(J$2>J$257,0,IF($C23=J$2,"PAGAR"&" "&TEXT($B23," #.##0,00"),0))) -> 0 | K23: =+IF(K$2=$E23,$D23,IF(K$2>K$257,0,IF($C23=K$2,"PAGAR"&" "&TEXT($B23," #.##0,00"),0))) -> 0 | L23: =+IF(L$2=$E23,$D23,IF(L$2>L$257,0,IF($C23=L$2,"PAGAR"&" "&TEXT($B23," #.##0,00"),0))) -> 0 | M23: =+IF(M$2=$E23,$D23,IF(M$2>M$257,0,IF($C23=M$2,"PAGAR"&" "&TEXT($B23," #.##0,00"),0))) -> 0 | N23: =+IF(N$2=$E23,$D23,IF(N$2>N$257,0,IF($C23=N$2,"PAGAR"&" "&TEXT($B23," #.##0,00"),0))) -> 0 | O23: =+IF(O$2=$E23,$D23,IF(O$2>O$257,0,IF($C23=O$2,"PAGAR"&" "&TEXT($B23," #.##0,00"),0))) -> 0 | P23: =+IF(P$2=$E23,$D23,IF(P$2>P$257,0,IF($C23=P$2,"PAGAR"&" "&TEXT($B23," #.##0,00"),0))) -> 0 | Q23: =+IF(Q$2=$E23,$D23,IF(Q$2>Q$257,0,IF($C23=Q$2,"PAGAR"&" "&TEXT($B23," #.##0,00"),0))) -> 0 | ... AM23: =+IF(AM$2=$E23,$D23,IF(AM$2>AM$257,0,IF($C23=AM$2,"PAGAR"&" "&TEXT($B23," #.##0,00"),0))) -> 0 | AN23: =+IF(F23<0,-F23,0) -> 0 | AO23: =+IF(AND(C23=0,B23>0),B23,0) -> 0
F24: =+IF(TODAY()<DATEVALUE(1&D$1&E$1),0,IF(C24>0,IF(C24-SUM(I$255:AM$255)<0,B24-SUM(I24:AM24,0),0),0))+IF(C24=-1,B24-SUM(J24:AM24)) -> 0 | G24: =+IF(B24=0,"-",D24/B24) -> - | I24: =IF(I$2=$E24,$D24,IF(I$2>I$257,0,IF($C24=I$2,"PAGAR"&" "&TEXT($B24," #.##0,00"),IF($C24=-1,"PAGAR"&" "&TEXT($B24," #.##0,00"),0)))) -> 0 | J24: =+IF(J$2=$E24,$D24,IF(J$2>J$257,0,IF($C24=J$2,"PAGAR"&" "&TEXT($B24," #.##0,00"),0))) -> 0 | K24: =+IF(K$2=$E24,$D24,IF(K$2>K$257,0,IF($C24=K$2,"PAGAR"&" "&TEXT($B24," #.##0,00"),0))) -> 0 | L24: =+IF(L$2=$E24,$D24,IF(L$2>L$257,0,IF($C24=L$2,"PAGAR"&" "&TEXT($B24," #.##0,00"),0))) -> 0 | M24: =+IF(M$2=$E24,$D24,IF(M$2>M$257,0,IF($C24=M$2,"PAGAR"&" "&TEXT($B24," #.##0,00"),0))) -> 0 | N24: =+IF(N$2=$E24,$D24,IF(N$2>N$257,0,IF($C24=N$2,"PAGAR"&" "&TEXT($B24," #.##0,00"),0))) -> 0 | O24: =+IF(O$2=$E24,$D24,IF(O$2>O$257,0,IF($C24=O$2,"PAGAR"&" "&TEXT($B24," #.##0,00"),0))) -> 0 | P24: =+IF(P$2=$E24,$D24,IF(P$2>P$257,0,IF($C24=P$2,"PAGAR"&" "&TEXT($B24," #.##0,00"),0))) -> 0 | Q24: =+IF(Q$2=$E24,$D24,IF(Q$2>Q$257,0,IF($C24=Q$2,"PAGAR"&" "&TEXT($B24," #.##0,00"),0))) -> 0 | ... AM24: =+IF(AM$2=$E24,$D24,IF(AM$2>AM$257,0,IF($C24=AM$2,"PAGAR"&" "&TEXT($B24," #.##0,00"),0))) -> 0 | AN24: =+IF(F24<0,-F24,0) -> 0 | AO24: =+IF(AND(C24=0,B24>0),B24,0) -> 0
F25: =+IF(TODAY()<DATEVALUE(1&D$1&E$1),0,IF(C25>0,IF(C25-SUM(I$255:AM$255)<0,B25-SUM(I25:AM25,0),0),0))+IF(C25=-1,B25-SUM(J25:AM25)) -> 0 | G25: =+IF(B25=0,"-",D25/B25) -> - | I25: =IF(I$2=$E25,$D25,IF(I$2>I$257,0,IF($C25=I$2,"PAGAR"&" "&TEXT($B25," #.##0,00"),IF($C25=-1,"PAGAR"&" "&TEXT($B25," #.##0,00"),0)))) -> 0 | J25: =+IF(J$2=$E25,$D25,IF(J$2>J$257,0,IF($C25=J$2,"PAGAR"&" "&TEXT($B25," #.##0,00"),0))) -> 0 | K25: =+IF(K$2=$E25,$D25,IF(K$2>K$257,0,IF($C25=K$2,"PAGAR"&" "&TEXT($B25," #.##0,00"),0))) -> 0 | L25: =+IF(L$2=$E25,$D25,IF(L$2>L$257,0,IF($C25=L$2,"PAGAR"&" "&TEXT($B25," #.##0,00"),0))) -> 0 | M25: =+IF(M$2=$E25,$D25,IF(M$2>M$257,0,IF($C25=M$2,"PAGAR"&" "&TEXT($B25," #.##0,00"),0))) -> 0 | N25: =+IF(N$2=$E25,$D25,IF(N$2>N$257,0,IF($C25=N$2,"PAGAR"&" "&TEXT($B25," #.##0,00"),0))) -> 0 | O25: =+IF(O$2=$E25,$D25,IF(O$2>O$257,0,IF($C25=O$2,"PAGAR"&" "&TEXT($B25," #.##0,00"),0))) -> 0 | P25: =+IF(P$2=$E25,$D25,IF(P$2>P$257,0,IF($C25=P$2,"PAGAR"&" "&TEXT($B25," #.##0,00"),0))) -> 0 | Q25: =+IF(Q$2=$E25,$D25,IF(Q$2>Q$257,0,IF($C25=Q$2,"PAGAR"&" "&TEXT($B25," #.##0,00"),0))) -> 0 | ... AM25: =+IF(AM$2=$E25,$D25,IF(AM$2>AM$257,0,IF($C25=AM$2,"PAGAR"&" "&TEXT($B25," #.##0,00"),0))) -> 0 | AN25: =+IF(F25<0,-F25,0) -> 0 | AO25: =+IF(AND(C25=0,B25>0),B25,0) -> 0
A26: Total de despesas previstas (Plan 2) | B26: =+SUM(B5:B25) -> 17706.7 | D26: =+SUM(D5:D25) -> 8190.14 | F26: =+SUMIF(F5:F25,">0") -> 6499.2 | G26: =+IF(B26=0,"-",D26/B26) -> 0.46254469 | I26: =+PLAN2!H27 -> 0 | J26: =+PLAN2!I27 -> 6650 | K26: =+PLAN2!J27 -> 65.9 | L26: =+PLAN2!K27 -> 22.99 | M26: =+PLAN2!L27 -> 5.9 | N26: =+PLAN2!M27 -> 0 | O26: =+PLAN2!N27 -> 6404.41 | P26: =+PLAN2!O27 -> 0 | ... AM26: =+PLAN2!AL27 -> 0 | AN26: =SUM(AN5:AN25) -> 0 | AQ26: =+W2 -> 15 | AS26: =+X2 -> 16 | AU26: =+Y2 -> 17 | AW26: =+Z2 -> 18 | AY26: =+AA2 -> 19 | BA26: =+AB2 -> 20 | BC26: =+AC2 -> 21
A27: EXTRA EMPRESA | AQ27: {=_xlfn._xlws.FILTER($A$5:$A$152,$C$5:$C$152=AQ26,"livre")} -> Cristiane | AR27: {=_xlfn._xlws.FILTER($B$5:$B$152,$C$5:$C$152=AQ26,"livre")} -> 940 | AS27: {=_xlfn._xlws.FILTER($A$5:$A$152,$C$5:$C$152=AS26,"livre")} -> livre | AT27: {=_xlfn._xlws.FILTER($B$5:$B$152,$C$5:$C$152=AS26,"livre")} -> livre | AU27: {=_xlfn._xlws.FILTER($A$5:$A$152,$C$5:$C$152=AU26,"livre")} -> Convênio Tina | AV27: {=_xlfn._xlws.FILTER($B$5:$B$152,$C$5:$C$152=AU26,"livre")} -> 1010 | AW27: {=_xlfn._xlws.FILTER($A$5:$A$152,$C$5:$C$152=AW26,"livre")} -> livre | AX27: {=_xlfn._xlws.FILTER($B$5:$B$152,$C$5:$C$152=AW26,"livre")} -> livre | AY27: {=_xlfn._xlws.FILTER($A$5:$A$152,$C$5:$C$152=AY26,"livre")} -> Frees + R$400 Josiane | AZ27: {=_xlfn._xlws.FILTER($B$5:$B$152,$C$5:$C$152=AY26,"livre")} -> 6900 | BA27: {=_xlfn._xlws.FILTER($A$5:$A$152,$C$5:$C$152=BA26,"livre")} -> Francisca | BB27: {=_xlfn._xlws.FILTER($B$5:$B$152,$C$5:$C$152=BA26,"livre")} -> 720 | BC27: {=_xlfn._xlws.FILTER($A$5:$A$152,$C$5:$C$152=BC26,"livre")} -> livre | BD27: {=_xlfn._xlws.FILTER($B$5:$B$152,$C$5:$C$152=BC26,"livre")} -> livre
A28: Escritório Aluguel | B28: 2945.42 | C28: 11 | F28: =+IF(TODAY()<DATEVALUE(1&D$1&E$1),0,IF(C28>0,IF(C28-SUM(I$255:AM$255)<0,B28-SUM(I28:AM28,0),0),0))+IF(C28=-1,B28-SUM(J28:AM28)) -> 2945.42 | G28: =+IF(B28=0,"-",D28/B28) -> 0 | H28: =IF(H$2=$E28,$D28,IF(H$2>H$257,0,IF($C28=H$2,"PAGAR"&" "&TEXT($B28," #.##0,00"),IF($C28=-1,"PAGAR"&" "&TEXT($B28," #.##0,00"),0)))) -> 0 | I28: =IF(I$2=$E28,$D28,IF(I$2>I$257,0,IF($C28=I$2,"PAGAR"&" "&TEXT($B28," #.##0,00"),IF($C28=-1,"PAGAR"&" "&TEXT($B28," #.##0,00"),0)))) -> 0 | J28: =+IF(J$2=$E28,$D28,IF(J$2>J$257,0,IF($C28=J$2,"PAGAR"&" "&TEXT($B28," #.##0,00"),0))) -> 0 | K28: =+IF(K$2=$E28,$D28,IF(K$2>K$257,0,IF($C28=K$2,"PAGAR"&" "&TEXT($B28," #.##0,00"),0))) -> 0 | L28: =+IF(L$2=$E28,$D28,IF(L$2>L$257,0,IF($C28=L$2,"PAGAR"&" "&TEXT($B28," #.##0,00"),0))) -> 0 | M28: =+IF(M$2=$E28,$D28,IF(M$2>M$257,0,IF($C28=M$2,"PAGAR"&" "&TEXT($B28," #.##0,00"),0))) -> 0 | N28: =+IF(N$2=$E28,$D28,IF(N$2>N$257,0,IF($C28=N$2,"PAGAR"&" "&TEXT($B28," #.##0,00"),0))) -> 0 | O28: =+IF(O$2=$E28,$D28,IF(O$2>O$257,0,IF($C28=O$2,"PAGAR"&" "&TEXT($B28," #.##0,00"),0))) -> 0 | P28: =+IF(P$2=$E28,$D28,IF(P$2>P$257,0,IF($C28=P$2,"PAGAR"&" "&TEXT($B28," #.##0,00"),0))) -> 0 | Q28: =+IF(Q$2=$E28,$D28,IF(Q$2>Q$257,0,IF($C28=Q$2,"PAGAR"&" "&TEXT($B28," #.##0,00"),0))) -> 0 | ... AM28: =+IF(AM$2=$E28,$D28,IF(AM$2>AM$257,0,IF($C28=AM$2,"PAGAR"&" "&TEXT($B28," #.##0,00"),0))) -> 0 | AN28: =+IF(F28<0,-F28,0) -> 0 | AO28: =+IF(AND(C28=0,B28>0),B28,0) -> 0 | AQ28: Bônus Adriano | AR28: 500 | BA28: 4 Lock -- adiant | BB28: 12000
A29: Água Barão | B29: 2775 | C29: 26 | F29: =+IF(TODAY()<DATEVALUE(1&D$1&E$1),0,IF(C29>0,IF(C29-SUM(I$255:AM$255)<0,B29-SUM(I29:AM29,0),0),0))+IF(C29=-1,B29-SUM(J29:AM29)) -> 0 | G29: =+IF(B29=0,"-",D29/B29) -> 0 | H29: =IF(H$2=$E29,$D29,IF(H$2>H$257,0,IF($C29=H$2,"PAGAR"&" "&TEXT($B29," #.##0,00"),IF($C29=-1,"PAGAR"&" "&TEXT($B29," #.##0,00"),0)))) -> 0 | I29: =IF(I$2=$E29,$D29,IF(I$2>I$257,0,IF($C29=I$2,"PAGAR"&" "&TEXT($B29," #.##0,00"),IF($C29=-1,"PAGAR"&" "&TEXT($B29," #.##0,00"),0)))) -> 0 | J29: =+IF(J$2=$E29,$D29,IF(J$2>J$257,0,IF($C29=J$2,"PAGAR"&" "&TEXT($B29," #.##0,00"),0))) -> 0 | K29: =+IF(K$2=$E29,$D29,IF(K$2>K$257,0,IF($C29=K$2,"PAGAR"&" "&TEXT($B29," #.##0,00"),0))) -> 0 | L29: =+IF(L$2=$E29,$D29,IF(L$2>L$257,0,IF($C29=L$2,"PAGAR"&" "&TEXT($B29," #.##0,00"),0))) -> 0 | M29: =+IF(M$2=$E29,$D29,IF(M$2>M$257,0,IF($C29=M$2,"PAGAR"&" "&TEXT($B29," #.##0,00"),0))) -> 0 | N29: =+IF(N$2=$E29,$D29,IF(N$2>N$257,0,IF($C29=N$2,"PAGAR"&" "&TEXT($B29," #.##0,00"),0))) -> 0 | O29: =+IF(O$2=$E29,$D29,IF(O$2>O$257,0,IF($C29=O$2,"PAGAR"&" "&TEXT($B29," #.##0,00"),0))) -> 0 | P29: =+IF(P$2=$E29,$D29,IF(P$2>P$257,0,IF($C29=P$2,"PAGAR"&" "&TEXT($B29," #.##0,00"),0))) -> 0 | Q29: =+IF(Q$2=$E29,$D29,IF(Q$2>Q$257,0,IF($C29=Q$2,"PAGAR"&" "&TEXT($B29," #.##0,00"),0))) -> 0 | ... AM29: =+IF(AM$2=$E29,$D29,IF(AM$2>AM$257,0,IF($C29=AM$2,"PAGAR"&" "&TEXT($B29," #.##0,00"),0))) -> 0 | AN29: =+IF(F29<0,-F29,0) -> 0 | AO29: =+IF(AND(C29=0,B29>0),B29,0) -> 0 | AQ29: Bônus Tamara | AR29: 569 | BA29: Perfecto -- adiant | BB29: 1500 | BK29: =+AK2 -> 29 | BL29: =+AL2 -> 30
A30: Cristiane | B30: 940 | C30: 15 | F30: =+IF(TODAY()<DATEVALUE(1&D$1&E$1),0,IF(C30>0,IF(C30-SUM(I$255:AM$255)<0,B30-SUM(I30:AM30,0),0),0))+IF(C30=-1,B30-SUM(J30:AM30)) -> 0 | G30: =+IF(B30=0,"-",D30/B30) -> 0 | H30: =IF(H$2=$E30,$D30,IF(H$2>H$257,0,IF($C30=H$2,"PAGAR"&" "&TEXT($B30," #.##0,00"),IF($C30=-1,"PAGAR"&" "&TEXT($B30," #.##0,00"),0)))) -> 0 | I30: =IF(I$2=$E30,$D30,IF(I$2>I$257,0,IF($C30=I$2,"PAGAR"&" "&TEXT($B30," #.##0,00"),IF($C30=-1,"PAGAR"&" "&TEXT($B30," #.##0,00"),0)))) -> 0 | J30: =+IF(J$2=$E30,$D30,IF(J$2>J$257,0,IF($C30=J$2,"PAGAR"&" "&TEXT($B30," #.##0,00"),0))) -> 0 | K30: =+IF(K$2=$E30,$D30,IF(K$2>K$257,0,IF($C30=K$2,"PAGAR"&" "&TEXT($B30," #.##0,00"),0))) -> 0 | L30: =+IF(L$2=$E30,$D30,IF(L$2>L$257,0,IF($C30=L$2,"PAGAR"&" "&TEXT($B30," #.##0,00"),0))) -> 0 | M30: =+IF(M$2=$E30,$D30,IF(M$2>M$257,0,IF($C30=M$2,"PAGAR"&" "&TEXT($B30," #.##0,00"),0))) -> 0 | N30: =+IF(N$2=$E30,$D30,IF(N$2>N$257,0,IF($C30=N$2,"PAGAR"&" "&TEXT($B30," #.##0,00"),0))) -> 0 | O30: =+IF(O$2=$E30,$D30,IF(O$2>O$257,0,IF($C30=O$2,"PAGAR"&" "&TEXT($B30," #.##0,00"),0))) -> 0 | P30: =+IF(P$2=$E30,$D30,IF(P$2>P$257,0,IF($C30=P$2,"PAGAR"&" "&TEXT($B30," #.##0,00"),0))) -> 0 | Q30: =+IF(Q$2=$E30,$D30,IF(Q$2>Q$257,0,IF($C30=Q$2,"PAGAR"&" "&TEXT($B30," #.##0,00"),0))) -> 0 | ... AM30: =+IF(AM$2=$E30,$D30,IF(AM$2>AM$257,0,IF($C30=AM$2,"PAGAR"&" "&TEXT($B30," #.##0,00"),0))) -> 0 | AN30: =+IF(F30<0,-F30,0) -> 0 | AO30: =+IF(AND(C30=0,B30>0),B30,0) -> 0 | AQ30: VT | AR30: 500
A31: Cristiane | B31: 940 | C31: 30 | F31: =+IF(TODAY()<DATEVALUE(1&D$1&E$1),0,IF(C31>0,IF(C31-SUM(I$255:AM$255)<0,B31-SUM(I31:AM31,0),0),0))+IF(C31=-1,B31-SUM(J31:AM31)) -> 0 | G31: =+IF(B31=0,"-",D31/B31) -> 0 | H31: =IF(H$2=$E31,$D31,IF(H$2>H$257,0,IF($C31=H$2,"PAGAR"&" "&TEXT($B31," #.##0,00"),IF($C31=-1,"PAGAR"&" "&TEXT($B31," #.##0,00"),0)))) -> 0 | I31: =IF(I$2=$E31,$D31,IF(I$2>I$257,0,IF($C31=I$2,"PAGAR"&" "&TEXT($B31," #.##0,00"),IF($C31=-1,"PAGAR"&" "&TEXT($B31," #.##0,00"),0)))) -> 0 | J31: =+IF(J$2=$E31,$D31,IF(J$2>J$257,0,IF($C31=J$2,"PAGAR"&" "&TEXT($B31," #.##0,00"),0))) -> 0 | K31: =+IF(K$2=$E31,$D31,IF(K$2>K$257,0,IF($C31=K$2,"PAGAR"&" "&TEXT($B31," #.##0,00"),0))) -> 0 | L31: =+IF(L$2=$E31,$D31,IF(L$2>L$257,0,IF($C31=L$2,"PAGAR"&" "&TEXT($B31," #.##0,00"),0))) -> 0 | M31: =+IF(M$2=$E31,$D31,IF(M$2>M$257,0,IF($C31=M$2,"PAGAR"&" "&TEXT($B31," #.##0,00"),0))) -> 0 | N31: =+IF(N$2=$E31,$D31,IF(N$2>N$257,0,IF($C31=N$2,"PAGAR"&" "&TEXT($B31," #.##0,00"),0))) -> 0 | O31: =+IF(O$2=$E31,$D31,IF(O$2>O$257,0,IF($C31=O$2,"PAGAR"&" "&TEXT($B31," #.##0,00"),0))) -> 0 | P31: =+IF(P$2=$E31,$D31,IF(P$2>P$257,0,IF($C31=P$2,"PAGAR"&" "&TEXT($B31," #.##0,00"),0))) -> 0 | Q31: =+IF(Q$2=$E31,$D31,IF(Q$2>Q$257,0,IF($C31=Q$2,"PAGAR"&" "&TEXT($B31," #.##0,00"),0))) -> 0 | ... AM31: =+IF(AM$2=$E31,$D31,IF(AM$2>AM$257,0,IF($C31=AM$2,"PAGAR"&" "&TEXT($B31," #.##0,00"),0))) -> 0 | AN31: =+IF(F31<0,-F31,0) -> 0 | AO31: =+IF(AND(C31=0,B31>0),B31,0) -> 0 | AQ31: Naturgy - estimado | AR31: 220
A32: Francisca | B32: 1080 | C32: 6 | F32: =+IF(TODAY()<DATEVALUE(1&D$1&E$1),0,IF(C32>0,IF(C32-SUM(I$255:AM$255)<0,B32-SUM(I32:AM32,0),0),0))+IF(C32=-1,B32-SUM(J32:AM32)) -> 1080 | G32: =+IF(B32=0,"-",D32/B32) -> 0 | H32: =IF(H$2=$E32,$D32,IF(H$2>H$257,0,IF($C32=H$2,"PAGAR"&" "&TEXT($B32," #.##0,00"),IF($C32=-1,"PAGAR"&" "&TEXT($B32," #.##0,00"),0)))) -> 0 | I32: =IF(I$2=$E32,$D32,IF(I$2>I$257,0,IF($C32=I$2,"PAGAR"&" "&TEXT($B32," #.##0,00"),IF($C32=-1,"PAGAR"&" "&TEXT($B32," #.##0,00"),0)))) -> 0 | J32: =+IF(J$2=$E32,$D32,IF(J$2>J$257,0,IF($C32=J$2,"PAGAR"&" "&TEXT($B32," #.##0,00"),0))) -> 0 | K32: =+IF(K$2=$E32,$D32,IF(K$2>K$257,0,IF($C32=K$2,"PAGAR"&" "&TEXT($B32," #.##0,00"),0))) -> 0 | L32: =+IF(L$2=$E32,$D32,IF(L$2>L$257,0,IF($C32=L$2,"PAGAR"&" "&TEXT($B32," #.##0,00"),0))) -> 0 | M32: =+IF(M$2=$E32,$D32,IF(M$2>M$257,0,IF($C32=M$2,"PAGAR"&" "&TEXT($B32," #.##0,00"),0))) -> 0 | N32: =+IF(N$2=$E32,$D32,IF(N$2>N$257,0,IF($C32=N$2,"PAGAR"&" "&TEXT($B32," #.##0,00"),0))) -> PAGAR 1.080,00 | O32: =+IF(O$2=$E32,$D32,IF(O$2>O$257,0,IF($C32=O$2,"PAGAR"&" "&TEXT($B32," #.##0,00"),0))) -> 0 | P32: =+IF(P$2=$E32,$D32,IF(P$2>P$257,0,IF($C32=P$2,"PAGAR"&" "&TEXT($B32," #.##0,00"),0))) -> 0 | Q32: =+IF(Q$2=$E32,$D32,IF(Q$2>Q$257,0,IF($C32=Q$2,"PAGAR"&" "&TEXT($B32," #.##0,00"),0))) -> 0 | ... AM32: =+IF(AM$2=$E32,$D32,IF(AM$2>AM$257,0,IF($C32=AM$2,"PAGAR"&" "&TEXT($B32," #.##0,00"),0))) -> 0 | AN32: =+IF(F32<0,-F32,0) -> 0 | AO32: =+IF(AND(C32=0,B32>0),B32,0) -> 0 | AQ32: Letízio ?/36 | AR32: 2750
A33: Francisca | B33: 720 | C33: 20 | F33: =+IF(TODAY()<DATEVALUE(1&D$1&E$1),0,IF(C33>0,IF(C33-SUM(I$255:AM$255)<0,B33-SUM(I33:AM33,0),0),0))+IF(C33=-1,B33-SUM(J33:AM33)) -> 0 | G33: =+IF(B33=0,"-",D33/B33) -> 0 | H33: =IF(H$2=$E33,$D33,IF(H$2>H$257,0,IF($C33=H$2,"PAGAR"&" "&TEXT($B33," #.##0,00"),IF($C33=-1,"PAGAR"&" "&TEXT($B33," #.##0,00"),0)))) -> 0 | I33: =IF(I$2=$E33,$D33,IF(I$2>I$257,0,IF($C33=I$2,"PAGAR"&" "&TEXT($B33," #.##0,00"),IF($C33=-1,"PAGAR"&" "&TEXT($B33," #.##0,00"),0)))) -> 0 | J33: =+IF(J$2=$E33,$D33,IF(J$2>J$257,0,IF($C33=J$2,"PAGAR"&" "&TEXT($B33," #.##0,00"),0))) -> 0 | K33: =+IF(K$2=$E33,$D33,IF(K$2>K$257,0,IF($C33=K$2,"PAGAR"&" "&TEXT($B33," #.##0,00"),0))) -> 0 | L33: =+IF(L$2=$E33,$D33,IF(L$2>L$257,0,IF($C33=L$2,"PAGAR"&" "&TEXT($B33," #.##0,00"),0))) -> 0 | M33: =+IF(M$2=$E33,$D33,IF(M$2>M$257,0,IF($C33=M$2,"PAGAR"&" "&TEXT($B33," #.##0,00"),0))) -> 0 | N33: =+IF(N$2=$E33,$D33,IF(N$2>N$257,0,IF($C33=N$2,"PAGAR"&" "&TEXT($B33," #.##0,00"),0))) -> 0 | O33: =+IF(O$2=$E33,$D33,IF(O$2>O$257,0,IF($C33=O$2,"PAGAR"&" "&TEXT($B33," #.##0,00"),0))) -> 0 | P33: =+IF(P$2=$E33,$D33,IF(P$2>P$257,0,IF($C33=P$2,"PAGAR"&" "&TEXT($B33," #.##0,00"),0))) -> 0 | Q33: =+IF(Q$2=$E33,$D33,IF(Q$2>Q$257,0,IF($C33=Q$2,"PAGAR"&" "&TEXT($B33," #.##0,00"),0))) -> 0 | ... AM33: =+IF(AM$2=$E33,$D33,IF(AM$2>AM$257,0,IF($C33=AM$2,"PAGAR"&" "&TEXT($B33," #.##0,00"),0))) -> 0 | AN33: =+IF(F33<0,-F33,0) -> 0 | AO33: =+IF(AND(C33=0,B33>0),B33,0) -> 0 | AQ33: Barão Aluguel | AR33: 4377.08
A34: Convênio Tina | B34: 1010 | C34: 17 | D34: 1010 | E34: 12 | F34: =+IF(TODAY()<DATEVALUE(1&D$1&E$1),0,IF(C34>0,IF(C34-SUM(I$255:AM$255)<0,B34-SUM(I34:AM34,0),0),0))+IF(C34=-1,B34-SUM(J34:AM34)) -> 0 | G34: =+IF(B34=0,"-",D34/B34) -> 1 | H34: =IF(H$2=$E34,$D34,IF(H$2>H$257,0,IF($C34=H$2,"PAGAR"&" "&TEXT($B34," #.##0,00"),IF($C34=-1,"PAGAR"&" "&TEXT($B34," #.##0,00"),0)))) -> 0 | I34: =IF(I$2=$E34,$D34,IF(I$2>I$257,0,IF($C34=I$2,"PAGAR"&" "&TEXT($B34," #.##0,00"),IF($C34=-1,"PAGAR"&" "&TEXT($B34," #.##0,00"),0)))) -> 0 | J34: =+IF(J$2=$E34,$D34,IF(J$2>J$257,0,IF($C34=J$2,"PAGAR"&" "&TEXT($B34," #.##0,00"),0))) -> 0 | K34: =+IF(K$2=$E34,$D34,IF(K$2>K$257,0,IF($C34=K$2,"PAGAR"&" "&TEXT($B34," #.##0,00"),0))) -> 0 | L34: =+IF(L$2=$E34,$D34,IF(L$2>L$257,0,IF($C34=L$2,"PAGAR"&" "&TEXT($B34," #.##0,00"),0))) -> 0 | M34: =+IF(M$2=$E34,$D34,IF(M$2>M$257,0,IF($C34=M$2,"PAGAR"&" "&TEXT($B34," #.##0,00"),0))) -> 0 | N34: =+IF(N$2=$E34,$D34,IF(N$2>N$257,0,IF($C34=N$2,"PAGAR"&" "&TEXT($B34," #.##0,00"),0))) -> 0 | O34: =+IF(O$2=$E34,$D34,IF(O$2>O$257,0,IF($C34=O$2,"PAGAR"&" "&TEXT($B34," #.##0,00"),0))) -> 0 | P34: =+IF(P$2=$E34,$D34,IF(P$2>P$257,0,IF($C34=P$2,"PAGAR"&" "&TEXT($B34," #.##0,00"),0))) -> 0 | Q34: =+IF(Q$2=$E34,$D34,IF(Q$2>Q$257,0,IF($C34=Q$2,"PAGAR"&" "&TEXT($B34," #.##0,00"),0))) -> 0 | ... AM34: =+IF(AM$2=$E34,$D34,IF(AM$2>AM$257,0,IF($C34=AM$2,"PAGAR"&" "&TEXT($B34," #.##0,00"),0))) -> 0 | AN34: =+IF(F34<0,-F34,0) -> 0 | AO34: =+IF(AND(C34=0,B34>0),B34,0) -> 0 | AQ34: Boa Vista Aluguel | AR34: 3450
A35: Bônus Adriano | B35: 500 | C35: 15 | F35: =+IF(TODAY()<DATEVALUE(1&D$1&E$1),0,IF(C35>0,IF(C35-SUM(I$255:AM$255)<0,B35-SUM(I35:AM35,0),0),0))+IF(C35=-1,B35-SUM(J35:AM35)) -> 0 | G35: =+IF(B35=0,"-",D35/B35) -> 0 | H35: =IF(H$2=$E35,$D35,IF(H$2>H$257,0,IF($C35=H$2,"PAGAR"&" "&TEXT($B35," #.##0,00"),IF($C35=-1,"PAGAR"&" "&TEXT($B35," #.##0,00"),0)))) -> 0 | I35: =IF(I$2=$E35,$D35,IF(I$2>I$257,0,IF($C35=I$2,"PAGAR"&" "&TEXT($B35," #.##0,00"),IF($C35=-1,"PAGAR"&" "&TEXT($B35," #.##0,00"),0)))) -> 0 | J35: =+IF(J$2=$E35,$D35,IF(J$2>J$257,0,IF($C35=J$2,"PAGAR"&" "&TEXT($B35," #.##0,00"),0))) -> 0 | K35: =+IF(K$2=$E35,$D35,IF(K$2>K$257,0,IF($C35=K$2,"PAGAR"&" "&TEXT($B35," #.##0,00"),0))) -> 0 | L35: =+IF(L$2=$E35,$D35,IF(L$2>L$257,0,IF($C35=L$2,"PAGAR"&" "&TEXT($B35," #.##0,00"),0))) -> 0 | M35: =+IF(M$2=$E35,$D35,IF(M$2>M$257,0,IF($C35=M$2,"PAGAR"&" "&TEXT($B35," #.##0,00"),0))) -> 0 | N35: =+IF(N$2=$E35,$D35,IF(N$2>N$257,0,IF($C35=N$2,"PAGAR"&" "&TEXT($B35," #.##0,00"),0))) -> 0 | O35: =+IF(O$2=$E35,$D35,IF(O$2>O$257,0,IF($C35=O$2,"PAGAR"&" "&TEXT($B35," #.##0,00"),0))) -> 0 | P35: =+IF(P$2=$E35,$D35,IF(P$2>P$257,0,IF($C35=P$2,"PAGAR"&" "&TEXT($B35," #.##0,00"),0))) -> 0 | Q35: =+IF(Q$2=$E35,$D35,IF(Q$2>Q$257,0,IF($C35=Q$2,"PAGAR"&" "&TEXT($B35," #.##0,00"),0))) -> 0 | ... AM35: =+IF(AM$2=$E35,$D35,IF(AM$2>AM$257,0,IF($C35=AM$2,"PAGAR"&" "&TEXT($B35," #.##0,00"),0))) -> 0 | AN35: =+IF(F35<0,-F35,0) -> 0 | AO35: =+IF(AND(C35=0,B35>0),B35,0) -> 0
A36: Bônus Tamara | B36: 569 | C36: 15 | F36: =+IF(TODAY()<DATEVALUE(1&D$1&E$1),0,IF(C36>0,IF(C36-SUM(I$255:AM$255)<0,B36-SUM(I36:AM36,0),0),0))+IF(C36=-1,B36-SUM(J36:AM36)) -> 0 | G36: =+IF(B36=0,"-",D36/B36) -> 0 | H36: =IF(H$2=$E36,$D36,IF(H$2>H$257,0,IF($C36=H$2,"PAGAR"&" "&TEXT($B36," #.##0,00"),IF($C36=-1,"PAGAR"&" "&TEXT($B36," #.##0,00"),0)))) -> 0 | I36: =IF(I$2=$E36,$D36,IF(I$2>I$257,0,IF($C36=I$2,"PAGAR"&" "&TEXT($B36," #.##0,00"),IF($C36=-1,"PAGAR"&" "&TEXT($B36," #.##0,00"),0)))) -> 0 | J36: =+IF(J$2=$E36,$D36,IF(J$2>J$257,0,IF($C36=J$2,"PAGAR"&" "&TEXT($B36," #.##0,00"),0))) -> 0 | K36: =+IF(K$2=$E36,$D36,IF(K$2>K$257,0,IF($C36=K$2,"PAGAR"&" "&TEXT($B36," #.##0,00"),0))) -> 0 | L36: =+IF(L$2=$E36,$D36,IF(L$2>L$257,0,IF($C36=L$2,"PAGAR"&" "&TEXT($B36," #.##0,00"),0))) -> 0 | M36: =+IF(M$2=$E36,$D36,IF(M$2>M$257,0,IF($C36=M$2,"PAGAR"&" "&TEXT($B36," #.##0,00"),0))) -> 0 | N36: =+IF(N$2=$E36,$D36,IF(N$2>N$257,0,IF($C36=N$2,"PAGAR"&" "&TEXT($B36," #.##0,00"),0))) -> 0 | O36: =+IF(O$2=$E36,$D36,IF(O$2>O$257,0,IF($C36=O$2,"PAGAR"&" "&TEXT($B36," #.##0,00"),0))) -> 0 | P36: =+IF(P$2=$E36,$D36,IF(P$2>P$257,0,IF($C36=P$2,"PAGAR"&" "&TEXT($B36," #.##0,00"),0))) -> 0 | Q36: =+IF(Q$2=$E36,$D36,IF(Q$2>Q$257,0,IF($C36=Q$2,"PAGAR"&" "&TEXT($B36," #.##0,00"),0))) -> 0 | ... AM36: =+IF(AM$2=$E36,$D36,IF(AM$2>AM$257,0,IF($C36=AM$2,"PAGAR"&" "&TEXT($B36," #.##0,00"),0))) -> 0 | AN36: =+IF(F36<0,-F36,0) -> 0 | AO36: =+IF(AND(C36=0,B36>0),B36,0) -> 0
A37: Clayton manutenção | B37: 1000 | C37: 2 | F37: =+IF(TODAY()<DATEVALUE(1&D$1&E$1),0,IF(C37>0,IF(C37-SUM(I$255:AM$255)<0,B37-SUM(I37:AM37,0),0),0))+IF(C37=-1,B37-SUM(J37:AM37)) -> 1000 | G37: =+IF(B37=0,"-",D37/B37) -> 0 | H37: =IF(H$2=$E37,$D37,IF(H$2>H$257,0,IF($C37=H$2,"PAGAR"&" "&TEXT($B37," #.##0,00"),IF($C37=-1,"PAGAR"&" "&TEXT($B37," #.##0,00"),0)))) -> 0 | I37: =IF(I$2=$E37,$D37,IF(I$2>I$257,0,IF($C37=I$2,"PAGAR"&" "&TEXT($B37," #.##0,00"),IF($C37=-1,"PAGAR"&" "&TEXT($B37," #.##0,00"),0)))) -> 0 | J37: =+IF(J$2=$E37,$D37,IF(J$2>J$257,0,IF($C37=J$2,"PAGAR"&" "&TEXT($B37," #.##0,00"),0))) -> PAGAR 1.000,00 | K37: =+IF(K$2=$E37,$D37,IF(K$2>K$257,0,IF($C37=K$2,"PAGAR"&" "&TEXT($B37," #.##0,00"),0))) -> 0 | L37: =+IF(L$2=$E37,$D37,IF(L$2>L$257,0,IF($C37=L$2,"PAGAR"&" "&TEXT($B37," #.##0,00"),0))) -> 0 | M37: =+IF(M$2=$E37,$D37,IF(M$2>M$257,0,IF($C37=M$2,"PAGAR"&" "&TEXT($B37," #.##0,00"),0))) -> 0 | N37: =+IF(N$2=$E37,$D37,IF(N$2>N$257,0,IF($C37=N$2,"PAGAR"&" "&TEXT($B37," #.##0,00"),0))) -> 0 | O37: =+IF(O$2=$E37,$D37,IF(O$2>O$257,0,IF($C37=O$2,"PAGAR"&" "&TEXT($B37," #.##0,00"),0))) -> 0 | P37: =+IF(P$2=$E37,$D37,IF(P$2>P$257,0,IF($C37=P$2,"PAGAR"&" "&TEXT($B37," #.##0,00"),0))) -> 0 | Q37: =+IF(Q$2=$E37,$D37,IF(Q$2>Q$257,0,IF($C37=Q$2,"PAGAR"&" "&TEXT($B37," #.##0,00"),0))) -> 0 | ... AM37: =+IF(AM$2=$E37,$D37,IF(AM$2>AM$257,0,IF($C37=AM$2,"PAGAR"&" "&TEXT($B37," #.##0,00"),0))) -> 0 | AN37: =+IF(F37<0,-F37,0) -> 0 | AO37: =+IF(AND(C37=0,B37>0),B37,0) -> 0 | AQ37: 22 | AS37: 23 | AU37: 24 | AW37: 25 | AY37: 26 | BA37: 27 | BC37: 28
A38: VA 5 anos | B38: 1890 | C38: 3 | F38: =+IF(TODAY()<DATEVALUE(1&D$1&E$1),0,IF(C38>0,IF(C38-SUM(I$255:AM$255)<0,B38-SUM(I38:AM38,0),0),0))+IF(C38=-1,B38-SUM(J38:AM38)) -> 1890 | G38: =+IF(B38=0,"-",D38/B38) -> 0 | H38: =IF(H$2=$E38,$D38,IF(H$2>H$257,0,IF($C38=H$2,"PAGAR"&" "&TEXT($B38," #.##0,00"),IF($C38=-1,"PAGAR"&" "&TEXT($B38," #.##0,00"),0)))) -> 0 | I38: =IF(I$2=$E38,$D38,IF(I$2>I$257,0,IF($C38=I$2,"PAGAR"&" "&TEXT($B38," #.##0,00"),IF($C38=-1,"PAGAR"&" "&TEXT($B38," #.##0,00"),0)))) -> 0 | J38: =+IF(J$2=$E38,$D38,IF(J$2>J$257,0,IF($C38=J$2,"PAGAR"&" "&TEXT($B38," #.##0,00"),0))) -> 0 | K38: =+IF(K$2=$E38,$D38,IF(K$2>K$257,0,IF($C38=K$2,"PAGAR"&" "&TEXT($B38," #.##0,00"),0))) -> PAGAR 1.890,00 | L38: =+IF(L$2=$E38,$D38,IF(L$2>L$257,0,IF($C38=L$2,"PAGAR"&" "&TEXT($B38," #.##0,00"),0))) -> 0 | M38: =+IF(M$2=$E38,$D38,IF(M$2>M$257,0,IF($C38=M$2,"PAGAR"&" "&TEXT($B38," #.##0,00"),0))) -> 0 | N38: =+IF(N$2=$E38,$D38,IF(N$2>N$257,0,IF($C38=N$2,"PAGAR"&" "&TEXT($B38," #.##0,00"),0))) -> 0 | O38: =+IF(O$2=$E38,$D38,IF(O$2>O$257,0,IF($C38=O$2,"PAGAR"&" "&TEXT($B38," #.##0,00"),0))) -> 0 | P38: =+IF(P$2=$E38,$D38,IF(P$2>P$257,0,IF($C38=P$2,"PAGAR"&" "&TEXT($B38," #.##0,00"),0))) -> 0 | Q38: =+IF(Q$2=$E38,$D38,IF(Q$2>Q$257,0,IF($C38=Q$2,"PAGAR"&" "&TEXT($B38," #.##0,00"),0))) -> 0 | ... AM38: =+IF(AM$2=$E38,$D38,IF(AM$2>AM$257,0,IF($C38=AM$2,"PAGAR"&" "&TEXT($B38," #.##0,00"),0))) -> 0 | AN38: =+IF(F38<0,-F38,0) -> 0 | AO38: =+IF(AND(C38=0,B38>0),B38,0) -> 0 | AQ38: {=_xlfn._xlws.FILTER($A$5:$A$152,$C$5:$C$152=AQ37,"livre")} -> Google One IA - Cartão | AR38: {=_xlfn._xlws.FILTER($B$5:$B$152,$C$5:$C$152=AQ37,"livre")} -> 96.99 | AS38: {=_xlfn._xlws.FILTER($A$5:$A$152,$C$5:$C$152=AS37,"livre")} -> Barão Aluguel | AT38: {=_xlfn._xlws.FILTER($B$5:$B$152,$C$5:$C$152=AS37,"livre")} -> 4377.08 | AU38: {=_xlfn._xlws.FILTER($A$5:$A$152,$C$5:$C$152=AU37,"livre")} -> livre | AV38: {=_xlfn._xlws.FILTER($B$5:$B$152,$C$5:$C$152=AU37,"livre")} -> livre | AW38: {=_xlfn._xlws.FILTER($A$5:$A$152,$C$5:$C$152=AW37,"livre")} -> Seguro Vida Presente 21 | AX38: {=_xlfn._xlws.FILTER($B$5:$B$152,$C$5:$C$152=AW37,"livre")} -> 770.07 | AY38: {=_xlfn._xlws.FILTER($A$5:$A$152,$C$5:$C$152=AY37,"livre")} -> Água Barão | AZ38: {=_xlfn._xlws.FILTER($B$5:$B$152,$C$5:$C$152=AY37,"livre")} -> 2775 | BA38: {=_xlfn._xlws.FILTER($A$5:$A$152,$C$5:$C$152=BA37,"livre")} -> IPTU Reserva | BB38: {=_xlfn._xlws.FILTER($B$5:$B$152,$C$5:$C$152=BA37,"livre")} -> 524.07 | BC38: {=_xlfn._xlws.FILTER($A$5:$A$152,$C$5:$C$152=BC37,"livre")} -> Cartão | BD38: {=_xlfn._xlws.FILTER($B$5:$B$152,$C$5:$C$152=BC37,"livre")} -> 1928.17
A39: Lucas VA 5 anos e normal | B39: 420 | C39: 3 | F39: =+IF(TODAY()<DATEVALUE(1&D$1&E$1),0,IF(C39>0,IF(C39-SUM(I$255:AM$255)<0,B39-SUM(I39:AM39,0),0),0))+IF(C39=-1,B39-SUM(J39:AM39)) -> 420 | G39: =+IF(B39=0,"-",D39/B39) -> 0 | H39: =IF(H$2=$E39,$D39,IF(H$2>H$257,0,IF($C39=H$2,"PAGAR"&" "&TEXT($B39," #.##0,00"),IF($C39=-1,"PAGAR"&" "&TEXT($B39," #.##0,00"),0)))) -> 0 | I39: =IF(I$2=$E39,$D39,IF(I$2>I$257,0,IF($C39=I$2,"PAGAR"&" "&TEXT($B39," #.##0,00"),IF($C39=-1,"PAGAR"&" "&TEXT($B39," #.##0,00"),0)))) -> 0 | J39: =+IF(J$2=$E39,$D39,IF(J$2>J$257,0,IF($C39=J$2,"PAGAR"&" "&TEXT($B39," #.##0,00"),0))) -> 0 | K39: =+IF(K$2=$E39,$D39,IF(K$2>K$257,0,IF($C39=K$2,"PAGAR"&" "&TEXT($B39," #.##0,00"),0))) -> PAGAR 420,00 | L39: =+IF(L$2=$E39,$D39,IF(L$2>L$257,0,IF($C39=L$2,"PAGAR"&" "&TEXT($B39," #.##0,00"),0))) -> 0 | M39: =+IF(M$2=$E39,$D39,IF(M$2>M$257,0,IF($C39=M$2,"PAGAR"&" "&TEXT($B39," #.##0,00"),0))) -> 0 | N39: =+IF(N$2=$E39,$D39,IF(N$2>N$257,0,IF($C39=N$2,"PAGAR"&" "&TEXT($B39," #.##0,00"),0))) -> 0 | O39: =+IF(O$2=$E39,$D39,IF(O$2>O$257,0,IF($C39=O$2,"PAGAR"&" "&TEXT($B39," #.##0,00"),0))) -> 0 | P39: =+IF(P$2=$E39,$D39,IF(P$2>P$257,0,IF($C39=P$2,"PAGAR"&" "&TEXT($B39," #.##0,00"),0))) -> 0 | Q39: =+IF(Q$2=$E39,$D39,IF(Q$2>Q$257,0,IF($C39=Q$2,"PAGAR"&" "&TEXT($B39," #.##0,00"),0))) -> 0 | ... AM39: =+IF(AM$2=$E39,$D39,IF(AM$2>AM$257,0,IF($C39=AM$2,"PAGAR"&" "&TEXT($B39," #.##0,00"),0))) -> 0 | AN39: =+IF(F39<0,-F39,0) -> 0 | AO39: =+IF(AND(C39=0,B39>0),B39,0) -> 0 | AQ39: {=_xlfn._xlws.FILTER($A43:$A190,$C43:$C190=1,"livre")} -> Condomínio Sta Rita | AR39: {=_xlfn._xlws.FILTER($B43:$B190,$C43:$C190=1,"livre")} -> 300 | AS39: {=_xlfn._xlws.FILTER($A43:$A190,$C43:$C190=1,"livre")} -> Condomínio Sta Rita | AT39: {=_xlfn._xlws.FILTER($B43:$B190,$C43:$C190=1,"livre")} -> 300 | AW39: Seguro Previdência VGBL 21 | AX39: 675.52 | AY39: Vivo Lago | AZ39: 236.13 | BC39: Yelum Seguro Civic - Cartão | BD39: 286.78
A40: VA normal | B40: 2520 | C40: 28 | F40: =+IF(TODAY()<DATEVALUE(1&D$1&E$1),0,IF(C40>0,IF(C40-SUM(I$255:AM$255)<0,B40-SUM(I40:AM40,0),0),0))+IF(C40=-1,B40-SUM(J40:AM40)) -> 0 | G40: =+IF(B40=0,"-",D40/B40) -> 0 | H40: =IF(H$2=$E40,$D40,IF(H$2>H$257,0,IF($C40=H$2,"PAGAR"&" "&TEXT($B40," #.##0,00"),IF($C40=-1,"PAGAR"&" "&TEXT($B40," #.##0,00"),0)))) -> 0 | I40: =IF(I$2=$E40,$D40,IF(I$2>I$257,0,IF($C40=I$2,"PAGAR"&" "&TEXT($B40," #.##0,00"),IF($C40=-1,"PAGAR"&" "&TEXT($B40," #.##0,00"),0)))) -> 0 | J40: =+IF(J$2=$E40,$D40,IF(J$2>J$257,0,IF($C40=J$2,"PAGAR"&" "&TEXT($B40," #.##0,00"),0))) -> 0 | K40: =+IF(K$2=$E40,$D40,IF(K$2>K$257,0,IF($C40=K$2,"PAGAR"&" "&TEXT($B40," #.##0,00"),0))) -> 0 | L40: =+IF(L$2=$E40,$D40,IF(L$2>L$257,0,IF($C40=L$2,"PAGAR"&" "&TEXT($B40," #.##0,00"),0))) -> 0 | M40: =+IF(M$2=$E40,$D40,IF(M$2>M$257,0,IF($C40=M$2,"PAGAR"&" "&TEXT($B40," #.##0,00"),0))) -> 0 | N40: =+IF(N$2=$E40,$D40,IF(N$2>N$257,0,IF($C40=N$2,"PAGAR"&" "&TEXT($B40," #.##0,00"),0))) -> 0 | O40: =+IF(O$2=$E40,$D40,IF(O$2>O$257,0,IF($C40=O$2,"PAGAR"&" "&TEXT($B40," #.##0,00"),0))) -> 0 | P40: =+IF(P$2=$E40,$D40,IF(P$2>P$257,0,IF($C40=P$2,"PAGAR"&" "&TEXT($B40," #.##0,00"),0))) -> 0 | Q40: =+IF(Q$2=$E40,$D40,IF(Q$2>Q$257,0,IF($C40=Q$2,"PAGAR"&" "&TEXT($B40," #.##0,00"),0))) -> 0 | ... AM40: =+IF(AM$2=$E40,$D40,IF(AM$2>AM$257,0,IF($C40=AM$2,"PAGAR"&" "&TEXT($B40," #.##0,00"),0))) -> 0 | AN40: =+IF(F40<0,-F40,0) -> 0 | AO40: =+IF(AND(C40=0,B40>0),B40,0) -> 0 | AQ40: Letízio mensal | AR40: 1750 | AS40: Letízio mensal | AT40: 1750 | AW40: Contabilidade | AX40: 2211 | AY40: Itaú - débito auto (6/37x) 5% 50k | AZ40: 3099 | BC40: Apple.com - Cartão | BD40: 29.9
A41: CPFL Plátamo | B41: 1305 | C41: 28 | F41: =+IF(TODAY()<DATEVALUE(1&D$1&E$1),0,IF(C41>0,IF(C41-SUM(I$255:AM$255)<0,B41-SUM(I41:AM41,0),0),0))+IF(C41=-1,B41-SUM(J41:AM41)) -> 0 | G41: =+IF(B41=0,"-",D41/B41) -> 0 | H41: =IF(H$2=$E41,$D41,IF(H$2>H$257,0,IF($C41=H$2,"PAGAR"&" "&TEXT($B41," #.##0,00"),IF($C41=-1,"PAGAR"&" "&TEXT($B41," #.##0,00"),0)))) -> 0 | I41: =IF(I$2=$E41,$D41,IF(I$2>I$257,0,IF($C41=I$2,"PAGAR"&" "&TEXT($B41," #.##0,00"),IF($C41=-1,"PAGAR"&" "&TEXT($B41," #.##0,00"),0)))) -> 0 | J41: =+IF(J$2=$E41,$D41,IF(J$2>J$257,0,IF($C41=J$2,"PAGAR"&" "&TEXT($B41," #.##0,00"),0))) -> 0 | K41: =+IF(K$2=$E41,$D41,IF(K$2>K$257,0,IF($C41=K$2,"PAGAR"&" "&TEXT($B41," #.##0,00"),0))) -> 0 | L41: =+IF(L$2=$E41,$D41,IF(L$2>L$257,0,IF($C41=L$2,"PAGAR"&" "&TEXT($B41," #.##0,00"),0))) -> 0 | M41: =+IF(M$2=$E41,$D41,IF(M$2>M$257,0,IF($C41=M$2,"PAGAR"&" "&TEXT($B41," #.##0,00"),0))) -> 0 | N41: =+IF(N$2=$E41,$D41,IF(N$2>N$257,0,IF($C41=N$2,"PAGAR"&" "&TEXT($B41," #.##0,00"),0))) -> 0 | O41: =+IF(O$2=$E41,$D41,IF(O$2>O$257,0,IF($C41=O$2,"PAGAR"&" "&TEXT($B41," #.##0,00"),0))) -> 0 | P41: =+IF(P$2=$E41,$D41,IF(P$2>P$257,0,IF($C41=P$2,"PAGAR"&" "&TEXT($B41," #.##0,00"),0))) -> 0 | Q41: =+IF(Q$2=$E41,$D41,IF(Q$2>Q$257,0,IF($C41=Q$2,"PAGAR"&" "&TEXT($B41," #.##0,00"),0))) -> 0 | ... AM41: =+IF(AM$2=$E41,$D41,IF(AM$2>AM$257,0,IF($C41=AM$2,"PAGAR"&" "&TEXT($B41," #.##0,00"),0))) -> 0 | AN41: =+IF(F41<0,-F41,0) -> 0 | AO41: =+IF(AND(C41=0,B41>0),B41,0) -> 0 | AW41: Telhanorte Aluguel | AX41: 1889.57 | AY41: Frees + R$400 Josiane | AZ41: 6900 | BC41: VA normal | BD41: 2520
A42: Result | B42: 1270 | C42: 28 | F42: =+IF(TODAY()<DATEVALUE(1&D$1&E$1),0,IF(C42>0,IF(C42-SUM(I$255:AM$255)<0,B42-SUM(I42:AM42,0),0),0))+IF(C42=-1,B42-SUM(J42:AM42)) -> 0 | G42: =+IF(B42=0,"-",D42/B42) -> 0 | H42: =IF(H$2=$E42,$D42,IF(H$2>H$257,0,IF($C42=H$2,"PAGAR"&" "&TEXT($B42," #.##0,00"),IF($C42=-1,"PAGAR"&" "&TEXT($B42," #.##0,00"),0)))) -> 0 | I42: =IF(I$2=$E42,$D42,IF(I$2>I$257,0,IF($C42=I$2,"PAGAR"&" "&TEXT($B42," #.##0,00"),IF($C42=-1,"PAGAR"&" "&TEXT($B42," #.##0,00"),0)))) -> 0 | J42: =+IF(J$2=$E42,$D42,IF(J$2>J$257,0,IF($C42=J$2,"PAGAR"&" "&TEXT($B42," #.##0,00"),0))) -> 0 | K42: =+IF(K$2=$E42,$D42,IF(K$2>K$257,0,IF($C42=K$2,"PAGAR"&" "&TEXT($B42," #.##0,00"),0))) -> 0 | L42: =+IF(L$2=$E42,$D42,IF(L$2>L$257,0,IF($C42=L$2,"PAGAR"&" "&TEXT($B42," #.##0,00"),0))) -> 0 | M42: =+IF(M$2=$E42,$D42,IF(M$2>M$257,0,IF($C42=M$2,"PAGAR"&" "&TEXT($B42," #.##0,00"),0))) -> 0 | N42: =+IF(N$2=$E42,$D42,IF(N$2>N$257,0,IF($C42=N$2,"PAGAR"&" "&TEXT($B42," #.##0,00"),0))) -> 0 | O42: =+IF(O$2=$E42,$D42,IF(O$2>O$257,0,IF($C42=O$2,"PAGAR"&" "&TEXT($B42," #.##0,00"),0))) -> 0 | P42: =+IF(P$2=$E42,$D42,IF(P$2>P$257,0,IF($C42=P$2,"PAGAR"&" "&TEXT($B42," #.##0,00"),0))) -> 0 | Q42: =+IF(Q$2=$E42,$D42,IF(Q$2>Q$257,0,IF($C42=Q$2,"PAGAR"&" "&TEXT($B42," #.##0,00"),0))) -> 0 | ... AM42: =+IF(AM$2=$E42,$D42,IF(AM$2>AM$257,0,IF($C42=AM$2,"PAGAR"&" "&TEXT($B42," #.##0,00"),0))) -> 0 | AN42: =+IF(F42<0,-F42,0) -> 0 | AO42: =+IF(AND(C42=0,B42>0),B42,0) -> 0 | BC42: CPFL Plátamo | BD42: 1305
A43: Contabilidade | B43: 2211 | C43: 25 | F43: =+IF(TODAY()<DATEVALUE(1&D$1&E$1),0,IF(C43>0,IF(C43-SUM(I$255:AM$255)<0,B43-SUM(I43:AM43,0),0),0))+IF(C43=-1,B43-SUM(J43:AM43)) -> 0 | G43: =+IF(B43=0,"-",D43/B43) -> 0 | H43: =IF(H$2=$E43,$D43,IF(H$2>H$257,0,IF($C43=H$2,"PAGAR"&" "&TEXT($B43," #.##0,00"),IF($C43=-1,"PAGAR"&" "&TEXT($B43," #.##0,00"),0)))) -> 0 | I43: =IF(I$2=$E43,$D43,IF(I$2>I$257,0,IF($C43=I$2,"PAGAR"&" "&TEXT($B43," #.##0,00"),IF($C43=-1,"PAGAR"&" "&TEXT($B43," #.##0,00"),0)))) -> 0 | J43: =+IF(J$2=$E43,$D43,IF(J$2>J$257,0,IF($C43=J$2,"PAGAR"&" "&TEXT($B43," #.##0,00"),0))) -> 0 | K43: =+IF(K$2=$E43,$D43,IF(K$2>K$257,0,IF($C43=K$2,"PAGAR"&" "&TEXT($B43," #.##0,00"),0))) -> 0 | L43: =+IF(L$2=$E43,$D43,IF(L$2>L$257,0,IF($C43=L$2,"PAGAR"&" "&TEXT($B43," #.##0,00"),0))) -> 0 | M43: =+IF(M$2=$E43,$D43,IF(M$2>M$257,0,IF($C43=M$2,"PAGAR"&" "&TEXT($B43," #.##0,00"),0))) -> 0 | N43: =+IF(N$2=$E43,$D43,IF(N$2>N$257,0,IF($C43=N$2,"PAGAR"&" "&TEXT($B43," #.##0,00"),0))) -> 0 | O43: =+IF(O$2=$E43,$D43,IF(O$2>O$257,0,IF($C43=O$2,"PAGAR"&" "&TEXT($B43," #.##0,00"),0))) -> 0 | P43: =+IF(P$2=$E43,$D43,IF(P$2>P$257,0,IF($C43=P$2,"PAGAR"&" "&TEXT($B43," #.##0,00"),0))) -> 0 | Q43: =+IF(Q$2=$E43,$D43,IF(Q$2>Q$257,0,IF($C43=Q$2,"PAGAR"&" "&TEXT($B43," #.##0,00"),0))) -> 0 | ... AM43: =+IF(AM$2=$E43,$D43,IF(AM$2>AM$257,0,IF($C43=AM$2,"PAGAR"&" "&TEXT($B43," #.##0,00"),0))) -> 0 | AN43: =+IF(F43<0,-F43,0) -> 0 | AO43: =+IF(AND(C43=0,B43>0),B43,0) -> 0 | BC43: Result | BD43: 1270
A44: Total de despesas previstas (Plan 2) | B44: =+SUM(B28:B43) -> 22095.42 | D44: =+SUM(D28:D43) -> 1010 | F44: =+SUMIF(F28:F43,">0") -> 7335.42 | G44: =+IF(B44=0,"-",D44/B44) -> 0.045710831 | I44: =+PLAN2!H45 -> 0 | J44: =+PLAN2!I45 -> 1000 | K44: =+PLAN2!J45 -> 2310 | L44: =+PLAN2!K45 -> 0 | M44: =+PLAN2!L45 -> 0 | N44: =+PLAN2!M45 -> 1080 | O44: =+PLAN2!N45 -> 0 | P44: =+PLAN2!O45 -> 0 | ... AM44: =+PLAN2!AL45 -> 0 | AN44: =SUM(AN28:AN43) -> 0
A45: EXTRA EMPRESA
A46: VT | B46: 500 | C46: 15 | F46: =+IF(TODAY()<DATEVALUE(1&D$1&E$1),0,IF(C46>0,IF(C46-SUM(I$255:AM$255)<0,B46-SUM(I46:AM46,0),0),0))+IF(C46=-1,B46-SUM(J46:AM46)) -> 0 | G46: =+IF(B46=0,"-",D46/B46) -> 0 | I46: =IF(I$2=$E46,$D46,IF(I$2>I$257,0,IF($C46=I$2,"PAGAR"&" "&TEXT($B46," #.##0,00"),IF($C46=-1,"PAGAR"&" "&TEXT($B46," #.##0,00"),0)))) -> 0 | J46: =+IF(J$2=$E46,$D46,IF(J$2>J$257,0,IF($C46=J$2,"PAGAR"&" "&TEXT($B46," #.##0,00"),0))) -> 0 | K46: =+IF(K$2=$E46,$D46,IF(K$2>K$257,0,IF($C46=K$2,"PAGAR"&" "&TEXT($B46," #.##0,00"),0))) -> 0 | L46: =+IF(L$2=$E46,$D46,IF(L$2>L$257,0,IF($C46=L$2,"PAGAR"&" "&TEXT($B46," #.##0,00"),0))) -> 0 | M46: =+IF(M$2=$E46,$D46,IF(M$2>M$257,0,IF($C46=M$2,"PAGAR"&" "&TEXT($B46," #.##0,00"),0))) -> 0 | N46: =+IF(N$2=$E46,$D46,IF(N$2>N$257,0,IF($C46=N$2,"PAGAR"&" "&TEXT($B46," #.##0,00"),0))) -> 0 | O46: =+IF(O$2=$E46,$D46,IF(O$2>O$257,0,IF($C46=O$2,"PAGAR"&" "&TEXT($B46," #.##0,00"),0))) -> 0 | P46: =+IF(P$2=$E46,$D46,IF(P$2>P$257,0,IF($C46=P$2,"PAGAR"&" "&TEXT($B46," #.##0,00"),0))) -> 0 | Q46: =+IF(Q$2=$E46,$D46,IF(Q$2>Q$257,0,IF($C46=Q$2,"PAGAR"&" "&TEXT($B46," #.##0,00"),0))) -> 0 | ... AM46: =+IF(AM$2=$E46,$D46,IF(AM$2>AM$257,0,IF($C46=AM$2,"PAGAR"&" "&TEXT($B46," #.##0,00"),0))) -> 0 | AN46: =+IF(F46<0,-F46,0) -> 0 | AO46: =+IF(AND(C46=0,B46>0),B46,0) -> 0
A47: VT | B47: 500 | C47: 2 | F47: =+IF(TODAY()<DATEVALUE(1&D$1&E$1),0,IF(C47>0,IF(C47-SUM(I$255:AM$255)<0,B47-SUM(I47:AM47,0),0),0))+IF(C47=-1,B47-SUM(J47:AM47)) -> 500 | G47: =+IF(B47=0,"-",D47/B47) -> 0 | I47: =IF(I$2=$E47,$D47,IF(I$2>I$257,0,IF($C47=I$2,"PAGAR"&" "&TEXT($B47," #.##0,00"),IF($C47=-1,"PAGAR"&" "&TEXT($B47," #.##0,00"),0)))) -> 0 | J47: =+IF(J$2=$E47,$D47,IF(J$2>J$257,0,IF($C47=J$2,"PAGAR"&" "&TEXT($B47," #.##0,00"),0))) -> PAGAR 500,00 | K47: =+IF(K$2=$E47,$D47,IF(K$2>K$257,0,IF($C47=K$2,"PAGAR"&" "&TEXT($B47," #.##0,00"),0))) -> 0 | L47: =+IF(L$2=$E47,$D47,IF(L$2>L$257,0,IF($C47=L$2,"PAGAR"&" "&TEXT($B47," #.##0,00"),0))) -> 0 | M47: =+IF(M$2=$E47,$D47,IF(M$2>M$257,0,IF($C47=M$2,"PAGAR"&" "&TEXT($B47," #.##0,00"),0))) -> 0 | N47: =+IF(N$2=$E47,$D47,IF(N$2>N$257,0,IF($C47=N$2,"PAGAR"&" "&TEXT($B47," #.##0,00"),0))) -> 0 | O47: =+IF(O$2=$E47,$D47,IF(O$2>O$257,0,IF($C47=O$2,"PAGAR"&" "&TEXT($B47," #.##0,00"),0))) -> 0 | P47: =+IF(P$2=$E47,$D47,IF(P$2>P$257,0,IF($C47=P$2,"PAGAR"&" "&TEXT($B47," #.##0,00"),0))) -> 0 | Q47: =+IF(Q$2=$E47,$D47,IF(Q$2>Q$257,0,IF($C47=Q$2,"PAGAR"&" "&TEXT($B47," #.##0,00"),0))) -> 0 | ... AM47: =+IF(AM$2=$E47,$D47,IF(AM$2>AM$257,0,IF($C47=AM$2,"PAGAR"&" "&TEXT($B47," #.##0,00"),0))) -> 0 | AN47: =+IF(F47<0,-F47,0) -> 0 | AO47: =+IF(AND(C47=0,B47>0),B47,0) -> 0
F48: =+IF(TODAY()<DATEVALUE(1&D$1&E$1),0,IF(C48>0,IF(C48-SUM(I$255:AM$255)<0,B48-SUM(I48:AM48,0),0),0))+IF(C48=-1,B48-SUM(J48:AM48)) -> 0 | G48: =+IF(B48=0,"-",D48/B48) -> - | I48: =IF(I$2=$E48,$D48,IF(I$2>I$257,0,IF($C48=I$2,"PAGAR"&" "&TEXT($B48," #.##0,00"),IF($C48=-1,"PAGAR"&" "&TEXT($B48," #.##0,00"),0)))) -> 0 | J48: =+IF(J$2=$E48,$D48,IF(J$2>J$257,0,IF($C48=J$2,"PAGAR"&" "&TEXT($B48," #.##0,00"),0))) -> 0 | K48: =+IF(K$2=$E48,$D48,IF(K$2>K$257,0,IF($C48=K$2,"PAGAR"&" "&TEXT($B48," #.##0,00"),0))) -> 0 | L48: =+IF(L$2=$E48,$D48,IF(L$2>L$257,0,IF($C48=L$2,"PAGAR"&" "&TEXT($B48," #.##0,00"),0))) -> 0 | M48: =+IF(M$2=$E48,$D48,IF(M$2>M$257,0,IF($C48=M$2,"PAGAR"&" "&TEXT($B48," #.##0,00"),0))) -> 0 | N48: =+IF(N$2=$E48,$D48,IF(N$2>N$257,0,IF($C48=N$2,"PAGAR"&" "&TEXT($B48," #.##0,00"),0))) -> 0 | O48: =+IF(O$2=$E48,$D48,IF(O$2>O$257,0,IF($C48=O$2,"PAGAR"&" "&TEXT($B48," #.##0,00"),0))) -> 0 | P48: =+IF(P$2=$E48,$D48,IF(P$2>P$257,0,IF($C48=P$2,"PAGAR"&" "&TEXT($B48," #.##0,00"),0))) -> 0 | Q48: =+IF(Q$2=$E48,$D48,IF(Q$2>Q$257,0,IF($C48=Q$2,"PAGAR"&" "&TEXT($B48," #.##0,00"),0))) -> 0 | ... AM48: =+IF(AM$2=$E48,$D48,IF(AM$2>AM$257,0,IF($C48=AM$2,"PAGAR"&" "&TEXT($B48," #.##0,00"),0))) -> 0 | AN48: =+IF(F48<0,-F48,0) -> 0 | AO48: =+IF(AND(C48=0,B48>0),B48,0) -> 0 | AQ48: 29 | AS48: 30 | AU48: 31
F49: =+IF(TODAY()<DATEVALUE(1&D$1&E$1),0,IF(C49>0,IF(C49-SUM(I$255:AM$255)<0,B49-SUM(I49:AM49,0),0),0))+IF(C49=-1,B49-SUM(J49:AM49)) -> 0 | G49: =+IF(B49=0,"-",D49/B49) -> - | I49: =IF(I$2=$E49,$D49,IF(I$2>I$257,0,IF($C49=I$2,"PAGAR"&" "&TEXT($B49," #.##0,00"),IF($C49=-1,"PAGAR"&" "&TEXT($B49," #.##0,00"),0)))) -> 0 | J49: =+IF(J$2=$E49,$D49,IF(J$2>J$257,0,IF($C49=J$2,"PAGAR"&" "&TEXT($B49," #.##0,00"),0))) -> 0 | K49: =+IF(K$2=$E49,$D49,IF(K$2>K$257,0,IF($C49=K$2,"PAGAR"&" "&TEXT($B49," #.##0,00"),0))) -> 0 | L49: =+IF(L$2=$E49,$D49,IF(L$2>L$257,0,IF($C49=L$2,"PAGAR"&" "&TEXT($B49," #.##0,00"),0))) -> 0 | M49: =+IF(M$2=$E49,$D49,IF(M$2>M$257,0,IF($C49=M$2,"PAGAR"&" "&TEXT($B49," #.##0,00"),0))) -> 0 | N49: =+IF(N$2=$E49,$D49,IF(N$2>N$257,0,IF($C49=N$2,"PAGAR"&" "&TEXT($B49," #.##0,00"),0))) -> 0 | O49: =+IF(O$2=$E49,$D49,IF(O$2>O$257,0,IF($C49=O$2,"PAGAR"&" "&TEXT($B49," #.##0,00"),0))) -> 0 | P49: =+IF(P$2=$E49,$D49,IF(P$2>P$257,0,IF($C49=P$2,"PAGAR"&" "&TEXT($B49," #.##0,00"),0))) -> 0 | Q49: =+IF(Q$2=$E49,$D49,IF(Q$2>Q$257,0,IF($C49=Q$2,"PAGAR"&" "&TEXT($B49," #.##0,00"),0))) -> 0 | ... AM49: =+IF(AM$2=$E49,$D49,IF(AM$2>AM$257,0,IF($C49=AM$2,"PAGAR"&" "&TEXT($B49," #.##0,00"),0))) -> 0 | AN49: =+IF(F49<0,-F49,0) -> 0 | AO49: =+IF(AND(C49=0,B49>0),B49,0) -> 0 | AQ49: {=_xlfn._xlws.FILTER($A$5:$A$152,$C$5:$C$152=AQ48,"livre")} -> livre | AR49: {=_xlfn._xlws.FILTER($B$5:$B$152,$C$5:$C$152=AQ48,"livre")} -> livre | AS49: {=_xlfn._xlws.FILTER($A$5:$A$152,$C$5:$C$152=AS48,"livre")} -> Cristiane | AT49: {=_xlfn._xlws.FILTER($B$5:$B$152,$C$5:$C$152=AS48,"livre")} -> 940 | AU49: {=_xlfn._xlws.FILTER($A$5:$A$152,$C$5:$C$152=AU48,"livre")} -> livre | AV49: {=_xlfn._xlws.FILTER($B$5:$B$152,$C$5:$C$152=AU48,"livre")} -> livre
F50: =+IF(TODAY()<DATEVALUE(1&D$1&E$1),0,IF(C50>0,IF(C50-SUM(I$255:AM$255)<0,B50-SUM(I50:AM50,0),0),0))+IF(C50=-1,B50-SUM(J50:AM50)) -> 0 | G50: =+IF(B50=0,"-",D50/B50) -> - | I50: =IF(I$2=$E50,$D50,IF(I$2>I$257,0,IF($C50=I$2,"PAGAR"&" "&TEXT($B50," #.##0,00"),IF($C50=-1,"PAGAR"&" "&TEXT($B50," #.##0,00"),0)))) -> 0 | J50: =+IF(J$2=$E50,$D50,IF(J$2>J$257,0,IF($C50=J$2,"PAGAR"&" "&TEXT($B50," #.##0,00"),0))) -> 0 | K50: =+IF(K$2=$E50,$D50,IF(K$2>K$257,0,IF($C50=K$2,"PAGAR"&" "&TEXT($B50," #.##0,00"),0))) -> 0 | L50: =+IF(L$2=$E50,$D50,IF(L$2>L$257,0,IF($C50=L$2,"PAGAR"&" "&TEXT($B50," #.##0,00"),0))) -> 0 | M50: =+IF(M$2=$E50,$D50,IF(M$2>M$257,0,IF($C50=M$2,"PAGAR"&" "&TEXT($B50," #.##0,00"),0))) -> 0 | N50: =+IF(N$2=$E50,$D50,IF(N$2>N$257,0,IF($C50=N$2,"PAGAR"&" "&TEXT($B50," #.##0,00"),0))) -> 0 | O50: =+IF(O$2=$E50,$D50,IF(O$2>O$257,0,IF($C50=O$2,"PAGAR"&" "&TEXT($B50," #.##0,00"),0))) -> 0 | P50: =+IF(P$2=$E50,$D50,IF(P$2>P$257,0,IF($C50=P$2,"PAGAR"&" "&TEXT($B50," #.##0,00"),0))) -> 0 | Q50: =+IF(Q$2=$E50,$D50,IF(Q$2>Q$257,0,IF($C50=Q$2,"PAGAR"&" "&TEXT($B50," #.##0,00"),0))) -> 0 | ... AM50: =+IF(AM$2=$E50,$D50,IF(AM$2>AM$257,0,IF($C50=AM$2,"PAGAR"&" "&TEXT($B50," #.##0,00"),0))) -> 0 | AN50: =+IF(F50<0,-F50,0) -> 0 | AO50: =+IF(AND(C50=0,B50>0),B50,0) -> 0 | AS50: Parcela IR 4lock até 2024 | AT50: 3237.6
F51: =+IF(TODAY()<DATEVALUE(1&D$1&E$1),0,IF(C51>0,IF(C51-SUM(I$255:AM$255)<0,B51-SUM(I51:AM51,0),0),0))+IF(C51=-1,B51-SUM(J51:AM51)) -> 0 | G51: =+IF(B51=0,"-",D51/B51) -> - | I51: =IF(I$2=$E51,$D51,IF(I$2>I$257,0,IF($C51=I$2,"PAGAR"&" "&TEXT($B51," #.##0,00"),IF($C51=-1,"PAGAR"&" "&TEXT($B51," #.##0,00"),0)))) -> 0 | J51: =+IF(J$2=$E51,$D51,IF(J$2>J$257,0,IF($C51=J$2,"PAGAR"&" "&TEXT($B51," #.##0,00"),0))) -> 0 | K51: =+IF(K$2=$E51,$D51,IF(K$2>K$257,0,IF($C51=K$2,"PAGAR"&" "&TEXT($B51," #.##0,00"),0))) -> 0 | L51: =+IF(L$2=$E51,$D51,IF(L$2>L$257,0,IF($C51=L$2,"PAGAR"&" "&TEXT($B51," #.##0,00"),0))) -> 0 | M51: =+IF(M$2=$E51,$D51,IF(M$2>M$257,0,IF($C51=M$2,"PAGAR"&" "&TEXT($B51," #.##0,00"),0))) -> 0 | N51: =+IF(N$2=$E51,$D51,IF(N$2>N$257,0,IF($C51=N$2,"PAGAR"&" "&TEXT($B51," #.##0,00"),0))) -> 0 | O51: =+IF(O$2=$E51,$D51,IF(O$2>O$257,0,IF($C51=O$2,"PAGAR"&" "&TEXT($B51," #.##0,00"),0))) -> 0 | P51: =+IF(P$2=$E51,$D51,IF(P$2>P$257,0,IF($C51=P$2,"PAGAR"&" "&TEXT($B51," #.##0,00"),0))) -> 0 | Q51: =+IF(Q$2=$E51,$D51,IF(Q$2>Q$257,0,IF($C51=Q$2,"PAGAR"&" "&TEXT($B51," #.##0,00"),0))) -> 0 | ... AM51: =+IF(AM$2=$E51,$D51,IF(AM$2>AM$257,0,IF($C51=AM$2,"PAGAR"&" "&TEXT($B51," #.##0,00"),0))) -> 0 | AN51: =+IF(F51<0,-F51,0) -> 0 | AO51: =+IF(AND(C51=0,B51>0),B51,0) -> 0 | AS51: Parcela IRPF Claudio? | AT51: 1286.35
F52: =+IF(TODAY()<DATEVALUE(1&D$1&E$1),0,IF(C52>0,IF(C52-SUM(I$255:AM$255)<0,B52-SUM(I52:AM52,0),0),0))+IF(C52=-1,B52-SUM(J52:AM52)) -> 0 | G52: =+IF(B52=0,"-",D52/B52) -> - | I52: =IF(I$2=$E52,$D52,IF(I$2>I$257,0,IF($C52=I$2,"PAGAR"&" "&TEXT($B52," #.##0,00"),IF($C52=-1,"PAGAR"&" "&TEXT($B52," #.##0,00"),0)))) -> 0 | J52: =+IF(J$2=$E52,$D52,IF(J$2>J$257,0,IF($C52=J$2,"PAGAR"&" "&TEXT($B52," #.##0,00"),0))) -> 0 | K52: =+IF(K$2=$E52,$D52,IF(K$2>K$257,0,IF($C52=K$2,"PAGAR"&" "&TEXT($B52," #.##0,00"),0))) -> 0 | L52: =+IF(L$2=$E52,$D52,IF(L$2>L$257,0,IF($C52=L$2,"PAGAR"&" "&TEXT($B52," #.##0,00"),0))) -> 0 | M52: =+IF(M$2=$E52,$D52,IF(M$2>M$257,0,IF($C52=M$2,"PAGAR"&" "&TEXT($B52," #.##0,00"),0))) -> 0 | N52: =+IF(N$2=$E52,$D52,IF(N$2>N$257,0,IF($C52=N$2,"PAGAR"&" "&TEXT($B52," #.##0,00"),0))) -> 0 | O52: =+IF(O$2=$E52,$D52,IF(O$2>O$257,0,IF($C52=O$2,"PAGAR"&" "&TEXT($B52," #.##0,00"),0))) -> 0 | P52: =+IF(P$2=$E52,$D52,IF(P$2>P$257,0,IF($C52=P$2,"PAGAR"&" "&TEXT($B52," #.##0,00"),0))) -> 0 | Q52: =+IF(Q$2=$E52,$D52,IF(Q$2>Q$257,0,IF($C52=Q$2,"PAGAR"&" "&TEXT($B52," #.##0,00"),0))) -> 0 | ... AM52: =+IF(AM$2=$E52,$D52,IF(AM$2>AM$257,0,IF($C52=AM$2,"PAGAR"&" "&TEXT($B52," #.##0,00"),0))) -> 0 | AN52: =+IF(F52<0,-F52,0) -> 0 | AO52: =+IF(AND(C52=0,B52>0),B52,0) -> 0
F53: =+IF(TODAY()<DATEVALUE(1&D$1&E$1),0,IF(C53>0,IF(C53-SUM(I$255:AM$255)<0,B53-SUM(I53:AM53,0),0),0))+IF(C53=-1,B53-SUM(J53:AM53)) -> 0 | G53: =+IF(B53=0,"-",D53/B53) -> - | I53: =IF(I$2=$E53,$D53,IF(I$2>I$257,0,IF($C53=I$2,"PAGAR"&" "&TEXT($B53," #.##0,00"),IF($C53=-1,"PAGAR"&" "&TEXT($B53," #.##0,00"),0)))) -> 0 | J53: =+IF(J$2=$E53,$D53,IF(J$2>J$257,0,IF($C53=J$2,"PAGAR"&" "&TEXT($B53," #.##0,00"),0))) -> 0 | K53: =+IF(K$2=$E53,$D53,IF(K$2>K$257,0,IF($C53=K$2,"PAGAR"&" "&TEXT($B53," #.##0,00"),0))) -> 0 | L53: =+IF(L$2=$E53,$D53,IF(L$2>L$257,0,IF($C53=L$2,"PAGAR"&" "&TEXT($B53," #.##0,00"),0))) -> 0 | M53: =+IF(M$2=$E53,$D53,IF(M$2>M$257,0,IF($C53=M$2,"PAGAR"&" "&TEXT($B53," #.##0,00"),0))) -> 0 | N53: =+IF(N$2=$E53,$D53,IF(N$2>N$257,0,IF($C53=N$2,"PAGAR"&" "&TEXT($B53," #.##0,00"),0))) -> 0 | O53: =+IF(O$2=$E53,$D53,IF(O$2>O$257,0,IF($C53=O$2,"PAGAR"&" "&TEXT($B53," #.##0,00"),0))) -> 0 | P53: =+IF(P$2=$E53,$D53,IF(P$2>P$257,0,IF($C53=P$2,"PAGAR"&" "&TEXT($B53," #.##0,00"),0))) -> 0 | Q53: =+IF(Q$2=$E53,$D53,IF(Q$2>Q$257,0,IF($C53=Q$2,"PAGAR"&" "&TEXT($B53," #.##0,00"),0))) -> 0 | ... AM53: =+IF(AM$2=$E53,$D53,IF(AM$2>AM$257,0,IF($C53=AM$2,"PAGAR"&" "&TEXT($B53," #.##0,00"),0))) -> 0 | AN53: =+IF(F53<0,-F53,0) -> 0 | AO53: =+IF(AND(C53=0,B53>0),B53,0) -> 0
F54: =+IF(TODAY()<DATEVALUE(1&D$1&E$1),0,IF(C54>0,IF(C54-SUM(I$255:AM$255)<0,B54-SUM(I54:AM54,0),0),0))+IF(C54=-1,B54-SUM(J54:AM54)) -> 0 | G54: =+IF(B54=0,"-",D54/B54) -> - | I54: =IF(I$2=$E54,$D54,IF(I$2>I$257,0,IF($C54=I$2,"PAGAR"&" "&TEXT($B54," #.##0,00"),IF($C54=-1,"PAGAR"&" "&TEXT($B54," #.##0,00"),0)))) -> 0 | J54: =+IF(J$2=$E54,$D54,IF(J$2>J$257,0,IF($C54=J$2,"PAGAR"&" "&TEXT($B54," #.##0,00"),0))) -> 0 | K54: =+IF(K$2=$E54,$D54,IF(K$2>K$257,0,IF($C54=K$2,"PAGAR"&" "&TEXT($B54," #.##0,00"),0))) -> 0 | L54: =+IF(L$2=$E54,$D54,IF(L$2>L$257,0,IF($C54=L$2,"PAGAR"&" "&TEXT($B54," #.##0,00"),0))) -> 0 | M54: =+IF(M$2=$E54,$D54,IF(M$2>M$257,0,IF($C54=M$2,"PAGAR"&" "&TEXT($B54," #.##0,00"),0))) -> 0 | N54: =+IF(N$2=$E54,$D54,IF(N$2>N$257,0,IF($C54=N$2,"PAGAR"&" "&TEXT($B54," #.##0,00"),0))) -> 0 | O54: =+IF(O$2=$E54,$D54,IF(O$2>O$257,0,IF($C54=O$2,"PAGAR"&" "&TEXT($B54," #.##0,00"),0))) -> 0 | P54: =+IF(P$2=$E54,$D54,IF(P$2>P$257,0,IF($C54=P$2,"PAGAR"&" "&TEXT($B54," #.##0,00"),0))) -> 0 | Q54: =+IF(Q$2=$E54,$D54,IF(Q$2>Q$257,0,IF($C54=Q$2,"PAGAR"&" "&TEXT($B54," #.##0,00"),0))) -> 0 | ... AM54: =+IF(AM$2=$E54,$D54,IF(AM$2>AM$257,0,IF($C54=AM$2,"PAGAR"&" "&TEXT($B54," #.##0,00"),0))) -> 0 | AN54: =+IF(F54<0,-F54,0) -> 0 | AO54: =+IF(AND(C54=0,B54>0),B54,0) -> 0
F55: =+IF(TODAY()<DATEVALUE(1&D$1&E$1),0,IF(C55>0,IF(C55-SUM(I$255:AM$255)<0,B55-SUM(I55:AM55,0),0),0))+IF(C55=-1,B55-SUM(J55:AM55)) -> 0 | G55: =+IF(B55=0,"-",D55/B55) -> - | I55: =IF(I$2=$E55,$D55,IF(I$2>I$257,0,IF($C55=I$2,"PAGAR"&" "&TEXT($B55," #.##0,00"),IF($C55=-1,"PAGAR"&" "&TEXT($B55," #.##0,00"),0)))) -> 0 | J55: =+IF(J$2=$E55,$D55,IF(J$2>J$257,0,IF($C55=J$2,"PAGAR"&" "&TEXT($B55," #.##0,00"),0))) -> 0 | K55: =+IF(K$2=$E55,$D55,IF(K$2>K$257,0,IF($C55=K$2,"PAGAR"&" "&TEXT($B55," #.##0,00"),0))) -> 0 | L55: =+IF(L$2=$E55,$D55,IF(L$2>L$257,0,IF($C55=L$2,"PAGAR"&" "&TEXT($B55," #.##0,00"),0))) -> 0 | M55: =+IF(M$2=$E55,$D55,IF(M$2>M$257,0,IF($C55=M$2,"PAGAR"&" "&TEXT($B55," #.##0,00"),0))) -> 0 | N55: =+IF(N$2=$E55,$D55,IF(N$2>N$257,0,IF($C55=N$2,"PAGAR"&" "&TEXT($B55," #.##0,00"),0))) -> 0 | O55: =+IF(O$2=$E55,$D55,IF(O$2>O$257,0,IF($C55=O$2,"PAGAR"&" "&TEXT($B55," #.##0,00"),0))) -> 0 | P55: =+IF(P$2=$E55,$D55,IF(P$2>P$257,0,IF($C55=P$2,"PAGAR"&" "&TEXT($B55," #.##0,00"),0))) -> 0 | Q55: =+IF(Q$2=$E55,$D55,IF(Q$2>Q$257,0,IF($C55=Q$2,"PAGAR"&" "&TEXT($B55," #.##0,00"),0))) -> 0 | ... AM55: =+IF(AM$2=$E55,$D55,IF(AM$2>AM$257,0,IF($C55=AM$2,"PAGAR"&" "&TEXT($B55," #.##0,00"),0))) -> 0 | AN55: =+IF(F55<0,-F55,0) -> 0 | AO55: =+IF(AND(C55=0,B55>0),B55,0) -> 0
F56: =+IF(TODAY()<DATEVALUE(1&D$1&E$1),0,IF(C56>0,IF(C56-SUM(I$255:AM$255)<0,B56-SUM(I56:AM56,0),0),0))+IF(C56=-1,B56-SUM(J56:AM56)) -> 0 | G56: =+IF(B56=0,"-",D56/B56) -> - | I56: =IF(I$2=$E56,$D56,IF(I$2>I$257,0,IF($C56=I$2,"PAGAR"&" "&TEXT($B56," #.##0,00"),IF($C56=-1,"PAGAR"&" "&TEXT($B56," #.##0,00"),0)))) -> 0 | J56: =+IF(J$2=$E56,$D56,IF(J$2>J$257,0,IF($C56=J$2,"PAGAR"&" "&TEXT($B56," #.##0,00"),0))) -> 0 | K56: =+IF(K$2=$E56,$D56,IF(K$2>K$257,0,IF($C56=K$2,"PAGAR"&" "&TEXT($B56," #.##0,00"),0))) -> 0 | L56: =+IF(L$2=$E56,$D56,IF(L$2>L$257,0,IF($C56=L$2,"PAGAR"&" "&TEXT($B56," #.##0,00"),0))) -> 0 | M56: =+IF(M$2=$E56,$D56,IF(M$2>M$257,0,IF($C56=M$2,"PAGAR"&" "&TEXT($B56," #.##0,00"),0))) -> 0 | N56: =+IF(N$2=$E56,$D56,IF(N$2>N$257,0,IF($C56=N$2,"PAGAR"&" "&TEXT($B56," #.##0,00"),0))) -> 0 | O56: =+IF(O$2=$E56,$D56,IF(O$2>O$257,0,IF($C56=O$2,"PAGAR"&" "&TEXT($B56," #.##0,00"),0))) -> 0 | P56: =+IF(P$2=$E56,$D56,IF(P$2>P$257,0,IF($C56=P$2,"PAGAR"&" "&TEXT($B56," #.##0,00"),0))) -> 0 | Q56: =+IF(Q$2=$E56,$D56,IF(Q$2>Q$257,0,IF($C56=Q$2,"PAGAR"&" "&TEXT($B56," #.##0,00"),0))) -> 0 | ... AM56: =+IF(AM$2=$E56,$D56,IF(AM$2>AM$257,0,IF($C56=AM$2,"PAGAR"&" "&TEXT($B56," #.##0,00"),0))) -> 0 | AN56: =+IF(F56<0,-F56,0) -> 0 | AO56: =+IF(AND(C56=0,B56>0),B56,0) -> 0
F57: =+IF(TODAY()<DATEVALUE(1&D$1&E$1),0,IF(C57>0,IF(C57-SUM(I$255:AM$255)<0,B57-SUM(I57:AM57,0),0),0))+IF(C57=-1,B57-SUM(J57:AM57)) -> 0 | G57: =+IF(B57=0,"-",D57/B57) -> - | I57: =IF(I$2=$E57,$D57,IF(I$2>I$257,0,IF($C57=I$2,"PAGAR"&" "&TEXT($B57," #.##0,00"),IF($C57=-1,"PAGAR"&" "&TEXT($B57," #.##0,00"),0)))) -> 0 | J57: =+IF(J$2=$E57,$D57,IF(J$2>J$257,0,IF($C57=J$2,"PAGAR"&" "&TEXT($B57," #.##0,00"),0))) -> 0 | K57: =+IF(K$2=$E57,$D57,IF(K$2>K$257,0,IF($C57=K$2,"PAGAR"&" "&TEXT($B57," #.##0,00"),0))) -> 0 | L57: =+IF(L$2=$E57,$D57,IF(L$2>L$257,0,IF($C57=L$2,"PAGAR"&" "&TEXT($B57," #.##0,00"),0))) -> 0 | M57: =+IF(M$2=$E57,$D57,IF(M$2>M$257,0,IF($C57=M$2,"PAGAR"&" "&TEXT($B57," #.##0,00"),0))) -> 0 | N57: =+IF(N$2=$E57,$D57,IF(N$2>N$257,0,IF($C57=N$2,"PAGAR"&" "&TEXT($B57," #.##0,00"),0))) -> 0 | O57: =+IF(O$2=$E57,$D57,IF(O$2>O$257,0,IF($C57=O$2,"PAGAR"&" "&TEXT($B57," #.##0,00"),0))) -> 0 | P57: =+IF(P$2=$E57,$D57,IF(P$2>P$257,0,IF($C57=P$2,"PAGAR"&" "&TEXT($B57," #.##0,00"),0))) -> 0 | Q57: =+IF(Q$2=$E57,$D57,IF(Q$2>Q$257,0,IF($C57=Q$2,"PAGAR"&" "&TEXT($B57," #.##0,00"),0))) -> 0 | ... AM57: =+IF(AM$2=$E57,$D57,IF(AM$2>AM$257,0,IF($C57=AM$2,"PAGAR"&" "&TEXT($B57," #.##0,00"),0))) -> 0 | AN57: =+IF(F57<0,-F57,0) -> 0 | AO57: =+IF(AND(C57=0,B57>0),B57,0) -> 0
F58: =+IF(TODAY()<DATEVALUE(1&D$1&E$1),0,IF(C58>0,IF(C58-SUM(I$255:AM$255)<0,B58-SUM(I58:AM58,0),0),0))+IF(C58=-1,B58-SUM(J58:AM58)) -> 0 | G58: =+IF(B58=0,"-",D58/B58) -> - | I58: =IF(I$2=$E58,$D58,IF(I$2>I$257,0,IF($C58=I$2,"PAGAR"&" "&TEXT($B58," #.##0,00"),IF($C58=-1,"PAGAR"&" "&TEXT($B58," #.##0,00"),0)))) -> 0 | J58: =+IF(J$2=$E58,$D58,IF(J$2>J$257,0,IF($C58=J$2,"PAGAR"&" "&TEXT($B58," #.##0,00"),0))) -> 0 | K58: =+IF(K$2=$E58,$D58,IF(K$2>K$257,0,IF($C58=K$2,"PAGAR"&" "&TEXT($B58," #.##0,00"),0))) -> 0 | L58: =+IF(L$2=$E58,$D58,IF(L$2>L$257,0,IF($C58=L$2,"PAGAR"&" "&TEXT($B58," #.##0,00"),0))) -> 0 | M58: =+IF(M$2=$E58,$D58,IF(M$2>M$257,0,IF($C58=M$2,"PAGAR"&" "&TEXT($B58," #.##0,00"),0))) -> 0 | N58: =+IF(N$2=$E58,$D58,IF(N$2>N$257,0,IF($C58=N$2,"PAGAR"&" "&TEXT($B58," #.##0,00"),0))) -> 0 | O58: =+IF(O$2=$E58,$D58,IF(O$2>O$257,0,IF($C58=O$2,"PAGAR"&" "&TEXT($B58," #.##0,00"),0))) -> 0 | P58: =+IF(P$2=$E58,$D58,IF(P$2>P$257,0,IF($C58=P$2,"PAGAR"&" "&TEXT($B58," #.##0,00"),0))) -> 0 | Q58: =+IF(Q$2=$E58,$D58,IF(Q$2>Q$257,0,IF($C58=Q$2,"PAGAR"&" "&TEXT($B58," #.##0,00"),0))) -> 0 | ... AM58: =+IF(AM$2=$E58,$D58,IF(AM$2>AM$257,0,IF($C58=AM$2,"PAGAR"&" "&TEXT($B58," #.##0,00"),0))) -> 0 | AN58: =+IF(F58<0,-F58,0) -> 0 | AO58: =+IF(AND(C58=0,B58>0),B58,0) -> 0
F59: =+IF(TODAY()<DATEVALUE(1&D$1&E$1),0,IF(C59>0,IF(C59-SUM(I$255:AM$255)<0,B59-SUM(I59:AM59,0),0),0))+IF(C59=-1,B59-SUM(J59:AM59)) -> 0 | G59: =+IF(B59=0,"-",D59/B59) -> - | I59: =IF(I$2=$E59,$D59,IF(I$2>I$257,0,IF($C59=I$2,"PAGAR"&" "&TEXT($B59," #.##0,00"),IF($C59=-1,"PAGAR"&" "&TEXT($B59," #.##0,00"),0)))) -> 0 | J59: =+IF(J$2=$E59,$D59,IF(J$2>J$257,0,IF($C59=J$2,"PAGAR"&" "&TEXT($B59," #.##0,00"),0))) -> 0 | K59: =+IF(K$2=$E59,$D59,IF(K$2>K$257,0,IF($C59=K$2,"PAGAR"&" "&TEXT($B59," #.##0,00"),0))) -> 0 | L59: =+IF(L$2=$E59,$D59,IF(L$2>L$257,0,IF($C59=L$2,"PAGAR"&" "&TEXT($B59," #.##0,00"),0))) -> 0 | M59: =+IF(M$2=$E59,$D59,IF(M$2>M$257,0,IF($C59=M$2,"PAGAR"&" "&TEXT($B59," #.##0,00"),0))) -> 0 | N59: =+IF(N$2=$E59,$D59,IF(N$2>N$257,0,IF($C59=N$2,"PAGAR"&" "&TEXT($B59," #.##0,00"),0))) -> 0 | O59: =+IF(O$2=$E59,$D59,IF(O$2>O$257,0,IF($C59=O$2,"PAGAR"&" "&TEXT($B59," #.##0,00"),0))) -> 0 | P59: =+IF(P$2=$E59,$D59,IF(P$2>P$257,0,IF($C59=P$2,"PAGAR"&" "&TEXT($B59," #.##0,00"),0))) -> 0 | Q59: =+IF(Q$2=$E59,$D59,IF(Q$2>Q$257,0,IF($C59=Q$2,"PAGAR"&" "&TEXT($B59," #.##0,00"),0))) -> 0 | ... AM59: =+IF(AM$2=$E59,$D59,IF(AM$2>AM$257,0,IF($C59=AM$2,"PAGAR"&" "&TEXT($B59," #.##0,00"),0))) -> 0 | AN59: =+IF(F59<0,-F59,0) -> 0 | AO59: =+IF(AND(C59=0,B59>0),B59,0) -> 0
F60: =+IF(TODAY()<DATEVALUE(1&D$1&E$1),0,IF(C60>0,IF(C60-SUM(I$255:AM$255)<0,B60-SUM(I60:AM60,0),0),0))+IF(C60=-1,B60-SUM(J60:AM60)) -> 0 | G60: =+IF(B60=0,"-",D60/B60) -> - | I60: =IF(I$2=$E60,$D60,IF(I$2>I$257,0,IF($C60=I$2,"PAGAR"&" "&TEXT($B60," #.##0,00"),IF($C60=-1,"PAGAR"&" "&TEXT($B60," #.##0,00"),0)))) -> 0 | J60: =+IF(J$2=$E60,$D60,IF(J$2>J$257,0,IF($C60=J$2,"PAGAR"&" "&TEXT($B60," #.##0,00"),0))) -> 0 | K60: =+IF(K$2=$E60,$D60,IF(K$2>K$257,0,IF($C60=K$2,"PAGAR"&" "&TEXT($B60," #.##0,00"),0))) -> 0 | L60: =+IF(L$2=$E60,$D60,IF(L$2>L$257,0,IF($C60=L$2,"PAGAR"&" "&TEXT($B60," #.##0,00"),0))) -> 0 | M60: =+IF(M$2=$E60,$D60,IF(M$2>M$257,0,IF($C60=M$2,"PAGAR"&" "&TEXT($B60," #.##0,00"),0))) -> 0 | N60: =+IF(N$2=$E60,$D60,IF(N$2>N$257,0,IF($C60=N$2,"PAGAR"&" "&TEXT($B60," #.##0,00"),0))) -> 0 | O60: =+IF(O$2=$E60,$D60,IF(O$2>O$257,0,IF($C60=O$2,"PAGAR"&" "&TEXT($B60," #.##0,00"),0))) -> 0 | P60: =+IF(P$2=$E60,$D60,IF(P$2>P$257,0,IF($C60=P$2,"PAGAR"&" "&TEXT($B60," #.##0,00"),0))) -> 0 | Q60: =+IF(Q$2=$E60,$D60,IF(Q$2>Q$257,0,IF($C60=Q$2,"PAGAR"&" "&TEXT($B60," #.##0,00"),0))) -> 0 | ... AM60: =+IF(AM$2=$E60,$D60,IF(AM$2>AM$257,0,IF($C60=AM$2,"PAGAR"&" "&TEXT($B60," #.##0,00"),0))) -> 0 | AN60: =+IF(F60<0,-F60,0) -> 0 | AO60: =+IF(AND(C60=0,B60>0),B60,0) -> 0
F61: =+IF(TODAY()<DATEVALUE(1&D$1&E$1),0,IF(C61>0,IF(C61-SUM(I$255:AM$255)<0,B61-SUM(I61:AM61,0),0),0))+IF(C61=-1,B61-SUM(J61:AM61)) -> 0 | G61: =+IF(B61=0,"-",D61/B61) -> - | I61: =IF(I$2=$E61,$D61,IF(I$2>I$257,0,IF($C61=I$2,"PAGAR"&" "&TEXT($B61," #.##0,00"),IF($C61=-1,"PAGAR"&" "&TEXT($B61," #.##0,00"),0)))) -> 0 | J61: =+IF(J$2=$E61,$D61,IF(J$2>J$257,0,IF($C61=J$2,"PAGAR"&" "&TEXT($B61," #.##0,00"),0))) -> 0 | K61: =+IF(K$2=$E61,$D61,IF(K$2>K$257,0,IF($C61=K$2,"PAGAR"&" "&TEXT($B61," #.##0,00"),0))) -> 0 | L61: =+IF(L$2=$E61,$D61,IF(L$2>L$257,0,IF($C61=L$2,"PAGAR"&" "&TEXT($B61," #.##0,00"),0))) -> 0 | M61: =+IF(M$2=$E61,$D61,IF(M$2>M$257,0,IF($C61=M$2,"PAGAR"&" "&TEXT($B61," #.##0,00"),0))) -> 0 | N61: =+IF(N$2=$E61,$D61,IF(N$2>N$257,0,IF($C61=N$2,"PAGAR"&" "&TEXT($B61," #.##0,00"),0))) -> 0 | O61: =+IF(O$2=$E61,$D61,IF(O$2>O$257,0,IF($C61=O$2,"PAGAR"&" "&TEXT($B61," #.##0,00"),0))) -> 0 | P61: =+IF(P$2=$E61,$D61,IF(P$2>P$257,0,IF($C61=P$2,"PAGAR"&" "&TEXT($B61," #.##0,00"),0))) -> 0 | Q61: =+IF(Q$2=$E61,$D61,IF(Q$2>Q$257,0,IF($C61=Q$2,"PAGAR"&" "&TEXT($B61," #.##0,00"),0))) -> 0 | ... AM61: =+IF(AM$2=$E61,$D61,IF(AM$2>AM$257,0,IF($C61=AM$2,"PAGAR"&" "&TEXT($B61," #.##0,00"),0))) -> 0 | AN61: =+IF(F61<0,-F61,0) -> 0 | AO61: =+IF(AND(C61=0,B61>0),B61,0) -> 0
F62: =+IF(TODAY()<DATEVALUE(1&D$1&E$1),0,IF(C62>0,IF(C62-SUM(I$255:AM$255)<0,B62-SUM(I62:AM62,0),0),0))+IF(C62=-1,B62-SUM(J62:AM62)) -> 0 | G62: =+IF(B62=0,"-",D62/B62) -> - | I62: =IF(I$2=$E62,$D62,IF(I$2>I$257,0,IF($C62=I$2,"PAGAR"&" "&TEXT($B62," #.##0,00"),IF($C62=-1,"PAGAR"&" "&TEXT($B62," #.##0,00"),0)))) -> 0 | J62: =+IF(J$2=$E62,$D62,IF(J$2>J$257,0,IF($C62=J$2,"PAGAR"&" "&TEXT($B62," #.##0,00"),0))) -> 0 | K62: =+IF(K$2=$E62,$D62,IF(K$2>K$257,0,IF($C62=K$2,"PAGAR"&" "&TEXT($B62," #.##0,00"),0))) -> 0 | L62: =+IF(L$2=$E62,$D62,IF(L$2>L$257,0,IF($C62=L$2,"PAGAR"&" "&TEXT($B62," #.##0,00"),0))) -> 0 | M62: =+IF(M$2=$E62,$D62,IF(M$2>M$257,0,IF($C62=M$2,"PAGAR"&" "&TEXT($B62," #.##0,00"),0))) -> 0 | N62: =+IF(N$2=$E62,$D62,IF(N$2>N$257,0,IF($C62=N$2,"PAGAR"&" "&TEXT($B62," #.##0,00"),0))) -> 0 | O62: =+IF(O$2=$E62,$D62,IF(O$2>O$257,0,IF($C62=O$2,"PAGAR"&" "&TEXT($B62," #.##0,00"),0))) -> 0 | P62: =+IF(P$2=$E62,$D62,IF(P$2>P$257,0,IF($C62=P$2,"PAGAR"&" "&TEXT($B62," #.##0,00"),0))) -> 0 | Q62: =+IF(Q$2=$E62,$D62,IF(Q$2>Q$257,0,IF($C62=Q$2,"PAGAR"&" "&TEXT($B62," #.##0,00"),0))) -> 0 | ... AM62: =+IF(AM$2=$E62,$D62,IF(AM$2>AM$257,0,IF($C62=AM$2,"PAGAR"&" "&TEXT($B62," #.##0,00"),0))) -> 0 | AN62: =+IF(F62<0,-F62,0) -> 0 | AO62: =+IF(AND(C62=0,B62>0),B62,0) -> 0
F63: =+IF(TODAY()<DATEVALUE(1&D$1&E$1),0,IF(C63>0,IF(C63-SUM(I$255:AM$255)<0,B63-SUM(I63:AM63,0),0),0))+IF(C63=-1,B63-SUM(J63:AM63)) -> 0 | G63: =+IF(B63=0,"-",D63/B63) -> - | I63: =IF(I$2=$E63,$D63,IF(I$2>I$257,0,IF($C63=I$2,"PAGAR"&" "&TEXT($B63," #.##0,00"),IF($C63=-1,"PAGAR"&" "&TEXT($B63," #.##0,00"),0)))) -> 0 | J63: =+IF(J$2=$E63,$D63,IF(J$2>J$257,0,IF($C63=J$2,"PAGAR"&" "&TEXT($B63," #.##0,00"),0))) -> 0 | K63: =+IF(K$2=$E63,$D63,IF(K$2>K$257,0,IF($C63=K$2,"PAGAR"&" "&TEXT($B63," #.##0,00"),0))) -> 0 | L63: =+IF(L$2=$E63,$D63,IF(L$2>L$257,0,IF($C63=L$2,"PAGAR"&" "&TEXT($B63," #.##0,00"),0))) -> 0 | M63: =+IF(M$2=$E63,$D63,IF(M$2>M$257,0,IF($C63=M$2,"PAGAR"&" "&TEXT($B63," #.##0,00"),0))) -> 0 | N63: =+IF(N$2=$E63,$D63,IF(N$2>N$257,0,IF($C63=N$2,"PAGAR"&" "&TEXT($B63," #.##0,00"),0))) -> 0 | O63: =+IF(O$2=$E63,$D63,IF(O$2>O$257,0,IF($C63=O$2,"PAGAR"&" "&TEXT($B63," #.##0,00"),0))) -> 0 | P63: =+IF(P$2=$E63,$D63,IF(P$2>P$257,0,IF($C63=P$2,"PAGAR"&" "&TEXT($B63," #.##0,00"),0))) -> 0 | Q63: =+IF(Q$2=$E63,$D63,IF(Q$2>Q$257,0,IF($C63=Q$2,"PAGAR"&" "&TEXT($B63," #.##0,00"),0))) -> 0 | ... AM63: =+IF(AM$2=$E63,$D63,IF(AM$2>AM$257,0,IF($C63=AM$2,"PAGAR"&" "&TEXT($B63," #.##0,00"),0))) -> 0 | AN63: =+IF(F63<0,-F63,0) -> 0 | AO63: =+IF(AND(C63=0,B63>0),B63,0) -> 0
... F66: =+IF(TODAY()<DATEVALUE(1&D$1&E$1),0,IF(C66>0,IF(C66-SUM(I$255:AM$255)<0,B66-SUM(I66:AM66,0),0),0))+IF(C66=-1,B66-SUM(J66:AM66)) -> 0 | G66: =+IF(B66=0,"-",D66/B66) -> - | I66: =IF(I$2=$E66,$D66,IF(I$2>I$257,0,IF($C66=I$2,"PAGAR"&" "&TEXT($B66," #.##0,00"),IF($C66=-1,"PAGAR"&" "&TEXT($B66," #.##0,00"),0)))) -> 0 | J66: =+IF(J$2=$E66,$D66,IF(J$2>J$257,0,IF($C66=J$2,"PAGAR"&" "&TEXT($B66," #.##0,00"),0))) -> 0 | K66: =+IF(K$2=$E66,$D66,IF(K$2>K$257,0,IF($C66=K$2,"PAGAR"&" "&TEXT($B66," #.##0,00"),0))) -> 0 | L66: =+IF(L$2=$E66,$D66,IF(L$2>L$257,0,IF($C66=L$2,"PAGAR"&" "&TEXT($B66," #.##0,00"),0))) -> 0 | M66: =+IF(M$2=$E66,$D66,IF(M$2>M$257,0,IF($C66=M$2,"PAGAR"&" "&TEXT($B66," #.##0,00"),0))) -> 0 | N66: =+IF(N$2=$E66,$D66,IF(N$2>N$257,0,IF($C66=N$2,"PAGAR"&" "&TEXT($B66," #.##0,00"),0))) -> 0 | O66: =+IF(O$2=$E66,$D66,IF(O$2>O$257,0,IF($C66=O$2,"PAGAR"&" "&TEXT($B66," #.##0,00"),0))) -> 0 | P66: =+IF(P$2=$E66,$D66,IF(P$2>P$257,0,IF($C66=P$2,"PAGAR"&" "&TEXT($B66," #.##0,00"),0))) -> 0 | Q66: =+IF(Q$2=$E66,$D66,IF(Q$2>Q$257,0,IF($C66=Q$2,"PAGAR"&" "&TEXT($B66," #.##0,00"),0))) -> 0 | ... AM66: =+IF(AM$2=$E66,$D66,IF(AM$2>AM$257,0,IF($C66=AM$2,"PAGAR"&" "&TEXT($B66," #.##0,00"),0))) -> 0 | AN66: =+IF(F66<0,-F66,0) -> 0 | AO66: =+IF(AND(C66=0,B66>0),B66,0) -> 0
A67: Total de despesas previstas (Plan 2) | B67: =+SUM(B46:B66) -> 1000 | D67: =+SUM(D46:D66) -> 0 | F67: =+SUMIF(F46:F66,">0") -> 500 | G67: =+IF(B67=0,"-",D67/B67) -> 0 | I67: =+PLAN2!H68 -> 0 | J67: =+PLAN2!I68 -> 500 | K67: =+PLAN2!J68 -> 0 | L67: =+PLAN2!K68 -> 0 | M67: =+PLAN2!L68 -> 0 | N67: =+PLAN2!M68 -> 0 | O67: =+PLAN2!N68 -> 0 | P67: =+PLAN2!O68 -> 0 | ... AM67: =+PLAN2!AL68 -> 0 | AN67: =SUM(AN46:AN66) -> 0
A68: MORADIA
F69: =+IF(TODAY()<DATEVALUE(1&D$1&E$1),0,IF(C69>0,IF(C69-SUM(I$255:AM$255)<0,B69-SUM(I69:AM69,0),0),0))+IF(C69=-1,B69-SUM(J69:AM69)) -> 0 | G69: =+IF(B69=0,"-",D69/B69) -> - | I69: =IF(I$2=$E69,$D69,IF(I$2>I$257,0,IF($C69=I$2,"PAGAR"&" "&TEXT($B69," #.##0,00"),IF($C69=-1,"PAGAR"&" "&TEXT($B69," #.##0,00"),0)))) -> 0 | J69: =+IF(J$2=$E69,$D69,IF(J$2>J$257,0,IF($C69=J$2,"PAGAR"&" "&TEXT($B69," #.##0,00"),0))) -> 0 | K69: =+IF(K$2=$E69,$D69,IF(K$2>K$257,0,IF($C69=K$2,"PAGAR"&" "&TEXT($B69," #.##0,00"),0))) -> 0 | L69: =+IF(L$2=$E69,$D69,IF(L$2>L$257,0,IF($C69=L$2,"PAGAR"&" "&TEXT($B69," #.##0,00"),0))) -> 0 | M69: =+IF(M$2=$E69,$D69,IF(M$2>M$257,0,IF($C69=M$2,"PAGAR"&" "&TEXT($B69," #.##0,00"),0))) -> 0 | N69: =+IF(N$2=$E69,$D69,IF(N$2>N$257,0,IF($C69=N$2,"PAGAR"&" "&TEXT($B69," #.##0,00"),0))) -> 0 | O69: =+IF(O$2=$E69,$D69,IF(O$2>O$257,0,IF($C69=O$2,"PAGAR"&" "&TEXT($B69," #.##0,00"),0))) -> 0 | P69: =+IF(P$2=$E69,$D69,IF(P$2>P$257,0,IF($C69=P$2,"PAGAR"&" "&TEXT($B69," #.##0,00"),0))) -> 0 | Q69: =+IF(Q$2=$E69,$D69,IF(Q$2>Q$257,0,IF($C69=Q$2,"PAGAR"&" "&TEXT($B69," #.##0,00"),0))) -> 0 | ... AM69: =+IF(AM$2=$E69,$D69,IF(AM$2>AM$257,0,IF($C69=AM$2,"PAGAR"&" "&TEXT($B69," #.##0,00"),0))) -> 0 | AN69: =+IF(F69<0,-F69,0) -> 0 | AO69: =+IF(AND(C69=0,B69>0),B69,0) -> 0
A70: IPTU Reserva | B70: 524.07 | C70: 27 | F70: =+IF(TODAY()<DATEVALUE(1&D$1&E$1),0,IF(C70>0,IF(C70-SUM(I$255:AM$255)<0,B70-SUM(I70:AM70,0),0),0))+IF(C70=-1,B70-SUM(J70:AM70)) -> 0 | G70: =+IF(B70=0,"-",D70/B70) -> 0 | I70: =IF(I$2=$E70,$D70,IF(I$2>I$257,0,IF($C70=I$2,"PAGAR"&" "&TEXT($B70," #.##0,00"),IF($C70=-1,"PAGAR"&" "&TEXT($B70," #.##0,00"),0)))) -> 0 | J70: =+IF(J$2=$E70,$D70,IF(J$2>J$257,0,IF($C70=J$2,"PAGAR"&" "&TEXT($B70," #.##0,00"),0))) -> 0 | K70: =+IF(K$2=$E70,$D70,IF(K$2>K$257,0,IF($C70=K$2,"PAGAR"&" "&TEXT($B70," #.##0,00"),0))) -> 0 | L70: =+IF(L$2=$E70,$D70,IF(L$2>L$257,0,IF($C70=L$2,"PAGAR"&" "&TEXT($B70," #.##0,00"),0))) -> 0 | M70: =+IF(M$2=$E70,$D70,IF(M$2>M$257,0,IF($C70=M$2,"PAGAR"&" "&TEXT($B70," #.##0,00"),0))) -> 0 | N70: =+IF(N$2=$E70,$D70,IF(N$2>N$257,0,IF($C70=N$2,"PAGAR"&" "&TEXT($B70," #.##0,00"),0))) -> 0 | O70: =+IF(O$2=$E70,$D70,IF(O$2>O$257,0,IF($C70=O$2,"PAGAR"&" "&TEXT($B70," #.##0,00"),0))) -> 0 | P70: =+IF(P$2=$E70,$D70,IF(P$2>P$257,0,IF($C70=P$2,"PAGAR"&" "&TEXT($B70," #.##0,00"),0))) -> 0 | Q70: =+IF(Q$2=$E70,$D70,IF(Q$2>Q$257,0,IF($C70=Q$2,"PAGAR"&" "&TEXT($B70," #.##0,00"),0))) -> 0 | ... AM70: =+IF(AM$2=$E70,$D70,IF(AM$2>AM$257,0,IF($C70=AM$2,"PAGAR"&" "&TEXT($B70," #.##0,00"),0))) -> 0 | AN70: =+IF(F70<0,-F70,0) -> 0 | AO70: =+IF(AND(C70=0,B70>0),B70,0) -> 0
A71: Condomínio Reserva (Nelson58@) | B71: 1504.62 | C71: 10 | F71: =+IF(TODAY()<DATEVALUE(1&D$1&E$1),0,IF(C71>0,IF(C71-SUM(I$255:AM$255)<0,B71-SUM(I71:AM71,0),0),0))+IF(C71=-1,B71-SUM(J71:AM71)) -> 1504.62 | G71: =+IF(B71=0,"-",D71/B71) -> 0 | I71: =IF(I$2=$E71,$D71,IF(I$2>I$257,0,IF($C71=I$2,"PAGAR"&" "&TEXT($B71," #.##0,00"),IF($C71=-1,"PAGAR"&" "&TEXT($B71," #.##0,00"),0)))) -> 0 | J71: =+IF(J$2=$E71,$D71,IF(J$2>J$257,0,IF($C71=J$2,"PAGAR"&" "&TEXT($B71," #.##0,00"),0))) -> 0 | K71: =+IF(K$2=$E71,$D71,IF(K$2>K$257,0,IF($C71=K$2,"PAGAR"&" "&TEXT($B71," #.##0,00"),0))) -> 0 | L71: =+IF(L$2=$E71,$D71,IF(L$2>L$257,0,IF($C71=L$2,"PAGAR"&" "&TEXT($B71," #.##0,00"),0))) -> 0 | M71: =+IF(M$2=$E71,$D71,IF(M$2>M$257,0,IF($C71=M$2,"PAGAR"&" "&TEXT($B71," #.##0,00"),0))) -> 0 | N71: =+IF(N$2=$E71,$D71,IF(N$2>N$257,0,IF($C71=N$2,"PAGAR"&" "&TEXT($B71," #.##0,00"),0))) -> 0 | O71: =+IF(O$2=$E71,$D71,IF(O$2>O$257,0,IF($C71=O$2,"PAGAR"&" "&TEXT($B71," #.##0,00"),0))) -> 0 | P71: =+IF(P$2=$E71,$D71,IF(P$2>P$257,0,IF($C71=P$2,"PAGAR"&" "&TEXT($B71," #.##0,00"),0))) -> 0 | Q71: =+IF(Q$2=$E71,$D71,IF(Q$2>Q$257,0,IF($C71=Q$2,"PAGAR"&" "&TEXT($B71," #.##0,00"),0))) -> 0 | ... AM71: =+IF(AM$2=$E71,$D71,IF(AM$2>AM$257,0,IF($C71=AM$2,"PAGAR"&" "&TEXT($B71," #.##0,00"),0))) -> 0 | AN71: =+IF(F71<0,-F71,0) -> 0 | AO71: =+IF(AND(C71=0,B71>0),B71,0) -> 0
A72: Condomínio Reserva - 5 a parcelar - aprox | B72: 6000 | C72: 0 | F72: =+IF(TODAY()<DATEVALUE(1&D$1&E$1),0,IF(C72>0,IF(C72-SUM(I$255:AM$255)<0,B72-SUM(I72:AM72,0),0),0))+IF(C72=-1,B72-SUM(J72:AM72)) -> 0 | G72: =+IF(B72=0,"-",D72/B72) -> 0 | I72: =IF(I$2=$E72,$D72,IF(I$2>I$257,0,IF($C72=I$2,"PAGAR"&" "&TEXT($B72," #.##0,00"),IF($C72=-1,"PAGAR"&" "&TEXT($B72," #.##0,00"),0)))) -> 0 | J72: =+IF(J$2=$E72,$D72,IF(J$2>J$257,0,IF($C72=J$2,"PAGAR"&" "&TEXT($B72," #.##0,00"),0))) -> 0 | K72: =+IF(K$2=$E72,$D72,IF(K$2>K$257,0,IF($C72=K$2,"PAGAR"&" "&TEXT($B72," #.##0,00"),0))) -> 0 | L72: =+IF(L$2=$E72,$D72,IF(L$2>L$257,0,IF($C72=L$2,"PAGAR"&" "&TEXT($B72," #.##0,00"),0))) -> 0 | M72: =+IF(M$2=$E72,$D72,IF(M$2>M$257,0,IF($C72=M$2,"PAGAR"&" "&TEXT($B72," #.##0,00"),0))) -> 0 | N72: =+IF(N$2=$E72,$D72,IF(N$2>N$257,0,IF($C72=N$2,"PAGAR"&" "&TEXT($B72," #.##0,00"),0))) -> 0 | O72: =+IF(O$2=$E72,$D72,IF(O$2>O$257,0,IF($C72=O$2,"PAGAR"&" "&TEXT($B72," #.##0,00"),0))) -> 0 | P72: =+IF(P$2=$E72,$D72,IF(P$2>P$257,0,IF($C72=P$2,"PAGAR"&" "&TEXT($B72," #.##0,00"),0))) -> 0 | Q72: =+IF(Q$2=$E72,$D72,IF(Q$2>Q$257,0,IF($C72=Q$2,"PAGAR"&" "&TEXT($B72," #.##0,00"),0))) -> 0 | ... AM72: =+IF(AM$2=$E72,$D72,IF(AM$2>AM$257,0,IF($C72=AM$2,"PAGAR"&" "&TEXT($B72," #.##0,00"),0))) -> 0 | AN72: =+IF(F72<0,-F72,0) -> 0 | AO72: =+IF(AND(C72=0,B72>0),B72,0) -> 6000
A73: Condomínio Reserva - 3 em atraso | B73: 3500 | C73: 0 | F73: =+IF(TODAY()<DATEVALUE(1&D$1&E$1),0,IF(C73>0,IF(C73-SUM(I$255:AM$255)<0,B73-SUM(I73:AM73,0),0),0))+IF(C73=-1,B73-SUM(J73:AM73)) -> 0 | G73: =+IF(B73=0,"-",D73/B73) -> 0 | I73: =IF(I$2=$E73,$D73,IF(I$2>I$257,0,IF($C73=I$2,"PAGAR"&" "&TEXT($B73," #.##0,00"),IF($C73=-1,"PAGAR"&" "&TEXT($B73," #.##0,00"),0)))) -> 0 | J73: =+IF(J$2=$E73,$D73,IF(J$2>J$257,0,IF($C73=J$2,"PAGAR"&" "&TEXT($B73," #.##0,00"),0))) -> 0 | K73: =+IF(K$2=$E73,$D73,IF(K$2>K$257,0,IF($C73=K$2,"PAGAR"&" "&TEXT($B73," #.##0,00"),0))) -> 0 | L73: =+IF(L$2=$E73,$D73,IF(L$2>L$257,0,IF($C73=L$2,"PAGAR"&" "&TEXT($B73," #.##0,00"),0))) -> 0 | M73: =+IF(M$2=$E73,$D73,IF(M$2>M$257,0,IF($C73=M$2,"PAGAR"&" "&TEXT($B73," #.##0,00"),0))) -> 0 | N73: =+IF(N$2=$E73,$D73,IF(N$2>N$257,0,IF($C73=N$2,"PAGAR"&" "&TEXT($B73," #.##0,00"),0))) -> 0 | O73: =+IF(O$2=$E73,$D73,IF(O$2>O$257,0,IF($C73=O$2,"PAGAR"&" "&TEXT($B73," #.##0,00"),0))) -> 0 | P73: =+IF(P$2=$E73,$D73,IF(P$2>P$257,0,IF($C73=P$2,"PAGAR"&" "&TEXT($B73," #.##0,00"),0))) -> 0 | Q73: =+IF(Q$2=$E73,$D73,IF(Q$2>Q$257,0,IF($C73=Q$2,"PAGAR"&" "&TEXT($B73," #.##0,00"),0))) -> 0 | ... AM73: =+IF(AM$2=$E73,$D73,IF(AM$2>AM$257,0,IF($C73=AM$2,"PAGAR"&" "&TEXT($B73," #.##0,00"),0))) -> 0 | AN73: =+IF(F73<0,-F73,0) -> 0 | AO73: =+IF(AND(C73=0,B73>0),B73,0) -> 3500
A74: Condomínio Lago 30/12 | B74: 2203.91 | C74: -1 | F74: =+IF(TODAY()<DATEVALUE(1&D$1&E$1),0,IF(C74>0,IF(C74-SUM(I$255:AM$255)<0,B74-SUM(I74:AM74,0),0),0))+IF(C74=-1,B74-SUM(J74:AM74)) -> 2203.91 | G74: =+IF(B74=0,"-",D74/B74) -> 0 | I74: =IF(I$2=$E74,$D74,IF(I$2>I$257,0,IF($C74=I$2,"PAGAR"&" "&TEXT($B74," #.##0,00"),IF($C74=-1,"PAGAR"&" "&TEXT($B74," #.##0,00"),0)))) -> PAGAR 2.203,91 | J74: =+IF(J$2=$E74,$D74,IF(J$2>J$257,0,IF($C74=J$2,"PAGAR"&" "&TEXT($B74," #.##0,00"),0))) -> 0 | K74: =+IF(K$2=$E74,$D74,IF(K$2>K$257,0,IF($C74=K$2,"PAGAR"&" "&TEXT($B74," #.##0,00"),0))) -> 0 | L74: =+IF(L$2=$E74,$D74,IF(L$2>L$257,0,IF($C74=L$2,"PAGAR"&" "&TEXT($B74," #.##0,00"),0))) -> 0 | M74: =+IF(M$2=$E74,$D74,IF(M$2>M$257,0,IF($C74=M$2,"PAGAR"&" "&TEXT($B74," #.##0,00"),0))) -> 0 | N74: =+IF(N$2=$E74,$D74,IF(N$2>N$257,0,IF($C74=N$2,"PAGAR"&" "&TEXT($B74," #.##0,00"),0))) -> 0 | O74: =+IF(O$2=$E74,$D74,IF(O$2>O$257,0,IF($C74=O$2,"PAGAR"&" "&TEXT($B74," #.##0,00"),0))) -> 0 | P74: =+IF(P$2=$E74,$D74,IF(P$2>P$257,0,IF($C74=P$2,"PAGAR"&" "&TEXT($B74," #.##0,00"),0))) -> 0 | Q74: =+IF(Q$2=$E74,$D74,IF(Q$2>Q$257,0,IF($C74=Q$2,"PAGAR"&" "&TEXT($B74," #.##0,00"),0))) -> 0 | ... AM74: =+IF(AM$2=$E74,$D74,IF(AM$2>AM$257,0,IF($C74=AM$2,"PAGAR"&" "&TEXT($B74," #.##0,00"),0))) -> 0 | AN74: =+IF(F74<0,-F74,0) -> 0 | AO74: =+IF(AND(C74=0,B74>0),B74,0) -> 0
A75: Condomínio Lago 01/09 aprox.(03/11 BBZ) | B75: 2200 | C75: 0 | F75: =+IF(TODAY()<DATEVALUE(1&D$1&E$1),0,IF(C75>0,IF(C75-SUM(I$255:AM$255)<0,B75-SUM(I75:AM75,0),0),0))+IF(C75=-1,B75-SUM(J75:AM75)) -> 0 | G75: =+IF(B75=0,"-",D75/B75) -> 0 | I75: =IF(I$2=$E75,$D75,IF(I$2>I$257,0,IF($C75=I$2,"PAGAR"&" "&TEXT($B75," #.##0,00"),IF($C75=-1,"PAGAR"&" "&TEXT($B75," #.##0,00"),0)))) -> 0 | J75: =+IF(J$2=$E75,$D75,IF(J$2>J$257,0,IF($C75=J$2,"PAGAR"&" "&TEXT($B75," #.##0,00"),0))) -> 0 | K75: =+IF(K$2=$E75,$D75,IF(K$2>K$257,0,IF($C75=K$2,"PAGAR"&" "&TEXT($B75," #.##0,00"),0))) -> 0 | L75: =+IF(L$2=$E75,$D75,IF(L$2>L$257,0,IF($C75=L$2,"PAGAR"&" "&TEXT($B75," #.##0,00"),0))) -> 0 | M75: =+IF(M$2=$E75,$D75,IF(M$2>M$257,0,IF($C75=M$2,"PAGAR"&" "&TEXT($B75," #.##0,00"),0))) -> 0 | N75: =+IF(N$2=$E75,$D75,IF(N$2>N$257,0,IF($C75=N$2,"PAGAR"&" "&TEXT($B75," #.##0,00"),0))) -> 0 | O75: =+IF(O$2=$E75,$D75,IF(O$2>O$257,0,IF($C75=O$2,"PAGAR"&" "&TEXT($B75," #.##0,00"),0))) -> 0 | P75: =+IF(P$2=$E75,$D75,IF(P$2>P$257,0,IF($C75=P$2,"PAGAR"&" "&TEXT($B75," #.##0,00"),0))) -> 0 | Q75: =+IF(Q$2=$E75,$D75,IF(Q$2>Q$257,0,IF($C75=Q$2,"PAGAR"&" "&TEXT($B75," #.##0,00"),0))) -> 0 | ... AM75: =+IF(AM$2=$E75,$D75,IF(AM$2>AM$257,0,IF($C75=AM$2,"PAGAR"&" "&TEXT($B75," #.##0,00"),0))) -> 0 | AN75: =+IF(F75<0,-F75,0) -> 0 | AO75: =+IF(AND(C75=0,B75>0),B75,0) -> 2200
A76: Naturgy - estimado | B76: 220 | C76: 15 | F76: =+IF(TODAY()<DATEVALUE(1&D$1&E$1),0,IF(C76>0,IF(C76-SUM(I$255:AM$255)<0,B76-SUM(I76:AM76,0),0),0))+IF(C76=-1,B76-SUM(J76:AM76)) -> 0 | G76: =+IF(B76=0,"-",D76/B76) -> 0 | I76: =IF(I$2=$E76,$D76,IF(I$2>I$257,0,IF($C76=I$2,"PAGAR"&" "&TEXT($B76," #.##0,00"),IF($C76=-1,"PAGAR"&" "&TEXT($B76," #.##0,00"),0)))) -> 0 | J76: =+IF(J$2=$E76,$D76,IF(J$2>J$257,0,IF($C76=J$2,"PAGAR"&" "&TEXT($B76," #.##0,00"),0))) -> 0 | K76: =+IF(K$2=$E76,$D76,IF(K$2>K$257,0,IF($C76=K$2,"PAGAR"&" "&TEXT($B76," #.##0,00"),0))) -> 0 | L76: =+IF(L$2=$E76,$D76,IF(L$2>L$257,0,IF($C76=L$2,"PAGAR"&" "&TEXT($B76," #.##0,00"),0))) -> 0 | M76: =+IF(M$2=$E76,$D76,IF(M$2>M$257,0,IF($C76=M$2,"PAGAR"&" "&TEXT($B76," #.##0,00"),0))) -> 0 | N76: =+IF(N$2=$E76,$D76,IF(N$2>N$257,0,IF($C76=N$2,"PAGAR"&" "&TEXT($B76," #.##0,00"),0))) -> 0 | O76: =+IF(O$2=$E76,$D76,IF(O$2>O$257,0,IF($C76=O$2,"PAGAR"&" "&TEXT($B76," #.##0,00"),0))) -> 0 | P76: =+IF(P$2=$E76,$D76,IF(P$2>P$257,0,IF($C76=P$2,"PAGAR"&" "&TEXT($B76," #.##0,00"),0))) -> 0 | Q76: =+IF(Q$2=$E76,$D76,IF(Q$2>Q$257,0,IF($C76=Q$2,"PAGAR"&" "&TEXT($B76," #.##0,00"),0))) -> 0 | ... AM76: =+IF(AM$2=$E76,$D76,IF(AM$2>AM$257,0,IF($C76=AM$2,"PAGAR"&" "&TEXT($B76," #.##0,00"),0))) -> 0 | AN76: =+IF(F76<0,-F76,0) -> 0 | AO76: =+IF(AND(C76=0,B76>0),B76,0) -> 0
F77: =+IF(TODAY()<DATEVALUE(1&D$1&E$1),0,IF(C77>0,IF(C77-SUM(I$255:AM$255)<0,B77-SUM(I77:AM77,0),0),0))+IF(C77=-1,B77-SUM(J77:AM77)) -> 0 | G77: =+IF(B77=0,"-",D77/B77) -> - | I77: =IF(I$2=$E77,$D77,IF(I$2>I$257,0,IF($C77=I$2,"PAGAR"&" "&TEXT($B77," #.##0,00"),IF($C77=-1,"PAGAR"&" "&TEXT($B77," #.##0,00"),0)))) -> 0 | J77: =+IF(J$2=$E77,$D77,IF(J$2>J$257,0,IF($C77=J$2,"PAGAR"&" "&TEXT($B77," #.##0,00"),0))) -> 0 | K77: =+IF(K$2=$E77,$D77,IF(K$2>K$257,0,IF($C77=K$2,"PAGAR"&" "&TEXT($B77," #.##0,00"),0))) -> 0 | L77: =+IF(L$2=$E77,$D77,IF(L$2>L$257,0,IF($C77=L$2,"PAGAR"&" "&TEXT($B77," #.##0,00"),0))) -> 0 | M77: =+IF(M$2=$E77,$D77,IF(M$2>M$257,0,IF($C77=M$2,"PAGAR"&" "&TEXT($B77," #.##0,00"),0))) -> 0 | N77: =+IF(N$2=$E77,$D77,IF(N$2>N$257,0,IF($C77=N$2,"PAGAR"&" "&TEXT($B77," #.##0,00"),0))) -> 0 | O77: =+IF(O$2=$E77,$D77,IF(O$2>O$257,0,IF($C77=O$2,"PAGAR"&" "&TEXT($B77," #.##0,00"),0))) -> 0 | P77: =+IF(P$2=$E77,$D77,IF(P$2>P$257,0,IF($C77=P$2,"PAGAR"&" "&TEXT($B77," #.##0,00"),0))) -> 0 | Q77: =+IF(Q$2=$E77,$D77,IF(Q$2>Q$257,0,IF($C77=Q$2,"PAGAR"&" "&TEXT($B77," #.##0,00"),0))) -> 0 | ... AM77: =+IF(AM$2=$E77,$D77,IF(AM$2>AM$257,0,IF($C77=AM$2,"PAGAR"&" "&TEXT($B77," #.##0,00"),0))) -> 0 | AN77: =+IF(F77<0,-F77,0) -> 0 | AO77: =+IF(AND(C77=0,B77>0),B77,0) -> 0
F78: =+IF(TODAY()<DATEVALUE(1&D$1&E$1),0,IF(C78>0,IF(C78-SUM(I$255:AM$255)<0,B78-SUM(I78:AM78,0),0),0))+IF(C78=-1,B78-SUM(J78:AM78)) -> 0 | G78: =+IF(B78=0,"-",D78/B78) -> - | I78: =IF(I$2=$E78,$D78,IF(I$2>I$257,0,IF($C78=I$2,"PAGAR"&" "&TEXT($B78," #.##0,00"),IF($C78=-1,"PAGAR"&" "&TEXT($B78," #.##0,00"),0)))) -> 0 | J78: =+IF(J$2=$E78,$D78,IF(J$2>J$257,0,IF($C78=J$2,"PAGAR"&" "&TEXT($B78," #.##0,00"),0))) -> 0 | K78: =+IF(K$2=$E78,$D78,IF(K$2>K$257,0,IF($C78=K$2,"PAGAR"&" "&TEXT($B78," #.##0,00"),0))) -> 0 | L78: =+IF(L$2=$E78,$D78,IF(L$2>L$257,0,IF($C78=L$2,"PAGAR"&" "&TEXT($B78," #.##0,00"),0))) -> 0 | M78: =+IF(M$2=$E78,$D78,IF(M$2>M$257,0,IF($C78=M$2,"PAGAR"&" "&TEXT($B78," #.##0,00"),0))) -> 0 | N78: =+IF(N$2=$E78,$D78,IF(N$2>N$257,0,IF($C78=N$2,"PAGAR"&" "&TEXT($B78," #.##0,00"),0))) -> 0 | O78: =+IF(O$2=$E78,$D78,IF(O$2>O$257,0,IF($C78=O$2,"PAGAR"&" "&TEXT($B78," #.##0,00"),0))) -> 0 | P78: =+IF(P$2=$E78,$D78,IF(P$2>P$257,0,IF($C78=P$2,"PAGAR"&" "&TEXT($B78," #.##0,00"),0))) -> 0 | Q78: =+IF(Q$2=$E78,$D78,IF(Q$2>Q$257,0,IF($C78=Q$2,"PAGAR"&" "&TEXT($B78," #.##0,00"),0))) -> 0 | ... AM78: =+IF(AM$2=$E78,$D78,IF(AM$2>AM$257,0,IF($C78=AM$2,"PAGAR"&" "&TEXT($B78," #.##0,00"),0))) -> 0 | AN78: =+IF(F78<0,-F78,0) -> 0 | AO78: =+IF(AND(C78=0,B78>0),B78,0) -> 0
A79: Claro Reserva | B79: 288.06 | C79: 5 | F79: =+IF(TODAY()<DATEVALUE(1&D$1&E$1),0,IF(C79>0,IF(C79-SUM(I$255:AM$255)<0,B79-SUM(I79:AM79,0),0),0))+IF(C79=-1,B79-SUM(J79:AM79)) -> 288.06 | G79: =+IF(B79=0,"-",D79/B79) -> 0 | I79: =IF(I$2=$E79,$D79,IF(I$2>I$257,0,IF($C79=I$2,"PAGAR"&" "&TEXT($B79," #.##0,00"),IF($C79=-1,"PAGAR"&" "&TEXT($B79," #.##0,00"),0)))) -> 0 | J79: =+IF(J$2=$E79,$D79,IF(J$2>J$257,0,IF($C79=J$2,"PAGAR"&" "&TEXT($B79," #.##0,00"),0))) -> 0 | K79: =+IF(K$2=$E79,$D79,IF(K$2>K$257,0,IF($C79=K$2,"PAGAR"&" "&TEXT($B79," #.##0,00"),0))) -> 0 | L79: =+IF(L$2=$E79,$D79,IF(L$2>L$257,0,IF($C79=L$2,"PAGAR"&" "&TEXT($B79," #.##0,00"),0))) -> 0 | M79: =+IF(M$2=$E79,$D79,IF(M$2>M$257,0,IF($C79=M$2,"PAGAR"&" "&TEXT($B79," #.##0,00"),0))) -> PAGAR 288,06 | N79: =+IF(N$2=$E79,$D79,IF(N$2>N$257,0,IF($C79=N$2,"PAGAR"&" "&TEXT($B79," #.##0,00"),0))) -> 0 | O79: =+IF(O$2=$E79,$D79,IF(O$2>O$257,0,IF($C79=O$2,"PAGAR"&" "&TEXT($B79," #.##0,00"),0))) -> 0 | P79: =+IF(P$2=$E79,$D79,IF(P$2>P$257,0,IF($C79=P$2,"PAGAR"&" "&TEXT($B79," #.##0,00"),0))) -> 0 | Q79: =+IF(Q$2=$E79,$D79,IF(Q$2>Q$257,0,IF($C79=Q$2,"PAGAR"&" "&TEXT($B79," #.##0,00"),0))) -> 0 | ... AM79: =+IF(AM$2=$E79,$D79,IF(AM$2>AM$257,0,IF($C79=AM$2,"PAGAR"&" "&TEXT($B79," #.##0,00"),0))) -> 0 | AN79: =+IF(F79<0,-F79,0) -> 0 | AO79: =+IF(AND(C79=0,B79>0),B79,0) -> 0
A80: Vivo Lago | B80: 236.13 | C80: 26 | F80: =+IF(TODAY()<DATEVALUE(1&D$1&E$1),0,IF(C80>0,IF(C80-SUM(I$255:AM$255)<0,B80-SUM(I80:AM80,0),0),0))+IF(C80=-1,B80-SUM(J80:AM80)) -> 0 | G80: =+IF(B80=0,"-",D80/B80) -> 0 | I80: =IF(I$2=$E80,$D80,IF(I$2>I$257,0,IF($C80=I$2,"PAGAR"&" "&TEXT($B80," #.##0,00"),IF($C80=-1,"PAGAR"&" "&TEXT($B80," #.##0,00"),0)))) -> 0 | J80: =+IF(J$2=$E80,$D80,IF(J$2>J$257,0,IF($C80=J$2,"PAGAR"&" "&TEXT($B80," #.##0,00"),0))) -> 0 | K80: =+IF(K$2=$E80,$D80,IF(K$2>K$257,0,IF($C80=K$2,"PAGAR"&" "&TEXT($B80," #.##0,00"),0))) -> 0 | L80: =+IF(L$2=$E80,$D80,IF(L$2>L$257,0,IF($C80=L$2,"PAGAR"&" "&TEXT($B80," #.##0,00"),0))) -> 0 | M80: =+IF(M$2=$E80,$D80,IF(M$2>M$257,0,IF($C80=M$2,"PAGAR"&" "&TEXT($B80," #.##0,00"),0))) -> 0 | N80: =+IF(N$2=$E80,$D80,IF(N$2>N$257,0,IF($C80=N$2,"PAGAR"&" "&TEXT($B80," #.##0,00"),0))) -> 0 | O80: =+IF(O$2=$E80,$D80,IF(O$2>O$257,0,IF($C80=O$2,"PAGAR"&" "&TEXT($B80," #.##0,00"),0))) -> 0 | P80: =+IF(P$2=$E80,$D80,IF(P$2>P$257,0,IF($C80=P$2,"PAGAR"&" "&TEXT($B80," #.##0,00"),0))) -> 0 | Q80: =+IF(Q$2=$E80,$D80,IF(Q$2>Q$257,0,IF($C80=Q$2,"PAGAR"&" "&TEXT($B80," #.##0,00"),0))) -> 0 | ... AM80: =+IF(AM$2=$E80,$D80,IF(AM$2>AM$257,0,IF($C80=AM$2,"PAGAR"&" "&TEXT($B80," #.##0,00"),0))) -> 0 | AN80: =+IF(F80<0,-F80,0) -> 0 | AO80: =+IF(AND(C80=0,B80>0),B80,0) -> 0
A81: IPTU Lago 003226 pedir parcelamento | B81: 859.92 | C81: 0 | F81: =+IF(TODAY()<DATEVALUE(1&D$1&E$1),0,IF(C81>0,IF(C81-SUM(I$255:AM$255)<0,B81-SUM(I81:AM81,0),0),0))+IF(C81=-1,B81-SUM(J81:AM81)) -> 0 | G81: =+IF(B81=0,"-",D81/B81) -> 0 | I81: =IF(I$2=$E81,$D81,IF(I$2>I$257,0,IF($C81=I$2,"PAGAR"&" "&TEXT($B81," #.##0,00"),IF($C81=-1,"PAGAR"&" "&TEXT($B81," #.##0,00"),0)))) -> 0 | J81: =+IF(J$2=$E81,$D81,IF(J$2>J$257,0,IF($C81=J$2,"PAGAR"&" "&TEXT($B81," #.##0,00"),0))) -> 0 | K81: =+IF(K$2=$E81,$D81,IF(K$2>K$257,0,IF($C81=K$2,"PAGAR"&" "&TEXT($B81," #.##0,00"),0))) -> 0 | L81: =+IF(L$2=$E81,$D81,IF(L$2>L$257,0,IF($C81=L$2,"PAGAR"&" "&TEXT($B81," #.##0,00"),0))) -> 0 | M81: =+IF(M$2=$E81,$D81,IF(M$2>M$257,0,IF($C81=M$2,"PAGAR"&" "&TEXT($B81," #.##0,00"),0))) -> 0 | N81: =+IF(N$2=$E81,$D81,IF(N$2>N$257,0,IF($C81=N$2,"PAGAR"&" "&TEXT($B81," #.##0,00"),0))) -> 0 | O81: =+IF(O$2=$E81,$D81,IF(O$2>O$257,0,IF($C81=O$2,"PAGAR"&" "&TEXT($B81," #.##0,00"),0))) -> 0 | P81: =+IF(P$2=$E81,$D81,IF(P$2>P$257,0,IF($C81=P$2,"PAGAR"&" "&TEXT($B81," #.##0,00"),0))) -> 0 | Q81: =+IF(Q$2=$E81,$D81,IF(Q$2>Q$257,0,IF($C81=Q$2,"PAGAR"&" "&TEXT($B81," #.##0,00"),0))) -> 0 | ... AM81: =+IF(AM$2=$E81,$D81,IF(AM$2>AM$257,0,IF($C81=AM$2,"PAGAR"&" "&TEXT($B81," #.##0,00"),0))) -> 0 | AN81: =+IF(F81<0,-F81,0) -> 0 | AO81: =+IF(AND(C81=0,B81>0),B81,0) -> 859.92
A82: Condomínio Sta Rita | B82: 300 | C82: 1 | F82: =+IF(TODAY()<DATEVALUE(1&D$1&E$1),0,IF(C82>0,IF(C82-SUM(I$255:AM$255)<0,B82-SUM(I82:AM82,0),0),0))+IF(C82=-1,B82-SUM(J82:AM82)) -> 300 | G82: =+IF(B82=0,"-",D82/B82) -> 0 | I82: =IF(I$2=$E82,$D82,IF(I$2>I$257,0,IF($C82=I$2,"PAGAR"&" "&TEXT($B82," #.##0,00"),IF($C82=-1,"PAGAR"&" "&TEXT($B82," #.##0,00"),0)))) -> PAGAR 300,00 | J82: =+IF(J$2=$E82,$D82,IF(J$2>J$257,0,IF($C82=J$2,"PAGAR"&" "&TEXT($B82," #.##0,00"),0))) -> 0 | K82: =+IF(K$2=$E82,$D82,IF(K$2>K$257,0,IF($C82=K$2,"PAGAR"&" "&TEXT($B82," #.##0,00"),0))) -> 0 | L82: =+IF(L$2=$E82,$D82,IF(L$2>L$257,0,IF($C82=L$2,"PAGAR"&" "&TEXT($B82," #.##0,00"),0))) -> 0 | M82: =+IF(M$2=$E82,$D82,IF(M$2>M$257,0,IF($C82=M$2,"PAGAR"&" "&TEXT($B82," #.##0,00"),0))) -> 0 | N82: =+IF(N$2=$E82,$D82,IF(N$2>N$257,0,IF($C82=N$2,"PAGAR"&" "&TEXT($B82," #.##0,00"),0))) -> 0 | O82: =+IF(O$2=$E82,$D82,IF(O$2>O$257,0,IF($C82=O$2,"PAGAR"&" "&TEXT($B82," #.##0,00"),0))) -> 0 | P82: =+IF(P$2=$E82,$D82,IF(P$2>P$257,0,IF($C82=P$2,"PAGAR"&" "&TEXT($B82," #.##0,00"),0))) -> 0 | Q82: =+IF(Q$2=$E82,$D82,IF(Q$2>Q$257,0,IF($C82=Q$2,"PAGAR"&" "&TEXT($B82," #.##0,00"),0))) -> 0 | ... AM82: =+IF(AM$2=$E82,$D82,IF(AM$2>AM$257,0,IF($C82=AM$2,"PAGAR"&" "&TEXT($B82," #.##0,00"),0))) -> 0 | AN82: =+IF(F82<0,-F82,0) -> 0 | AO82: =+IF(AND(C82=0,B82>0),B82,0) -> 0
A83: CPFL Reserva | B83: 159.64 | C83: 12 | F83: =+IF(TODAY()<DATEVALUE(1&D$1&E$1),0,IF(C83>0,IF(C83-SUM(I$255:AM$255)<0,B83-SUM(I83:AM83,0),0),0))+IF(C83=-1,B83-SUM(J83:AM83)) -> 159.64 | G83: =+IF(B83=0,"-",D83/B83) -> 0 | I83: =IF(I$2=$E83,$D83,IF(I$2>I$257,0,IF($C83=I$2,"PAGAR"&" "&TEXT($B83," #.##0,00"),IF($C83=-1,"PAGAR"&" "&TEXT($B83," #.##0,00"),0)))) -> 0 | J83: =+IF(J$2=$E83,$D83,IF(J$2>J$257,0,IF($C83=J$2,"PAGAR"&" "&TEXT($B83," #.##0,00"),0))) -> 0 | K83: =+IF(K$2=$E83,$D83,IF(K$2>K$257,0,IF($C83=K$2,"PAGAR"&" "&TEXT($B83," #.##0,00"),0))) -> 0 | L83: =+IF(L$2=$E83,$D83,IF(L$2>L$257,0,IF($C83=L$2,"PAGAR"&" "&TEXT($B83," #.##0,00"),0))) -> 0 | M83: =+IF(M$2=$E83,$D83,IF(M$2>M$257,0,IF($C83=M$2,"PAGAR"&" "&TEXT($B83," #.##0,00"),0))) -> 0 | N83: =+IF(N$2=$E83,$D83,IF(N$2>N$257,0,IF($C83=N$2,"PAGAR"&" "&TEXT($B83," #.##0,00"),0))) -> 0 | O83: =+IF(O$2=$E83,$D83,IF(O$2>O$257,0,IF($C83=O$2,"PAGAR"&" "&TEXT($B83," #.##0,00"),0))) -> 0 | P83: =+IF(P$2=$E83,$D83,IF(P$2>P$257,0,IF($C83=P$2,"PAGAR"&" "&TEXT($B83," #.##0,00"),0))) -> 0 | Q83: =+IF(Q$2=$E83,$D83,IF(Q$2>Q$257,0,IF($C83=Q$2,"PAGAR"&" "&TEXT($B83," #.##0,00"),0))) -> 0 | ... AM83: =+IF(AM$2=$E83,$D83,IF(AM$2>AM$257,0,IF($C83=AM$2,"PAGAR"&" "&TEXT($B83," #.##0,00"),0))) -> 0 | AN83: =+IF(F83<0,-F83,0) -> 0 | AO83: =+IF(AND(C83=0,B83>0),B83,0) -> 0
A84: CPFL Ágata | B84: 173.49 | C84: 6 | F84: =+IF(TODAY()<DATEVALUE(1&D$1&E$1),0,IF(C84>0,IF(C84-SUM(I$255:AM$255)<0,B84-SUM(I84:AM84,0),0),0))+IF(C84=-1,B84-SUM(J84:AM84)) -> 173.49 | G84: =+IF(B84=0,"-",D84/B84) -> 0 | I84: =IF(I$2=$E84,$D84,IF(I$2>I$257,0,IF($C84=I$2,"PAGAR"&" "&TEXT($B84," #.##0,00"),IF($C84=-1,"PAGAR"&" "&TEXT($B84," #.##0,00"),0)))) -> 0 | J84: =+IF(J$2=$E84,$D84,IF(J$2>J$257,0,IF($C84=J$2,"PAGAR"&" "&TEXT($B84," #.##0,00"),0))) -> 0 | K84: =+IF(K$2=$E84,$D84,IF(K$2>K$257,0,IF($C84=K$2,"PAGAR"&" "&TEXT($B84," #.##0,00"),0))) -> 0 | L84: =+IF(L$2=$E84,$D84,IF(L$2>L$257,0,IF($C84=L$2,"PAGAR"&" "&TEXT($B84," #.##0,00"),0))) -> 0 | M84: =+IF(M$2=$E84,$D84,IF(M$2>M$257,0,IF($C84=M$2,"PAGAR"&" "&TEXT($B84," #.##0,00"),0))) -> 0 | N84: =+IF(N$2=$E84,$D84,IF(N$2>N$257,0,IF($C84=N$2,"PAGAR"&" "&TEXT($B84," #.##0,00"),0))) -> PAGAR 173,49 | O84: =+IF(O$2=$E84,$D84,IF(O$2>O$257,0,IF($C84=O$2,"PAGAR"&" "&TEXT($B84," #.##0,00"),0))) -> 0 | P84: =+IF(P$2=$E84,$D84,IF(P$2>P$257,0,IF($C84=P$2,"PAGAR"&" "&TEXT($B84," #.##0,00"),0))) -> 0 | Q84: =+IF(Q$2=$E84,$D84,IF(Q$2>Q$257,0,IF($C84=Q$2,"PAGAR"&" "&TEXT($B84," #.##0,00"),0))) -> 0 | ... AM84: =+IF(AM$2=$E84,$D84,IF(AM$2>AM$257,0,IF($C84=AM$2,"PAGAR"&" "&TEXT($B84," #.##0,00"),0))) -> 0 | AN84: =+IF(F84<0,-F84,0) -> 0 | AO84: =+IF(AND(C84=0,B84>0),B84,0) -> 0
A85: AGDES Reserva | B85: 291.1 | C85: 6 | F85: =+IF(TODAY()<DATEVALUE(1&D$1&E$1),0,IF(C85>0,IF(C85-SUM(I$255:AM$255)<0,B85-SUM(I85:AM85,0),0),0))+IF(C85=-1,B85-SUM(J85:AM85)) -> 291.1 | G85: =+IF(B85=0,"-",D85/B85) -> 0 | I85: =IF(I$2=$E85,$D85,IF(I$2>I$257,0,IF($C85=I$2,"PAGAR"&" "&TEXT($B85," #.##0,00"),IF($C85=-1,"PAGAR"&" "&TEXT($B85," #.##0,00"),0)))) -> 0 | J85: =+IF(J$2=$E85,$D85,IF(J$2>J$257,0,IF($C85=J$2,"PAGAR"&" "&TEXT($B85," #.##0,00"),0))) -> 0 | K85: =+IF(K$2=$E85,$D85,IF(K$2>K$257,0,IF($C85=K$2,"PAGAR"&" "&TEXT($B85," #.##0,00"),0))) -> 0 | L85: =+IF(L$2=$E85,$D85,IF(L$2>L$257,0,IF($C85=L$2,"PAGAR"&" "&TEXT($B85," #.##0,00"),0))) -> 0 | M85: =+IF(M$2=$E85,$D85,IF(M$2>M$257,0,IF($C85=M$2,"PAGAR"&" "&TEXT($B85," #.##0,00"),0))) -> 0 | N85: =+IF(N$2=$E85,$D85,IF(N$2>N$257,0,IF($C85=N$2,"PAGAR"&" "&TEXT($B85," #.##0,00"),0))) -> PAGAR 291,10 | O85: =+IF(O$2=$E85,$D85,IF(O$2>O$257,0,IF($C85=O$2,"PAGAR"&" "&TEXT($B85," #.##0,00"),0))) -> 0 | P85: =+IF(P$2=$E85,$D85,IF(P$2>P$257,0,IF($C85=P$2,"PAGAR"&" "&TEXT($B85," #.##0,00"),0))) -> 0 | Q85: =+IF(Q$2=$E85,$D85,IF(Q$2>Q$257,0,IF($C85=Q$2,"PAGAR"&" "&TEXT($B85," #.##0,00"),0))) -> 0 | ... AM85: =+IF(AM$2=$E85,$D85,IF(AM$2>AM$257,0,IF($C85=AM$2,"PAGAR"&" "&TEXT($B85," #.##0,00"),0))) -> 0 | AN85: =+IF(F85<0,-F85,0) -> 0 | AO85: =+IF(AND(C85=0,B85>0),B85,0) -> 0
F86: =+IF(TODAY()<DATEVALUE(1&D$1&E$1),0,IF(C86>0,IF(C86-SUM(I$255:AM$255)<0,B86-SUM(I86:AM86,0),0),0))+IF(C86=-1,B86-SUM(J86:AM86)) -> 0 | G86: =+IF(B86=0,"-",D86/B86) -> - | I86: =IF(I$2=$E86,$D86,IF(I$2>I$257,0,IF($C86=I$2,"PAGAR"&" "&TEXT($B86," #.##0,00"),IF($C86=-1,"PAGAR"&" "&TEXT($B86," #.##0,00"),0)))) -> 0 | J86: =+IF(J$2=$E86,$D86,IF(J$2>J$257,0,IF($C86=J$2,"PAGAR"&" "&TEXT($B86," #.##0,00"),0))) -> 0 | K86: =+IF(K$2=$E86,$D86,IF(K$2>K$257,0,IF($C86=K$2,"PAGAR"&" "&TEXT($B86," #.##0,00"),0))) -> 0 | L86: =+IF(L$2=$E86,$D86,IF(L$2>L$257,0,IF($C86=L$2,"PAGAR"&" "&TEXT($B86," #.##0,00"),0))) -> 0 | M86: =+IF(M$2=$E86,$D86,IF(M$2>M$257,0,IF($C86=M$2,"PAGAR"&" "&TEXT($B86," #.##0,00"),0))) -> 0 | N86: =+IF(N$2=$E86,$D86,IF(N$2>N$257,0,IF($C86=N$2,"PAGAR"&" "&TEXT($B86," #.##0,00"),0))) -> 0 | O86: =+IF(O$2=$E86,$D86,IF(O$2>O$257,0,IF($C86=O$2,"PAGAR"&" "&TEXT($B86," #.##0,00"),0))) -> 0 | P86: =+IF(P$2=$E86,$D86,IF(P$2>P$257,0,IF($C86=P$2,"PAGAR"&" "&TEXT($B86," #.##0,00"),0))) -> 0 | Q86: =+IF(Q$2=$E86,$D86,IF(Q$2>Q$257,0,IF($C86=Q$2,"PAGAR"&" "&TEXT($B86," #.##0,00"),0))) -> 0 | ... AM86: =+IF(AM$2=$E86,$D86,IF(AM$2>AM$257,0,IF($C86=AM$2,"PAGAR"&" "&TEXT($B86," #.##0,00"),0))) -> 0 | AN86: =+IF(F86<0,-F86,0) -> 0 | AO86: =+IF(AND(C86=0,B86>0),B86,0) -> 0
F87: =+IF(TODAY()<DATEVALUE(1&D$1&E$1),0,IF(C87>0,IF(C87-SUM(I$255:AM$255)<0,B87-SUM(I87:AM87,0),0),0))+IF(C87=-1,B87-SUM(J87:AM87)) -> 0 | G87: =+IF(B87=0,"-",D87/B87) -> - | I87: =IF(I$2=$E87,$D87,IF(I$2>I$257,0,IF($C87=I$2,"PAGAR"&" "&TEXT($B87," #.##0,00"),IF($C87=-1,"PAGAR"&" "&TEXT($B87," #.##0,00"),0)))) -> 0 | J87: =+IF(J$2=$E87,$D87,IF(J$2>J$257,0,IF($C87=J$2,"PAGAR"&" "&TEXT($B87," #.##0,00"),0))) -> 0 | K87: =+IF(K$2=$E87,$D87,IF(K$2>K$257,0,IF($C87=K$2,"PAGAR"&" "&TEXT($B87," #.##0,00"),0))) -> 0 | L87: =+IF(L$2=$E87,$D87,IF(L$2>L$257,0,IF($C87=L$2,"PAGAR"&" "&TEXT($B87," #.##0,00"),0))) -> 0 | M87: =+IF(M$2=$E87,$D87,IF(M$2>M$257,0,IF($C87=M$2,"PAGAR"&" "&TEXT($B87," #.##0,00"),0))) -> 0 | N87: =+IF(N$2=$E87,$D87,IF(N$2>N$257,0,IF($C87=N$2,"PAGAR"&" "&TEXT($B87," #.##0,00"),0))) -> 0 | O87: =+IF(O$2=$E87,$D87,IF(O$2>O$257,0,IF($C87=O$2,"PAGAR"&" "&TEXT($B87," #.##0,00"),0))) -> 0 | P87: =+IF(P$2=$E87,$D87,IF(P$2>P$257,0,IF($C87=P$2,"PAGAR"&" "&TEXT($B87," #.##0,00"),0))) -> 0 | Q87: =+IF(Q$2=$E87,$D87,IF(Q$2>Q$257,0,IF($C87=Q$2,"PAGAR"&" "&TEXT($B87," #.##0,00"),0))) -> 0 | ... AM87: =+IF(AM$2=$E87,$D87,IF(AM$2>AM$257,0,IF($C87=AM$2,"PAGAR"&" "&TEXT($B87," #.##0,00"),0))) -> 0 | AN87: =+IF(F87<0,-F87,0) -> 0 | AO87: =+IF(AND(C87=0,B87>0),B87,0) -> 0
F88: =+IF(TODAY()<DATEVALUE(1&D$1&E$1),0,IF(C88>0,IF(C88-SUM(I$255:AM$255)<0,B88-SUM(I88:AM88,0),0),0))+IF(C88=-1,B88-SUM(J88:AM88)) -> 0 | G88: =+IF(B88=0,"-",D88/B88) -> - | I88: =IF(I$2=$E88,$D88,IF(I$2>I$257,0,IF($C88=I$2,"PAGAR"&" "&TEXT($B88," #.##0,00"),IF($C88=-1,"PAGAR"&" "&TEXT($B88," #.##0,00"),0)))) -> 0 | J88: =+IF(J$2=$E88,$D88,IF(J$2>J$257,0,IF($C88=J$2,"PAGAR"&" "&TEXT($B88," #.##0,00"),0))) -> 0 | K88: =+IF(K$2=$E88,$D88,IF(K$2>K$257,0,IF($C88=K$2,"PAGAR"&" "&TEXT($B88," #.##0,00"),0))) -> 0 | L88: =+IF(L$2=$E88,$D88,IF(L$2>L$257,0,IF($C88=L$2,"PAGAR"&" "&TEXT($B88," #.##0,00"),0))) -> 0 | M88: =+IF(M$2=$E88,$D88,IF(M$2>M$257,0,IF($C88=M$2,"PAGAR"&" "&TEXT($B88," #.##0,00"),0))) -> 0 | N88: =+IF(N$2=$E88,$D88,IF(N$2>N$257,0,IF($C88=N$2,"PAGAR"&" "&TEXT($B88," #.##0,00"),0))) -> 0 | O88: =+IF(O$2=$E88,$D88,IF(O$2>O$257,0,IF($C88=O$2,"PAGAR"&" "&TEXT($B88," #.##0,00"),0))) -> 0 | P88: =+IF(P$2=$E88,$D88,IF(P$2>P$257,0,IF($C88=P$2,"PAGAR"&" "&TEXT($B88," #.##0,00"),0))) -> 0 | Q88: =+IF(Q$2=$E88,$D88,IF(Q$2>Q$257,0,IF($C88=Q$2,"PAGAR"&" "&TEXT($B88," #.##0,00"),0))) -> 0 | ... AM88: =+IF(AM$2=$E88,$D88,IF(AM$2>AM$257,0,IF($C88=AM$2,"PAGAR"&" "&TEXT($B88," #.##0,00"),0))) -> 0 | AN88: =+IF(F88<0,-F88,0) -> 0 | AO88: =+IF(AND(C88=0,B88>0),B88,0) -> 0
A89: Total de despesas previstas (Plan 2) | B89: =+SUM(B69:B88) -> 18460.94 | D89: =+SUM(D69:D88) -> 0 | F89: =+SUMIF(F69:F88,">0") -> 4920.82 | G89: =+IF(B89=0,"-",D89/B89) -> 0 | I89: =+PLAN2!H90 -> 2503.91 | J89: =+PLAN2!I90 -> 0 | K89: =+PLAN2!J90 -> 0 | L89: =+PLAN2!K90 -> 0 | M89: =+PLAN2!L90 -> 288.06 | N89: =+PLAN2!M90 -> 464.59 | O89: =+PLAN2!N90 -> 0 | P89: =+PLAN2!O90 -> 0 | ... AM89: =+PLAN2!AL90 -> 0 | AN89: =SUM(AN69:AN88) -> 0
A90: PRESTAÇÕES/EMPRÉSTIMOS
F91: =+IF(TODAY()<DATEVALUE(1&D$1&E$1),0,IF(C91>0,IF(C91-SUM(I$255:AM$255)<0,B91-SUM(I91:AM91,0),0),0))+IF(C91=-1,B91-SUM(J91:AM91)) -> 0 | G91: =+IF(B91=0,"-",D91/B91) -> - | I91: =IF(I$2=$E91,$D91,IF(I$2>I$257,0,IF($C91=I$2,"PAGAR"&" "&TEXT($B91," #.##0,00"),IF($C91=-1,"PAGAR"&" "&TEXT($B91," #.##0,00"),0)))) -> 0 | J91: =+IF(J$2=$E91,$D91,IF(J$2>J$257,0,IF($C91=J$2,"PAGAR"&" "&TEXT($B91," #.##0,00"),0))) -> 0 | K91: =+IF(K$2=$E91,$D91,IF(K$2>K$257,0,IF($C91=K$2,"PAGAR"&" "&TEXT($B91," #.##0,00"),0))) -> 0 | L91: =+IF(L$2=$E91,$D91,IF(L$2>L$257,0,IF($C91=L$2,"PAGAR"&" "&TEXT($B91," #.##0,00"),0))) -> 0 | M91: =+IF(M$2=$E91,$D91,IF(M$2>M$257,0,IF($C91=M$2,"PAGAR"&" "&TEXT($B91," #.##0,00"),0))) -> 0 | N91: =+IF(N$2=$E91,$D91,IF(N$2>N$257,0,IF($C91=N$2,"PAGAR"&" "&TEXT($B91," #.##0,00"),0))) -> 0 | O91: =+IF(O$2=$E91,$D91,IF(O$2>O$257,0,IF($C91=O$2,"PAGAR"&" "&TEXT($B91," #.##0,00"),0))) -> 0 | P91: =+IF(P$2=$E91,$D91,IF(P$2>P$257,0,IF($C91=P$2,"PAGAR"&" "&TEXT($B91," #.##0,00"),0))) -> 0 | Q91: =+IF(Q$2=$E91,$D91,IF(Q$2>Q$257,0,IF($C91=Q$2,"PAGAR"&" "&TEXT($B91," #.##0,00"),0))) -> 0 | ... AM91: =+IF(AM$2=$E91,$D91,IF(AM$2>AM$257,0,IF($C91=AM$2,"PAGAR"&" "&TEXT($B91," #.##0,00"),0))) -> 0 | AN91: =+IF(F91<0,-F91,0) -> 0 | AO91: =+IF(AND(C91=0,B91>0),B91,0) -> 0
A92: Itaú - pron. débito auto (6/24x) 1,6% 150k | B92: 5188 | C92: 5 | F92: =+IF(TODAY()<DATEVALUE(1&D$1&E$1),0,IF(C92>0,IF(C92-SUM(I$255:AM$255)<0,B92-SUM(I92:AM92,0),0),0))+IF(C92=-1,B92-SUM(J92:AM92)) -> 5188 | G92: =+IF(B92=0,"-",D92/B92) -> 0 | I92: =IF(I$2=$E92,$D92,IF(I$2>I$257,0,IF($C92=I$2,"PAGAR"&" "&TEXT($B92," #.##0,00"),IF($C92=-1,"PAGAR"&" "&TEXT($B92," #.##0,00"),0)))) -> 0 | J92: =+IF(J$2=$E92,$D92,IF(J$2>J$257,0,IF($C92=J$2,"PAGAR"&" "&TEXT($B92," #.##0,00"),0))) -> 0 | K92: =+IF(K$2=$E92,$D92,IF(K$2>K$257,0,IF($C92=K$2,"PAGAR"&" "&TEXT($B92," #.##0,00"),0))) -> 0 | L92: =+IF(L$2=$E92,$D92,IF(L$2>L$257,0,IF($C92=L$2,"PAGAR"&" "&TEXT($B92," #.##0,00"),0))) -> 0 | M92: =+IF(M$2=$E92,$D92,IF(M$2>M$257,0,IF($C92=M$2,"PAGAR"&" "&TEXT($B92," #.##0,00"),0))) -> PAGAR 5.188,00 | N92: =+IF(N$2=$E92,$D92,IF(N$2>N$257,0,IF($C92=N$2,"PAGAR"&" "&TEXT($B92," #.##0,00"),0))) -> 0 | O92: =+IF(O$2=$E92,$D92,IF(O$2>O$257,0,IF($C92=O$2,"PAGAR"&" "&TEXT($B92," #.##0,00"),0))) -> 0 | P92: =+IF(P$2=$E92,$D92,IF(P$2>P$257,0,IF($C92=P$2,"PAGAR"&" "&TEXT($B92," #.##0,00"),0))) -> 0 | Q92: =+IF(Q$2=$E92,$D92,IF(Q$2>Q$257,0,IF($C92=Q$2,"PAGAR"&" "&TEXT($B92," #.##0,00"),0))) -> 0 | ... AM92: =+IF(AM$2=$E92,$D92,IF(AM$2>AM$257,0,IF($C92=AM$2,"PAGAR"&" "&TEXT($B92," #.##0,00"),0))) -> 0 | AN92: =+IF(F92<0,-F92,0) -> 0 | AO92: =+IF(AND(C92=0,B92>0),B92,0) -> 0
A93: Caixa Penhor 20/02 R$ | B93: 1709 | C93: 0 | F93: =+IF(TODAY()<DATEVALUE(1&D$1&E$1),0,IF(C93>0,IF(C93-SUM(I$255:AM$255)<0,B93-SUM(I93:AM93,0),0),0))+IF(C93=-1,B93-SUM(J93:AM93)) -> 0 | G93: =+IF(B93=0,"-",D93/B93) -> 0 | I93: =IF(I$2=$E93,$D93,IF(I$2>I$257,0,IF($C93=I$2,"PAGAR"&" "&TEXT($B93," #.##0,00"),IF($C93=-1,"PAGAR"&" "&TEXT($B93," #.##0,00"),0)))) -> 0 | J93: =+IF(J$2=$E93,$D93,IF(J$2>J$257,0,IF($C93=J$2,"PAGAR"&" "&TEXT($B93," #.##0,00"),0))) -> 0 | K93: =+IF(K$2=$E93,$D93,IF(K$2>K$257,0,IF($C93=K$2,"PAGAR"&" "&TEXT($B93," #.##0,00"),0))) -> 0 | L93: =+IF(L$2=$E93,$D93,IF(L$2>L$257,0,IF($C93=L$2,"PAGAR"&" "&TEXT($B93," #.##0,00"),0))) -> 0 | M93: =+IF(M$2=$E93,$D93,IF(M$2>M$257,0,IF($C93=M$2,"PAGAR"&" "&TEXT($B93," #.##0,00"),0))) -> 0 | N93: =+IF(N$2=$E93,$D93,IF(N$2>N$257,0,IF($C93=N$2,"PAGAR"&" "&TEXT($B93," #.##0,00"),0))) -> 0 | O93: =+IF(O$2=$E93,$D93,IF(O$2>O$257,0,IF($C93=O$2,"PAGAR"&" "&TEXT($B93," #.##0,00"),0))) -> 0 | P93: =+IF(P$2=$E93,$D93,IF(P$2>P$257,0,IF($C93=P$2,"PAGAR"&" "&TEXT($B93," #.##0,00"),0))) -> 0 | Q93: =+IF(Q$2=$E93,$D93,IF(Q$2>Q$257,0,IF($C93=Q$2,"PAGAR"&" "&TEXT($B93," #.##0,00"),0))) -> 0 | ... AM93: =+IF(AM$2=$E93,$D93,IF(AM$2>AM$257,0,IF($C93=AM$2,"PAGAR"&" "&TEXT($B93," #.##0,00"),0))) -> 0 | AN93: =+IF(F93<0,-F93,0) -> 0 | AO93: =+IF(AND(C93=0,B93>0),B93,0) -> 1709
A94: Itaú - débito auto (6/37x) 5% 50k | B94: 3099 | C94: 26 | F94: =+IF(TODAY()<DATEVALUE(1&D$1&E$1),0,IF(C94>0,IF(C94-SUM(I$255:AM$255)<0,B94-SUM(I94:AM94,0),0),0))+IF(C94=-1,B94-SUM(J94:AM94)) -> 0 | G94: =+IF(B94=0,"-",D94/B94) -> 0 | I94: =IF(I$2=$E94,$D94,IF(I$2>I$257,0,IF($C94=I$2,"PAGAR"&" "&TEXT($B94," #.##0,00"),IF($C94=-1,"PAGAR"&" "&TEXT($B94," #.##0,00"),0)))) -> 0 | J94: =+IF(J$2=$E94,$D94,IF(J$2>J$257,0,IF($C94=J$2,"PAGAR"&" "&TEXT($B94," #.##0,00"),0))) -> 0 | K94: =+IF(K$2=$E94,$D94,IF(K$2>K$257,0,IF($C94=K$2,"PAGAR"&" "&TEXT($B94," #.##0,00"),0))) -> 0 | L94: =+IF(L$2=$E94,$D94,IF(L$2>L$257,0,IF($C94=L$2,"PAGAR"&" "&TEXT($B94," #.##0,00"),0))) -> 0 | M94: =+IF(M$2=$E94,$D94,IF(M$2>M$257,0,IF($C94=M$2,"PAGAR"&" "&TEXT($B94," #.##0,00"),0))) -> 0 | N94: =+IF(N$2=$E94,$D94,IF(N$2>N$257,0,IF($C94=N$2,"PAGAR"&" "&TEXT($B94," #.##0,00"),0))) -> 0 | O94: =+IF(O$2=$E94,$D94,IF(O$2>O$257,0,IF($C94=O$2,"PAGAR"&" "&TEXT($B94," #.##0,00"),0))) -> 0 | P94: =+IF(P$2=$E94,$D94,IF(P$2>P$257,0,IF($C94=P$2,"PAGAR"&" "&TEXT($B94," #.##0,00"),0))) -> 0 | Q94: =+IF(Q$2=$E94,$D94,IF(Q$2>Q$257,0,IF($C94=Q$2,"PAGAR"&" "&TEXT($B94," #.##0,00"),0))) -> 0 | ... AM94: =+IF(AM$2=$E94,$D94,IF(AM$2>AM$257,0,IF($C94=AM$2,"PAGAR"&" "&TEXT($B94," #.##0,00"),0))) -> 0 | AN94: =+IF(F94<0,-F94,0) -> 0 | AO94: =+IF(AND(C94=0,B94>0),B94,0) -> 0
F95: =+IF(TODAY()<DATEVALUE(1&D$1&E$1),0,IF(C95>0,IF(C95-SUM(I$255:AM$255)<0,B95-SUM(I95:AM95,0),0),0))+IF(C95=-1,B95-SUM(J95:AM95)) -> 0 | G95: =+IF(B95=0,"-",D95/B95) -> - | I95: =IF(I$2=$E95,$D95,IF(I$2>I$257,0,IF($C95=I$2,"PAGAR"&" "&TEXT($B95," #.##0,00"),IF($C95=-1,"PAGAR"&" "&TEXT($B95," #.##0,00"),0)))) -> 0 | J95: =+IF(J$2=$E95,$D95,IF(J$2>J$257,0,IF($C95=J$2,"PAGAR"&" "&TEXT($B95," #.##0,00"),0))) -> 0 | K95: =+IF(K$2=$E95,$D95,IF(K$2>K$257,0,IF($C95=K$2,"PAGAR"&" "&TEXT($B95," #.##0,00"),0))) -> 0 | L95: =+IF(L$2=$E95,$D95,IF(L$2>L$257,0,IF($C95=L$2,"PAGAR"&" "&TEXT($B95," #.##0,00"),0))) -> 0 | M95: =+IF(M$2=$E95,$D95,IF(M$2>M$257,0,IF($C95=M$2,"PAGAR"&" "&TEXT($B95," #.##0,00"),0))) -> 0 | N95: =+IF(N$2=$E95,$D95,IF(N$2>N$257,0,IF($C95=N$2,"PAGAR"&" "&TEXT($B95," #.##0,00"),0))) -> 0 | O95: =+IF(O$2=$E95,$D95,IF(O$2>O$257,0,IF($C95=O$2,"PAGAR"&" "&TEXT($B95," #.##0,00"),0))) -> 0 | P95: =+IF(P$2=$E95,$D95,IF(P$2>P$257,0,IF($C95=P$2,"PAGAR"&" "&TEXT($B95," #.##0,00"),0))) -> 0 | Q95: =+IF(Q$2=$E95,$D95,IF(Q$2>Q$257,0,IF($C95=Q$2,"PAGAR"&" "&TEXT($B95," #.##0,00"),0))) -> 0 | ... AM95: =+IF(AM$2=$E95,$D95,IF(AM$2>AM$257,0,IF($C95=AM$2,"PAGAR"&" "&TEXT($B95," #.##0,00"),0))) -> 0 | AN95: =+IF(F95<0,-F95,0) -> 0 | AO95: =+IF(AND(C95=0,B95>0),B95,0) -> 0
F96: =+IF(TODAY()<DATEVALUE(1&D$1&E$1),0,IF(C96>0,IF(C96-SUM(I$255:AM$255)<0,B96-SUM(I96:AM96,0),0),0))+IF(C96=-1,B96-SUM(J96:AM96)) -> 0 | G96: =+IF(B96=0,"-",D96/B96) -> - | I96: =IF(I$2=$E96,$D96,IF(I$2>I$257,0,IF($C96=I$2,"PAGAR"&" "&TEXT($B96," #.##0,00"),IF($C96=-1,"PAGAR"&" "&TEXT($B96," #.##0,00"),0)))) -> 0 | J96: =+IF(J$2=$E96,$D96,IF(J$2>J$257,0,IF($C96=J$2,"PAGAR"&" "&TEXT($B96," #.##0,00"),0))) -> 0 | K96: =+IF(K$2=$E96,$D96,IF(K$2>K$257,0,IF($C96=K$2,"PAGAR"&" "&TEXT($B96," #.##0,00"),0))) -> 0 | L96: =+IF(L$2=$E96,$D96,IF(L$2>L$257,0,IF($C96=L$2,"PAGAR"&" "&TEXT($B96," #.##0,00"),0))) -> 0 | M96: =+IF(M$2=$E96,$D96,IF(M$2>M$257,0,IF($C96=M$2,"PAGAR"&" "&TEXT($B96," #.##0,00"),0))) -> 0 | N96: =+IF(N$2=$E96,$D96,IF(N$2>N$257,0,IF($C96=N$2,"PAGAR"&" "&TEXT($B96," #.##0,00"),0))) -> 0 | O96: =+IF(O$2=$E96,$D96,IF(O$2>O$257,0,IF($C96=O$2,"PAGAR"&" "&TEXT($B96," #.##0,00"),0))) -> 0 | P96: =+IF(P$2=$E96,$D96,IF(P$2>P$257,0,IF($C96=P$2,"PAGAR"&" "&TEXT($B96," #.##0,00"),0))) -> 0 | Q96: =+IF(Q$2=$E96,$D96,IF(Q$2>Q$257,0,IF($C96=Q$2,"PAGAR"&" "&TEXT($B96," #.##0,00"),0))) -> 0 | ... AM96: =+IF(AM$2=$E96,$D96,IF(AM$2>AM$257,0,IF($C96=AM$2,"PAGAR"&" "&TEXT($B96," #.##0,00"),0))) -> 0 | AN96: =+IF(F96<0,-F96,0) -> 0 | AO96: =+IF(AND(C96=0,B96>0),B96,0) -> 0
F97: =+IF(TODAY()<DATEVALUE(1&D$1&E$1),0,IF(C97>0,IF(C97-SUM(I$255:AM$255)<0,B97-SUM(I97:AM97,0),0),0))+IF(C97=-1,B97-SUM(J97:AM97)) -> 0 | G97: =+IF(B97=0,"-",D97/B97) -> - | I97: =IF(I$2=$E97,$D97,IF(I$2>I$257,0,IF($C97=I$2,"PAGAR"&" "&TEXT($B97," #.##0,00"),IF($C97=-1,"PAGAR"&" "&TEXT($B97," #.##0,00"),0)))) -> 0 | J97: =+IF(J$2=$E97,$D97,IF(J$2>J$257,0,IF($C97=J$2,"PAGAR"&" "&TEXT($B97," #.##0,00"),0))) -> 0 | K97: =+IF(K$2=$E97,$D97,IF(K$2>K$257,0,IF($C97=K$2,"PAGAR"&" "&TEXT($B97," #.##0,00"),0))) -> 0 | L97: =+IF(L$2=$E97,$D97,IF(L$2>L$257,0,IF($C97=L$2,"PAGAR"&" "&TEXT($B97," #.##0,00"),0))) -> 0 | M97: =+IF(M$2=$E97,$D97,IF(M$2>M$257,0,IF($C97=M$2,"PAGAR"&" "&TEXT($B97," #.##0,00"),0))) -> 0 | N97: =+IF(N$2=$E97,$D97,IF(N$2>N$257,0,IF($C97=N$2,"PAGAR"&" "&TEXT($B97," #.##0,00"),0))) -> 0 | O97: =+IF(O$2=$E97,$D97,IF(O$2>O$257,0,IF($C97=O$2,"PAGAR"&" "&TEXT($B97," #.##0,00"),0))) -> 0 | P97: =+IF(P$2=$E97,$D97,IF(P$2>P$257,0,IF($C97=P$2,"PAGAR"&" "&TEXT($B97," #.##0,00"),0))) -> 0 | Q97: =+IF(Q$2=$E97,$D97,IF(Q$2>Q$257,0,IF($C97=Q$2,"PAGAR"&" "&TEXT($B97," #.##0,00"),0))) -> 0 | ... AM97: =+IF(AM$2=$E97,$D97,IF(AM$2>AM$257,0,IF($C97=AM$2,"PAGAR"&" "&TEXT($B97," #.##0,00"),0))) -> 0 | AN97: =+IF(F97<0,-F97,0) -> 0 | AO97: =+IF(AND(C97=0,B97>0),B97,0) -> 0
A98: Total de despesas previstas (Plan 2) | B98: =+SUM(B91:B97) -> 9996 | D98: =+SUM(D91:D97) -> 0 | F98: =+SUMIF(F91:F97,">0") -> 5188 | G98: =+IF(B98=0,"-",D98/B98) -> 0 | I98: =+PLAN2!H99 -> 0 | J98: =+PLAN2!I99 -> 0 | K98: =+PLAN2!J99 -> 0 | L98: =+PLAN2!K99 -> 0 | M98: =+PLAN2!L99 -> 5188 | N98: =+PLAN2!M99 -> 0 | O98: =+PLAN2!N99 -> 0 | P98: =+PLAN2!O99 -> 0 | ... AM98: =+PLAN2!AL99 -> 0 | AN98: =SUM(AN91:AN97) -> 0
A99: ACORDOS
A100: 5asec (22/22 parcelas) | B100: 10606.05 | C100: 8 | F100: =+IF(TODAY()<DATEVALUE(1&D$1&E$1),0,IF(C100>0,IF(C100-SUM(I$255:AM$255)<0,B100-SUM(I100:AM100,0),0),0))+IF(C100=-1,B100-SUM(J100:AM100)) -> 10606.05 | G100: =+IF(B100=0,"-",D100/B100) -> 0 | I100: =IF(I$2=$E100,$D100,IF(I$2>I$257,0,IF($C100=I$2,"PAGAR"&" "&TEXT($B100," #.##0,00"),IF($C100=-1,"PAGAR"&" "&TEXT($B100," #.##0,00"),0)))) -> 0 | J100: =+IF(J$2=$E100,$D100,IF(J$2>J$257,0,IF($C100=J$2,"PAGAR"&" "&TEXT($B100," #.##0,00"),0))) -> 0 | K100: =+IF(K$2=$E100,$D100,IF(K$2>K$257,0,IF($C100=K$2,"PAGAR"&" "&TEXT($B100," #.##0,00"),0))) -> 0 | L100: =+IF(L$2=$E100,$D100,IF(L$2>L$257,0,IF($C100=L$2,"PAGAR"&" "&TEXT($B100," #.##0,00"),0))) -> 0 | M100: =+IF(M$2=$E100,$D100,IF(M$2>M$257,0,IF($C100=M$2,"PAGAR"&" "&TEXT($B100," #.##0,00"),0))) -> 0 | N100: =+IF(N$2=$E100,$D100,IF(N$2>N$257,0,IF($C100=N$2,"PAGAR"&" "&TEXT($B100," #.##0,00"),0))) -> 0 | O100: =+IF(O$2=$E100,$D100,IF(O$2>O$257,0,IF($C100=O$2,"PAGAR"&" "&TEXT($B100," #.##0,00"),0))) -> 0 | P100: =+IF(P$2=$E100,$D100,IF(P$2>P$257,0,IF($C100=P$2,"PAGAR"&" "&TEXT($B100," #.##0,00"),0))) -> PAGAR 10.606,05 | Q100: =+IF(Q$2=$E100,$D100,IF(Q$2>Q$257,0,IF($C100=Q$2,"PAGAR"&" "&TEXT($B100," #.##0,00"),0))) -> 0 | ... AM100: =+IF(AM$2=$E100,$D100,IF(AM$2>AM$257,0,IF($C100=AM$2,"PAGAR"&" "&TEXT($B100," #.##0,00"),0))) -> 0 | AN100: =+IF(F100<0,-F100,0) -> 0 | AO100: =+IF(AND(C100=0,B100>0),B100,0) -> 0
A101: 5asec advogados (22/22parcelas) | B101: 3030.3 | C101: 11 | F101: =+IF(TODAY()<DATEVALUE(1&D$1&E$1),0,IF(C101>0,IF(C101-SUM(I$255:AM$255)<0,B101-SUM(I101:AM101,0),0),0))+IF(C101=-1,B101-SUM(J101:AM101)) -> 3030.3 | G101: =+IF(B101=0,"-",D101/B101) -> 0 | I101: =IF(I$2=$E101,$D101,IF(I$2>I$257,0,IF($C101=I$2,"PAGAR"&" "&TEXT($B101," #.##0,00"),IF($C101=-1,"PAGAR"&" "&TEXT($B101," #.##0,00"),0)))) -> 0 | J101: =+IF(J$2=$E101,$D101,IF(J$2>J$257,0,IF($C101=J$2,"PAGAR"&" "&TEXT($B101," #.##0,00"),0))) -> 0 | K101: =+IF(K$2=$E101,$D101,IF(K$2>K$257,0,IF($C101=K$2,"PAGAR"&" "&TEXT($B101," #.##0,00"),0))) -> 0 | L101: =+IF(L$2=$E101,$D101,IF(L$2>L$257,0,IF($C101=L$2,"PAGAR"&" "&TEXT($B101," #.##0,00"),0))) -> 0 | M101: =+IF(M$2=$E101,$D101,IF(M$2>M$257,0,IF($C101=M$2,"PAGAR"&" "&TEXT($B101," #.##0,00"),0))) -> 0 | N101: =+IF(N$2=$E101,$D101,IF(N$2>N$257,0,IF($C101=N$2,"PAGAR"&" "&TEXT($B101," #.##0,00"),0))) -> 0 | O101: =+IF(O$2=$E101,$D101,IF(O$2>O$257,0,IF($C101=O$2,"PAGAR"&" "&TEXT($B101," #.##0,00"),0))) -> 0 | P101: =+IF(P$2=$E101,$D101,IF(P$2>P$257,0,IF($C101=P$2,"PAGAR"&" "&TEXT($B101," #.##0,00"),0))) -> 0 | Q101: =+IF(Q$2=$E101,$D101,IF(Q$2>Q$257,0,IF($C101=Q$2,"PAGAR"&" "&TEXT($B101," #.##0,00"),0))) -> 0 | ... AM101: =+IF(AM$2=$E101,$D101,IF(AM$2>AM$257,0,IF($C101=AM$2,"PAGAR"&" "&TEXT($B101," #.##0,00"),0))) -> 0 | AN101: =+IF(F101<0,-F101,0) -> 0 | AO101: =+IF(AND(C101=0,B101>0),B101,0) -> 0
F102: =+IF(TODAY()<DATEVALUE(1&D$1&E$1),0,IF(C102>0,IF(C102-SUM(I$255:AM$255)<0,B102-SUM(I102:AM102,0),0),0))+IF(C102=-1,B102-SUM(J102:AM102)) -> 0 | G102: =+IF(B102=0,"-",D102/B102) -> - | I102: =IF(I$2=$E102,$D102,IF(I$2>I$257,0,IF($C102=I$2,"PAGAR"&" "&TEXT($B102," #.##0,00"),IF($C102=-1,"PAGAR"&" "&TEXT($B102," #.##0,00"),0)))) -> 0 | J102: =+IF(J$2=$E102,$D102,IF(J$2>J$257,0,IF($C102=J$2,"PAGAR"&" "&TEXT($B102," #.##0,00"),0))) -> 0 | K102: =+IF(K$2=$E102,$D102,IF(K$2>K$257,0,IF($C102=K$2,"PAGAR"&" "&TEXT($B102," #.##0,00"),0))) -> 0 | L102: =+IF(L$2=$E102,$D102,IF(L$2>L$257,0,IF($C102=L$2,"PAGAR"&" "&TEXT($B102," #.##0,00"),0))) -> 0 | M102: =+IF(M$2=$E102,$D102,IF(M$2>M$257,0,IF($C102=M$2,"PAGAR"&" "&TEXT($B102," #.##0,00"),0))) -> 0 | N102: =+IF(N$2=$E102,$D102,IF(N$2>N$257,0,IF($C102=N$2,"PAGAR"&" "&TEXT($B102," #.##0,00"),0))) -> 0 | O102: =+IF(O$2=$E102,$D102,IF(O$2>O$257,0,IF($C102=O$2,"PAGAR"&" "&TEXT($B102," #.##0,00"),0))) -> 0 | P102: =+IF(P$2=$E102,$D102,IF(P$2>P$257,0,IF($C102=P$2,"PAGAR"&" "&TEXT($B102," #.##0,00"),0))) -> 0 | Q102: =+IF(Q$2=$E102,$D102,IF(Q$2>Q$257,0,IF($C102=Q$2,"PAGAR"&" "&TEXT($B102," #.##0,00"),0))) -> 0 | ... AM102: =+IF(AM$2=$E102,$D102,IF(AM$2>AM$257,0,IF($C102=AM$2,"PAGAR"&" "&TEXT($B102," #.##0,00"),0))) -> 0 | AN102: =+IF(F102<0,-F102,0) -> 0 | AO102: =+IF(AND(C102=0,B102>0),B102,0) -> 0
...

Sheet PLAN2
D1: =+DESP_JANEIRO!I258 -> 46053 | F1: =DAY(TODAY()) -> 13 | H1: =+DESP_JANEIRO!I256 -> 46023 | I1: =+DESP_JANEIRO!J256 -> 46024 | J1: =+DESP_JANEIRO!K256 -> 46025 | K1: =+DESP_JANEIRO!L256 -> 46026 | L1: =+DESP_JANEIRO!M256 -> 46027 | M1: =+DESP_JANEIRO!N256 -> 46028 | N1: =+DESP_JANEIRO!O256 -> 46029 | O1: =+DESP_JANEIRO!P256 -> 46030 | ... AL1: =+DESP_JANEIRO!AM256 -> 46053
A2: =+DESP_JANEIRO!D1 -> JANEIRO | B2: =+DESP_JANEIRO!E1 -> 2026 | C2: DIAS NO MÊS ==> | D2: =+DESP_JANEIRO!G1 -> 31 | E2: % mês==> | F2: =+SUM(H$172:AL$172)/$D$2 -> 0.41935484 | H2: =IF(H1>$D1,"",WEEKDAY(H1)) -> 5 | I2: =IF(I1>$D1,"",WEEKDAY(I1)) -> 6 | J2: =IF(J1>$D1,"",WEEKDAY(J1)) -> 7 | K2: =IF(K1>$D1,"",WEEKDAY(K1)) -> 1 | L2: =IF(L1>$D1,"",WEEKDAY(L1)) -> 2 | M2: =IF(M1>$D1,"",WEEKDAY(M1)) -> 3 | N2: =IF(N1>$D1,"",WEEKDAY(N1)) -> 4 | O2: =IF(O1>$D1,"",WEEKDAY(O1)) -> 5 | ... AL2: =IF(AL1>$D1,"",WEEKDAY(AL1)) -> 7
A3: DESCRIÇÃO | B3: Orçado | C3: Dia Vencimento | D3: Em atraso | E3: Realizado Acum. | F3: R/O | H3: 1 | I3: =H3+1 -> 2 | J3: =I3+1 -> 3 | K3: =J3+1 -> 4 | L3: =K3+1 -> 5 | M3: =L3+1 -> 6 | N3: =M3+1 -> 7 | O3: =N3+1 -> 8 | P3: =O3+1 -> 9 | ... AL3: =AK3+1 -> 31
D4: e acumulado
A6: =+SUM(H6:AL6)-B6 -> 0 | B6: =+DESP_JANEIRO!B5 -> 6650 | C6: =+DESP_JANEIRO!C5 -> 2 | D6: =+DESP_JANEIRO!F5 -> 0 | E6: =+SUM(H6:AL6) -> 6650 | F6: =+IF(B6=0,"-",E6/B6) -> 1 | H6: =+IF(H$3>$D$2,0,IF(OR(C6=-1,C6=H$3),$B6,0)) -> 0 | I6: =+IF(I$3>$D$2,0,IF($C6=I$3,$B6,0)) -> 6650 | J6: =+IF(J$3>$D$2,0,IF($C6=J$3,$B6,0)) -> 0 | K6: =+IF(K$3>$D$2,0,IF($C6=K$3,$B6,0)) -> 0 | L6: =+IF(L$3>$D$2,0,IF($C6=L$3,$B6,0)) -> 0 | M6: =+IF(M$3>$D$2,0,IF($C6=M$3,$B6,0)) -> 0 | N6: =+IF(N$3>$D$2,0,IF($C6=N$3,$B6,0)) -> 0 | O6: =+IF(O$3>$D$2,0,IF($C6=O$3,$B6,0)) -> 0 | P6: =+IF(P$3>$D$2,0,IF($C6=P$3,$B6,0)) -> 0 | ... AL6: =+IF(AL$3>$D$2,0,IF($C6=AL$3,$B6,0)) -> 0
A7: =+SUM(H7:AL7)-B7 -> 0 | B7: =+DESP_JANEIRO!B6 -> 6359.51 | C7: =+DESP_JANEIRO!C6 -> 7 | D7: =+DESP_JANEIRO!F6 -> 6359.51 | E7: =+SUM(H7:AL7) -> 6359.51 | F7: =+IF(B7=0,"-",E7/B7) -> 1 | H7: =+IF(H$3>$D$2,0,IF(OR(C7=-1,C7=H$3),$B7,0)) -> 0 | I7: =+IF(I$3>$D$2,0,IF($C7=I$3,$B7,0)) -> 0 | J7: =+IF(J$3>$D$2,0,IF($C7=J$3,$B7,0)) -> 0 | K7: =+IF(K$3>$D$2,0,IF($C7=K$3,$B7,0)) -> 0 | L7: =+IF(L$3>$D$2,0,IF($C7=L$3,$B7,0)) -> 0 | M7: =+IF(M$3>$D$2,0,IF($C7=M$3,$B7,0)) -> 0 | N7: =+IF(N$3>$D$2,0,IF($C7=N$3,$B7,0)) -> 6359.51 | O7: =+IF(O$3>$D$2,0,IF($C7=O$3,$B7,0)) -> 0 | P7: =+IF(P$3>$D$2,0,IF($C7=P$3,$B7,0)) -> 0 | ... AL7: =+IF(AL$3>$D$2,0,IF($C7=AL$3,$B7,0)) -> 0
A8: =+SUM(H8:AL8)-B8 -> -770.07 | B8: =+DESP_JANEIRO!B7 -> 770.07 | C8: =+DESP_JANEIRO!C7 -> 0 | D8: =+DESP_JANEIRO!F7 -> 0 | E8: =+SUM(H8:AL8) -> 0 | F8: =+IF(B8=0,"-",E8/B8) -> 0 | H8: =+IF(H$3>$D$2,0,IF(OR(C8=-1,C8=H$3),$B8,0)) -> 0 | I8: =+IF(I$3>$D$2,0,IF($C8=I$3,$B8,0)) -> 0 | J8: =+IF(J$3>$D$2,0,IF($C8=J$3,$B8,0)) -> 0 | K8: =+IF(K$3>$D$2,0,IF($C8=K$3,$B8,0)) -> 0 | L8: =+IF(L$3>$D$2,0,IF($C8=L$3,$B8,0)) -> 0 | M8: =+IF(M$3>$D$2,0,IF($C8=M$3,$B8,0)) -> 0 | N8: =+IF(N$3>$D$2,0,IF($C8=N$3,$B8,0)) -> 0 | O8: =+IF(O$3>$D$2,0,IF($C8=O$3,$B8,0)) -> 0 | P8: =+IF(P$3>$D$2,0,IF($C8=P$3,$B8,0)) -> 0 | ... AL8: =+IF(AL$3>$D$2,0,IF($C8=AL$3,$B8,0)) -> 0
A9: =+SUM(H9:AL9)-B9 -> 0 | B9: =+DESP_JANEIRO!B8 -> 770.07 | C9: =+DESP_JANEIRO!C8 -> 25 | D9: =+DESP_JANEIRO!F8 -> 0 | E9: =+SUM(H9:AL9) -> 770.07 | F9: =+IF(B9=0,"-",E9/B9) -> 1 | H9: =+IF(H$3>$D$2,0,IF(OR(C9=-1,C9=H$3),$B9,0)) -> 0 | I9: =+IF(I$3>$D$2,0,IF($C9=I$3,$B9,0)) -> 0 | J9: =+IF(J$3>$D$2,0,IF($C9=J$3,$B9,0)) -> 0 | K9: =+IF(K$3>$D$2,0,IF($C9=K$3,$B9,0)) -> 0 | L9: =+IF(L$3>$D$2,0,IF($C9=L$3,$B9,0)) -> 0 | M9: =+IF(M$3>$D$2,0,IF($C9=M$3,$B9,0)) -> 0 | N9: =+IF(N$3>$D$2,0,IF($C9=N$3,$B9,0)) -> 0 | O9: =+IF(O$3>$D$2,0,IF($C9=O$3,$B9,0)) -> 0 | P9: =+IF(P$3>$D$2,0,IF($C9=P$3,$B9,0)) -> 0 | ... AL9: =+IF(AL$3>$D$2,0,IF($C9=AL$3,$B9,0)) -> 0
A10: =+SUM(H10:AL10)-B10 -> 0 | B10: =+DESP_JANEIRO!B9 -> 675.52 | C10: =+DESP_JANEIRO!C9 -> 25 | D10: =+DESP_JANEIRO!F9 -> 0 | E10: =+SUM(H10:AL10) -> 675.52 | F10: =+IF(B10=0,"-",E10/B10) -> 1 | H10: =+IF(H$3>$D$2,0,IF(OR(C10=-1,C10=H$3),$B10,0)) -> 0 | I10: =+IF(I$3>$D$2,0,IF($C10=I$3,$B10,0)) -> 0 | J10: =+IF(J$3>$D$2,0,IF($C10=J$3,$B10,0)) -> 0 | K10: =+IF(K$3>$D$2,0,IF($C10=K$3,$B10,0)) -> 0 | L10: =+IF(L$3>$D$2,0,IF($C10=L$3,$B10,0)) -> 0 | M10: =+IF(M$3>$D$2,0,IF($C10=M$3,$B10,0)) -> 0 | N10: =+IF(N$3>$D$2,0,IF($C10=N$3,$B10,0)) -> 0 | O10: =+IF(O$3>$D$2,0,IF($C10=O$3,$B10,0)) -> 0 | P10: =+IF(P$3>$D$2,0,IF($C10=P$3,$B10,0)) -> 0 | ... AL10: =+IF(AL$3>$D$2,0,IF($C10=AL$3,$B10,0)) -> 0
A11: =+SUM(H11:AL11)-B11 -> 0 | B11: =+DESP_JANEIRO!B10 -> 1928.17 | C11: =+DESP_JANEIRO!C10 -> 28 | D11: =+DESP_JANEIRO!F10 -> 0 | E11: =+SUM(H11:AL11) -> 1928.17 | F11: =+IF(B11=0,"-",E11/B11) -> 1 | H11: =+IF(H$3>$D$2,0,IF(OR(C11=-1,C11=H$3),$B11,0)) -> 0 | I11: =+IF(I$3>$D$2,0,IF($C11=I$3,$B11,0)) -> 0 | J11: =+IF(J$3>$D$2,0,IF($C11=J$3,$B11,0)) -> 0 | K11: =+IF(K$3>$D$2,0,IF($C11=K$3,$B11,0)) -> 0 | L11: =+IF(L$3>$D$2,0,IF($C11=L$3,$B11,0)) -> 0 | M11: =+IF(M$3>$D$2,0,IF($C11=M$3,$B11,0)) -> 0 | N11: =+IF(N$3>$D$2,0,IF($C11=N$3,$B11,0)) -> 0 | O11: =+IF(O$3>$D$2,0,IF($C11=O$3,$B11,0)) -> 0 | P11: =+IF(P$3>$D$2,0,IF($C11=P$3,$B11,0)) -> 0 | ... AL11: =+IF(AL$3>$D$2,0,IF($C11=AL$3,$B11,0)) -> 0
A12: =+SUM(H12:AL12)-B12 -> 0 | B12: =+DESP_JANEIRO!B11 -> 5.9 | C12: =+DESP_JANEIRO!C11 -> 3 | D12: =+DESP_JANEIRO!F11 -> 5.9 | E12: =+SUM(H12:AL12) -> 5.9 | F12: =+IF(B12=0,"-",E12/B12) -> 1 | H12: =+IF(H$3>$D$2,0,IF(OR(C12=-1,C12=H$3),$B12,0)) -> 0 | I12: =+IF(I$3>$D$2,0,IF($C12=I$3,$B12,0)) -> 0 | J12: =+IF(J$3>$D$2,0,IF($C12=J$3,$B12,0)) -> 5.9 | K12: =+IF(K$3>$D$2,0,IF($C12=K$3,$B12,0)) -> 0 | L12: =+IF(L$3>$D$2,0,IF($C12=L$3,$B12,0)) -> 0 | M12: =+IF(M$3>$D$2,0,IF($C12=M$3,$B12,0)) -> 0 | N12: =+IF(N$3>$D$2,0,IF($C12=N$3,$B12,0)) -> 0 | O12: =+IF(O$3>$D$2,0,IF($C12=O$3,$B12,0)) -> 0 | P12: =+IF(P$3>$D$2,0,IF($C12=P$3,$B12,0)) -> 0 | ... AL12: =+IF(AL$3>$D$2,0,IF($C12=AL$3,$B12,0)) -> 0
A13: =+SUM(H13:AL13)-B13 -> 0 | B13: =+DESP_JANEIRO!B12 -> 44.9 | C13: =+DESP_JANEIRO!C12 -> 7 | D13: =+DESP_JANEIRO!F12 -> 44.9 | E13: =+SUM(H13:AL13) -> 44.9 | F13: =+IF(B13=0,"-",E13/B13) -> 1 | H13: =+IF(H$3>$D$2,0,IF(OR(C13=-1,C13=H$3),$B13,0)) -> 0 | I13: =+IF(I$3>$D$2,0,IF($C13=I$3,$B13,0)) -> 0 | J13: =+IF(J$3>$D$2,0,IF($C13=J$3,$B13,0)) -> 0 | K13: =+IF(K$3>$D$2,0,IF($C13=K$3,$B13,0)) -> 0 | L13: =+IF(L$3>$D$2,0,IF($C13=L$3,$B13,0)) -> 0 | M13: =+IF(M$3>$D$2,0,IF($C13=M$3,$B13,0)) -> 0 | N13: =+IF(N$3>$D$2,0,IF($C13=N$3,$B13,0)) -> 44.9 | O13: =+IF(O$3>$D$2,0,IF($C13=O$3,$B13,0)) -> 0 | P13: =+IF(P$3>$D$2,0,IF($C13=P$3,$B13,0)) -> 0 | ... AL13: =+IF(AL$3>$D$2,0,IF($C13=AL$3,$B13,0)) -> 0
A14: =+SUM(H14:AL14)-B14 -> 0 | B14: =+DESP_JANEIRO!B13 -> 96.99 | C14: =+DESP_JANEIRO!C13 -> 22 | D14: =+DESP_JANEIRO!F13 -> 0 | E14: =+SUM(H14:AL14) -> 96.99 | F14: =+IF(B14=0,"-",E14/B14) -> 1 | H14: =+IF(H$3>$D$2,0,IF(OR(C14=-1,C14=H$3),$B14,0)) -> 0 | I14: =+IF(I$3>$D$2,0,IF($C14=I$3,$B14,0)) -> 0 | J14: =+IF(J$3>$D$2,0,IF($C14=J$3,$B14,0)) -> 0 | K14: =+IF(K$3>$D$2,0,IF($C14=K$3,$B14,0)) -> 0 | L14: =+IF(L$3>$D$2,0,IF($C14=L$3,$B14,0)) -> 0 | M14: =+IF(M$3>$D$2,0,IF($C14=M$3,$B14,0)) -> 0 | N14: =+IF(N$3>$D$2,0,IF($C14=N$3,$B14,0)) -> 0 | O14: =+IF(O$3>$D$2,0,IF($C14=O$3,$B14,0)) -> 0 | P14: =+IF(P$3>$D$2,0,IF($C14=P$3,$B14,0)) -> 0 | ... AL14: =+IF(AL$3>$D$2,0,IF($C14=AL$3,$B14,0)) -> 0
A15: =+SUM(H15:AL15)-B15 -> 0 | B15: =+DESP_JANEIRO!B14 -> 286.78 | C15: =+DESP_JANEIRO!C14 -> 28 | D15: =+DESP_JANEIRO!F14 -> 0 | E15: =+SUM(H15:AL15) -> 286.78 | F15: =+IF(B15=0,"-",E15/B15) -> 1 | H15: =+IF(H$3>$D$2,0,IF(OR(C15=-1,C15=H$3),$B15,0)) -> 0 | I15: =+IF(I$3>$D$2,0,IF($C15=I$3,$B15,0)) -> 0 | J15: =+IF(J$3>$D$2,0,IF($C15=J$3,$B15,0)) -> 0 | K15: =+IF(K$3>$D$2,0,IF($C15=K$3,$B15,0)) -> 0 | L15: =+IF(L$3>$D$2,0,IF($C15=L$3,$B15,0)) -> 0 | M15: =+IF(M$3>$D$2,0,IF($C15=M$3,$B15,0)) -> 0 | N15: =+IF(N$3>$D$2,0,IF($C15=N$3,$B15,0)) -> 0 | O15: =+IF(O$3>$D$2,0,IF($C15=O$3,$B15,0)) -> 0 | P15: =+IF(P$3>$D$2,0,IF($C15=P$3,$B15,0)) -> 0 | ... AL15: =+IF(AL$3>$D$2,0,IF($C15=AL$3,$B15,0)) -> 0
A16: =+SUM(H16:AL16)-B16 -> 0 | B16: =+DESP_JANEIRO!B15 -> 29.9 | C16: =+DESP_JANEIRO!C15 -> 28 | D16: =+DESP_JANEIRO!F15 -> 0 | E16: =+SUM(H16:AL16) -> 29.9 | F16: =+IF(B16=0,"-",E16/B16) -> 1 | H16: =+IF(H$3>$D$2,0,IF(OR(C16=-1,C16=H$3),$B16,0)) -> 0 | I16: =+IF(I$3>$D$2,0,IF($C16=I$3,$B16,0)) -> 0 | J16: =+IF(J$3>$D$2,0,IF($C16=J$3,$B16,0)) -> 0 | K16: =+IF(K$3>$D$2,0,IF($C16=K$3,$B16,0)) -> 0 | L16: =+IF(L$3>$D$2,0,IF($C16=L$3,$B16,0)) -> 0 | M16: =+IF(M$3>$D$2,0,IF($C16=M$3,$B16,0)) -> 0 | N16: =+IF(N$3>$D$2,0,IF($C16=N$3,$B16,0)) -> 0 | O16: =+IF(O$3>$D$2,0,IF($C16=O$3,$B16,0)) -> 0 | P16: =+IF(P$3>$D$2,0,IF($C16=P$3,$B16,0)) -> 0 | ... AL16: =+IF(AL$3>$D$2,0,IF($C16=AL$3,$B16,0)) -> 0
A17: =+SUM(H17:AL17)-B17 -> 0 | B17: =+DESP_JANEIRO!B16 -> 5.9 | C17: =+DESP_JANEIRO!C16 -> 5 | D17: =+DESP_JANEIRO!F16 -> 5.9 | E17: =+SUM(H17:AL17) -> 5.9 | F17: =+IF(B17=0,"-",E17/B17) -> 1 | H17: =+IF(H$3>$D$2,0,IF(OR(C17=-1,C17=H$3),$B17,0)) -> 0 | I17: =+IF(I$3>$D$2,0,IF($C17=I$3,$B17,0)) -> 0 | J17: =+IF(J$3>$D$2,0,IF($C17=J$3,$B17,0)) -> 0 | K17: =+IF(K$3>$D$2,0,IF($C17=K$3,$B17,0)) -> 0 | L17: =+IF(L$3>$D$2,0,IF($C17=L$3,$B17,0)) -> 5.9 | M17: =+IF(M$3>$D$2,0,IF($C17=M$3,$B17,0)) -> 0 | N17: =+IF(N$3>$D$2,0,IF($C17=N$3,$B17,0)) -> 0 | O17: =+IF(O$3>$D$2,0,IF($C17=O$3,$B17,0)) -> 0 | P17: =+IF(P$3>$D$2,0,IF($C17=P$3,$B17,0)) -> 0 | ... AL17: =+IF(AL$3>$D$2,0,IF($C17=AL$3,$B17,0)) -> 0
... A26: =+SUM(H26:AL26)-B26 -> 0 | B26: =+DESP_JANEIRO!B25 -> 0 | C26: =+DESP_JANEIRO!C25 -> 0 | D26: =+DESP_JANEIRO!F25 -> 0 | E26: =+SUM(H26:AL26) -> 0 | F26: =+IF(B26=0,"-",E26/B26) -> - | H26: =+IF(H$3>$D$2,0,IF(OR(C26=-1,C26=H$3),$B26,0)) -> 0 | I26: =+IF(I$3>$D$2,0,IF($C26=I$3,$B26,0)) -> 0 | J26: =+IF(J$3>$D$2,0,IF($C26=J$3,$B26,0)) -> 0 | K26: =+IF(K$3>$D$2,0,IF($C26=K$3,$B26,0)) -> 0 | L26: =+IF(L$3>$D$2,0,IF($C26=L$3,$B26,0)) -> 0 | M26: =+IF(M$3>$D$2,0,IF($C26=M$3,$B26,0)) -> 0 | N26: =+IF(N$3>$D$2,0,IF($C26=N$3,$B26,0)) -> 0 | O26: =+IF(O$3>$D$2,0,IF($C26=O$3,$B26,0)) -> 0 | P26: =+IF(P$3>$D$2,0,IF($C26=P$3,$B26,0)) -> 0 | ... AL26: =+IF(AL$3>$D$2,0,IF($C26=AL$3,$B26,0)) -> 0
A27: Totais | B27: =+SUM(B6:B26) -> 17706.7 | D27: =+SUM(D6:D26) -> 6499.2 | E27: =+SUM(E6:E26) -> 16936.63 | F27: =+IF(B27=0,"-",E27/B27) -> 0.95650968 | H27: =+SUM(H6:H26) -> 0 | I27: =+SUM(I6:I26) -> 6650 | J27: =+SUM(J6:J26) -> 65.9 | K27: =+SUM(K6:K26) -> 22.99 | L27: =+SUM(L6:L26) -> 5.9 | M27: =+SUM(M6:M26) -> 0 | N27: =+SUM(N6:N26) -> 6404.41 | O27: =+SUM(O6:O26) -> 0 | ... AL27: =+SUM(AL6:AL26) -> 0
A29: =+SUM(H29:AL29)-B29 -> 0 | B29: =+DESP_JANEIRO!B28 -> 2945.42 | C29: =+DESP_JANEIRO!C28 -> 11 | D29: =+DESP_JANEIRO!F28 -> 2945.42 | E29: =+SUM(H29:AL29) -> 2945.42 | F29: =+IF(B29=0,"-",E29/B29) -> 1 | H29: =+IF(H$3>$D$2,0,IF(OR(C29=-1,C29=H$3),$B29,0)) -> 0 | I29: =+IF(I$3>$D$2,0,IF($C29=I$3,$B29,0)) -> 0 | J29: =+IF(J$3>$D$2,0,IF($C29=J$3,$B29,0)) -> 0 | K29: =+IF(K$3>$D$2,0,IF($C29=K$3,$B29,0)) -> 0 | L29: =+IF(L$3>$D$2,0,IF($C29=L$3,$B29,0)) -> 0 | M29: =+IF(M$3>$D$2,0,IF($C29=M$3,$B29,0)) -> 0 | N29: =+IF(N$3>$D$2,0,IF($C29=N$3,$B29,0)) -> 0 | O29: =+IF(O$3>$D$2,0,IF($C29=O$3,$B29,0)) -> 0 | P29: =+IF(P$3>$D$2,0,IF($C29=P$3,$B29,0)) -> 0 | ... AL29: =+IF(AL$3>$D$2,0,IF($C29=AL$3,$B29,0)) -> 0
A30: =+SUM(H30:AL30)-B30 -> 0 | B30: =+DESP_JANEIRO!B29 -> 2775 | C30: =+DESP_JANEIRO!C29 -> 26 | D30: =+DESP_JANEIRO!F29 -> 0 | E30: =+SUM(H30:AL30) -> 2775 | F30: =+IF(B30=0,"-",E30/B30) -> 1 | H30: =+IF(H$3>$D$2,0,IF(OR(C30=-1,C30=H$3),$B30,0)) -> 0 | I30: =+IF(I$3>$D$2,0,IF($C30=I$3,$B30,0)) -> 0 | J30: =+IF(J$3>$D$2,0,IF($C30=J$3,$B30,0)) -> 0 | K30: =+IF(K$3>$D$2,0,IF($C30=K$3,$B30,0)) -> 0 | L30: =+IF(L$3>$D$2,0,IF($C30=L$3,$B30,0)) -> 0 | M30: =+IF(M$3>$D$2,0,IF($C30=M$3,$B30,0)) -> 0 | N30: =+IF(N$3>$D$2,0,IF($C30=N$3,$B30,0)) -> 0 | O30: =+IF(O$3>$D$2,0,IF($C30=O$3,$B30,0)) -> 0 | P30: =+IF(P$3>$D$2,0,IF($C30=P$3,$B30,0)) -> 0 | ... AL30: =+IF(AL$3>$D$2,0,IF($C30=AL$3,$B30,0)) -> 0
A31: =+SUM(H31:AL31)-B31 -> 0 | B31: =+DESP_JANEIRO!B30 -> 940 | C31: =+DESP_JANEIRO!C30 -> 15 | D31: =+DESP_JANEIRO!F30 -> 0 | E31: =+SUM(H31:AL31) -> 940 | F31: =+IF(B31=0,"-",E31/B31) -> 1 | H31: =+IF(H$3>$D$2,0,IF(OR(C31=-1,C31=H$3),$B31,0)) -> 0 | I31: =+IF(I$3>$D$2,0,IF($C31=I$3,$B31,0)) -> 0 | J31: =+IF(J$3>$D$2,0,IF($C31=J$3,$B31,0)) -> 0 | K31: =+IF(K$3>$D$2,0,IF($C31=K$3,$B31,0)) -> 0 | L31: =+IF(L$3>$D$2,0,IF($C31=L$3,$B31,0)) -> 0 | M31: =+IF(M$3>$D$2,0,IF($C31=M$3,$B31,0)) -> 0 | N31: =+IF(N$3>$D$2,0,IF($C31=N$3,$B31,0)) -> 0 | O31: =+IF(O$3>$D$2,0,IF($C31=O$3,$B31,0)) -> 0 | P31: =+IF(P$3>$D$2,0,IF($C31=P$3,$B31,0)) -> 0 | ... AL31: =+IF(AL$3>$D$2,0,IF($C31=AL$3,$B31,0)) -> 0
A32: =+SUM(H32:AL32)-B32 -> 0 | B32: =+DESP_JANEIRO!B31 -> 940 | C32: =+DESP_JANEIRO!C31 -> 30 | D32: =+DESP_JANEIRO!F31 -> 0 | E32: =+SUM(H32:AL32) -> 940 | F32: =+IF(B32=0,"-",E32/B32) -> 1 | H32: =+IF(H$3>$D$2,0,IF(OR(C32=-1,C32=H$3),$B32,0)) -> 0 | I32: =+IF(I$3>$D$2,0,IF($C32=I$3,$B32,0)) -> 0 | J32: =+IF(J$3>$D$2,0,IF($C32=J$3,$B32,0)) -> 0 | K32: =+IF(K$3>$D$2,0,IF($C32=K$3,$B32,0)) -> 0 | L32: =+IF(L$3>$D$2,0,IF($C32=L$3,$B32,0)) -> 0 | M32: =+IF(M$3>$D$2,0,IF($C32=M$3,$B32,0)) -> 0 | N32: =+IF(N$3>$D$2,0,IF($C32=N$3,$B32,0)) -> 0 | O32: =+IF(O$3>$D$2,0,IF($C32=O$3,$B32,0)) -> 0 | P32: =+IF(P$3>$D$2,0,IF($C32=P$3,$B32,0)) -> 0 | ... AL32: =+IF(AL$3>$D$2,0,IF($C32=AL$3,$B32,0)) -> 0
A33: =+SUM(H33:AL33)-B33 -> 0 | B33: =+DESP_JANEIRO!B32 -> 1080 | C33: =+DESP_JANEIRO!C32 -> 6 | D33: =+DESP_JANEIRO!F32 -> 1080 | E33: =+SUM(H33:AL33) -> 1080 | F33: =+IF(B33=0,"-",E33/B33) -> 1 | H33: =+IF(H$3>$D$2,0,IF(OR(C33=-1,C33=H$3),$B33,0)) -> 0 | I33: =+IF(I$3>$D$2,0,IF($C33=I$3,$B33,0)) -> 0 | J33: =+IF(J$3>$D$2,0,IF($C33=J$3,$B33,0)) -> 0 | K33: =+IF(K$3>$D$2,0,IF($C33=K$3,$B33,0)) -> 0 | L33: =+IF(L$3>$D$2,0,IF($C33=L$3,$B33,0)) -> 0 | M33: =+IF(M$3>$D$2,0,IF($C33=M$3,$B33,0)) -> 1080 | N33: =+IF(N$3>$D$2,0,IF($C33=N$3,$B33,0)) -> 0 | O33: =+IF(O$3>$D$2,0,IF($C33=O$3,$B33,0)) -> 0 | P33: =+IF(P$3>$D$2,0,IF($C33=P$3,$B33,0)) -> 0 | ... AL33: =+IF(AL$3>$D$2,0,IF($C33=AL$3,$B33,0)) -> 0
A34: =+SUM(H34:AL34)-B34 -> 0 | B34: =+DESP_JANEIRO!B33 -> 720 | C34: =+DESP_JANEIRO!C33 -> 20 | D34: =+DESP_JANEIRO!F33 -> 0 | E34: =+SUM(H34:AL34) -> 720 | F34: =+IF(B34=0,"-",E34/B34) -> 1 | H34: =+IF(H$3>$D$2,0,IF(OR(C34=-1,C34=H$3),$B34,0)) -> 0 | I34: =+IF(I$3>$D$2,0,IF($C34=I$3,$B34,0)) -> 0 | J34: =+IF(J$3>$D$2,0,IF($C34=J$3,$B34,0)) -> 0 | K34: =+IF(K$3>$D$2,0,IF($C34=K$3,$B34,0)) -> 0 | L34: =+IF(L$3>$D$2,0,IF($C34=L$3,$B34,0)) -> 0 | M34: =+IF(M$3>$D$2,0,IF($C34=M$3,$B34,0)) -> 0 | N34: =+IF(N$3>$D$2,0,IF($C34=N$3,$B34,0)) -> 0 | O34: =+IF(O$3>$D$2,0,IF($C34=O$3,$B34,0)) -> 0 | P34: =+IF(P$3>$D$2,0,IF($C34=P$3,$B34,0)) -> 0 | ... AL34: =+IF(AL$3>$D$2,0,IF($C34=AL$3,$B34,0)) -> 0
A35: =+SUM(H35:AL35)-B35 -> 0 | B35: =+DESP_JANEIRO!B34 -> 1010 | C35: =+DESP_JANEIRO!C34 -> 17 | D35: =+DESP_JANEIRO!F34 -> 0 | E35: =+SUM(H35:AL35) -> 1010 | F35: =+IF(B35=0,"-",E35/B35) -> 1 | H35: =+IF(H$3>$D$2,0,IF(OR(C35=-1,C35=H$3),$B35,0)) -> 0 | I35: =+IF(I$3>$D$2,0,IF($C35=I$3,$B35,0)) -> 0 | J35: =+IF(J$3>$D$2,0,IF($C35=J$3,$B35,0)) -> 0 | K35: =+IF(K$3>$D$2,0,IF($C35=K$3,$B35,0)) -> 0 | L35: =+IF(L$3>$D$2,0,IF($C35=L$3,$B35,0)) -> 0 | M35: =+IF(M$3>$D$2,0,IF($C35=M$3,$B35,0)) -> 0 | N35: =+IF(N$3>$D$2,0,IF($C35=N$3,$B35,0)) -> 0 | O35: =+IF(O$3>$D$2,0,IF($C35=O$3,$B35,0)) -> 0 | P35: =+IF(P$3>$D$2,0,IF($C35=P$3,$B35,0)) -> 0 | ... AL35: =+IF(AL$3>$D$2,0,IF($C35=AL$3,$B35,0)) -> 0
A36: =+SUM(H36:AL36)-B36 -> 0 | B36: =+DESP_JANEIRO!B35 -> 500 | C36: =+DESP_JANEIRO!C35 -> 15 | D36: =+DESP_JANEIRO!F35 -> 0 | E36: =+SUM(H36:AL36) -> 500 | F36: =+IF(B36=0,"-",E36/B36) -> 1 | H36: =+IF(H$3>$D$2,0,IF(OR(C36=-1,C36=H$3),$B36,0)) -> 0 | I36: =+IF(I$3>$D$2,0,IF($C36=I$3,$B36,0)) -> 0 | J36: =+IF(J$3>$D$2,0,IF($C36=J$3,$B36,0)) -> 0 | K36: =+IF(K$3>$D$2,0,IF($C36=K$3,$B36,0)) -> 0 | L36: =+IF(L$3>$D$2,0,IF($C36=L$3,$B36,0)) -> 0 | M36: =+IF(M$3>$D$2,0,IF($C36=M$3,$B36,0)) -> 0 | N36: =+IF(N$3>$D$2,0,IF($C36=N$3,$B36,0)) -> 0 | O36: =+IF(O$3>$D$2,0,IF($C36=O$3,$B36,0)) -> 0 | P36: =+IF(P$3>$D$2,0,IF($C36=P$3,$B36,0)) -> 0 | ... AL36: =+IF(AL$3>$D$2,0,IF($C36=AL$3,$B36,0)) -> 0
A37: =+SUM(H37:AL37)-B37 -> 0 | B37: =+DESP_JANEIRO!B36 -> 569 | C37: =+DESP_JANEIRO!C36 -> 15 | D37: =+DESP_JANEIRO!F36 -> 0 | E37: =+SUM(H37:AL37) -> 569 | F37: =+IF(B37=0,"-",E37/B37) -> 1 | H37: =+IF(H$3>$D$2,0,IF(OR(C37=-1,C37=H$3),$B37,0)) -> 0 | I37: =+IF(I$3>$D$2,0,IF($C37=I$3,$B37,0)) -> 0 | J37: =+IF(J$3>$D$2,0,IF($C37=J$3,$B37,0)) -> 0 | K37: =+IF(K$3>$D$2,0,IF($C37=K$3,$B37,0)) -> 0 | L37: =+IF(L$3>$D$2,0,IF($C37=L$3,$B37,0)) -> 0 | M37: =+IF(M$3>$D$2,0,IF($C37=M$3,$B37,0)) -> 0 | N37: =+IF(N$3>$D$2,0,IF($C37=N$3,$B37,0)) -> 0 | O37: =+IF(O$3>$D$2,0,IF($C37=O$3,$B37,0)) -> 0 | P37: =+IF(P$3>$D$2,0,IF($C37=P$3,$B37,0)) -> 0 | ... AL37: =+IF(AL$3>$D$2,0,IF($C37=AL$3,$B37,0)) -> 0
A38: =+SUM(H38:AL38)-B38 -> 0 | B38: =+DESP_JANEIRO!B37 -> 1000 | C38: =+DESP_JANEIRO!C37 -> 2 | D38: =+DESP_JANEIRO!F37 -> 1000 | E38: =+SUM(H38:AL38) -> 1000 | F38: =+IF(B38=0,"-",E38/B38) -> 1 | H38: =+IF(H$3>$D$2,0,IF(OR(C38=-1,C38=H$3),$B38,0)) -> 0 | I38: =+IF(I$3>$D$2,0,IF($C38=I$3,$B38,0)) -> 1000 | J38: =+IF(J$3>$D$2,0,IF($C38=J$3,$B38,0)) -> 0 | K38: =+IF(K$3>$D$2,0,IF($C38=K$3,$B38,0)) -> 0 | L38: =+IF(L$3>$D$2,0,IF($C38=L$3,$B38,0)) -> 0 | M38: =+IF(M$3>$D$2,0,IF($C38=M$3,$B38,0)) -> 0 | N38: =+IF(N$3>$D$2,0,IF($C38=N$3,$B38,0)) -> 0 | O38: =+IF(O$3>$D$2,0,IF($C38=O$3,$B38,0)) -> 0 | P38: =+IF(P$3>$D$2,0,IF($C38=P$3,$B38,0)) -> 0 | ... AL38: =+IF(AL$3>$D$2,0,IF($C38=AL$3,$B38,0)) -> 0
A39: =+SUM(H39:AL39)-B39 -> 0 | B39: =+DESP_JANEIRO!B38 -> 1890 | C39: =+DESP_JANEIRO!C38 -> 3 | D39: =+DESP_JANEIRO!F38 -> 1890 | E39: =+SUM(H39:AL39) -> 1890 | F39: =+IF(B39=0,"-",E39/B39) -> 1 | H39: =+IF(H$3>$D$2,0,IF(OR(C39=-1,C39=H$3),$B39,0)) -> 0 | I39: =+IF(I$3>$D$2,0,IF($C39=I$3,$B39,0)) -> 0 | J39: =+IF(J$3>$D$2,0,IF($C39=J$3,$B39,0)) -> 1890 | K39: =+IF(K$3>$D$2,0,IF($C39=K$3,$B39,0)) -> 0 | L39: =+IF(L$3>$D$2,0,IF($C39=L$3,$B39,0)) -> 0 | M39: =+IF(M$3>$D$2,0,IF($C39=M$3,$B39,0)) -> 0 | N39: =+IF(N$3>$D$2,0,IF($C39=N$3,$B39,0)) -> 0 | O39: =+IF(O$3>$D$2,0,IF($C39=O$3,$B39,0)) -> 0 | P39: =+IF(P$3>$D$2,0,IF($C39=P$3,$B39,0)) -> 0 | ... AL39: =+IF(AL$3>$D$2,0,IF($C39=AL$3,$B39,0)) -> 0
A40: =+SUM(H40:AL40)-B40 -> 0 | B40: =+DESP_JANEIRO!B39 -> 420 | C40: =+DESP_JANEIRO!C39 -> 3 | D40: =+DESP_JANEIRO!F39 -> 420 | E40: =+SUM(H40:AL40) -> 420 | F40: =+IF(B40=0,"-",E40/B40) -> 1 | H40: =+IF(H$3>$D$2,0,IF(OR(C40=-1,C40=H$3),$B40,0)) -> 0 | I40: =+IF(I$3>$D$2,0,IF($C40=I$3,$B40,0)) -> 0 | J40: =+IF(J$3>$D$2,0,IF($C40=J$3,$B40,0)) -> 420 | K40: =+IF(K$3>$D$2,0,IF($C40=K$3,$B40,0)) -> 0 | L40: =+IF(L$3>$D$2,0,IF($C40=L$3,$B40,0)) -> 0 | M40: =+IF(M$3>$D$2,0,IF($C40=M$3,$B40,0)) -> 0 | N40: =+IF(N$3>$D$2,0,IF($C40=N$3,$B40,0)) -> 0 | O40: =+IF(O$3>$D$2,0,IF($C40=O$3,$B40,0)) -> 0 | P40: =+IF(P$3>$D$2,0,IF($C40=P$3,$B40,0)) -> 0 | ... AL40: =+IF(AL$3>$D$2,0,IF($C40=AL$3,$B40,0)) -> 0
... A44: =+SUM(H44:AL44)-B44 -> 0 | B44: =+DESP_JANEIRO!B43 -> 2211 | C44: =+DESP_JANEIRO!C43 -> 25 | D44: =+DESP_JANEIRO!F43 -> 0 | E44: =+SUM(H44:AL44) -> 2211 | F44: =+IF(B44=0,"-",E44/B44) -> 1 | H44: =+IF(H$3>$D$2,0,IF(OR(C44=-1,C44=H$3),$B44,0)) -> 0 | I44: =+IF(I$3>$D$2,0,IF($C44=I$3,$B44,0)) -> 0 | J44: =+IF(J$3>$D$2,0,IF($C44=J$3,$B44,0)) -> 0 | K44: =+IF(K$3>$D$2,0,IF($C44=K$3,$B44,0)) -> 0 | L44: =+IF(L$3>$D$2,0,IF($C44=L$3,$B44,0)) -> 0 | M44: =+IF(M$3>$D$2,0,IF($C44=M$3,$B44,0)) -> 0 | N44: =+IF(N$3>$D$2,0,IF($C44=N$3,$B44,0)) -> 0 | O44: =+IF(O$3>$D$2,0,IF($C44=O$3,$B44,0)) -> 0 | P44: =+IF(P$3>$D$2,0,IF($C44=P$3,$B44,0)) -> 0 | ... AL44: =+IF(AL$3>$D$2,0,IF($C44=AL$3,$B44,0)) -> 0
A45: Totais | B45: =+SUM(B29:B44) -> 22095.42 | D45: =+SUM(D29:D44) -> 7335.42 | E45: =+SUM(E29:E44) -> 22095.42 | F45: =+IF(B45=0,"-",E45/B45) -> 1 | H45: =+SUM(H29:H44) -> 0 | I45: =+SUM(I29:I44) -> 1000 | J45: =+SUM(J29:J44) -> 2310 | K45: =+SUM(K29:K44) -> 0 | L45: =+SUM(L29:L44) -> 0 | M45: =+SUM(M29:M44) -> 1080 | N45: =+SUM(N29:N44) -> 0 | O45: =+SUM(O29:O44) -> 0 | ... AL45: =+SUM(AL29:AL44) -> 0
A47: =+SUM(H47:AL47)-B47 -> 0 | B47: =+DESP_JANEIRO!B46 -> 500 | C47: =+DESP_JANEIRO!C46 -> 15 | D47: =+DESP_JANEIRO!F46 -> 0 | E47: =+SUM(H47:AL47) -> 500 | F47: =+IF(B47=0,"-",E47/B47) -> 1 | H47: =+IF(H$3>$D$2,0,IF(OR(C47=-1,C47=H$3),$B47,0)) -> 0 | I47: =+IF(I$3>$D$2,0,IF($C47=I$3,$B47,0)) -> 0 | J47: =+IF(J$3>$D$2,0,IF($C47=J$3,$B47,0)) -> 0 | K47: =+IF(K$3>$D$2,0,IF($C47=K$3,$B47,0)) -> 0 | L47: =+IF(L$3>$D$2,0,IF($C47=L$3,$B47,0)) -> 0 | M47: =+IF(M$3>$D$2,0,IF($C47=M$3,$B47,0)) -> 0 | N47: =+IF(N$3>$D$2,0,IF($C47=N$3,$B47,0)) -> 0 | O47: =+IF(O$3>$D$2,0,IF($C47=O$3,$B47,0)) -> 0 | P47: =+IF(P$3>$D$2,0,IF($C47=P$3,$B47,0)) -> 0 | ... AL47: =+IF(AL$3>$D$2,0,IF($C47=AL$3,$B47,0)) -> 0
A48: =+SUM(H48:AL48)-B48 -> 0 | B48: =+DESP_JANEIRO!B47 -> 500 | C48: =+DESP_JANEIRO!C47 -> 2 | D48: =+DESP_JANEIRO!F47 -> 500 | E48: =+SUM(H48:AL48) -> 500 | F48: =+IF(B48=0,"-",E48/B48) -> 1 | H48: =+IF(H$3>$D$2,0,IF(OR(C48=-1,C48=H$3),$B48,0)) -> 0 | I48: =+IF(I$3>$D$2,0,IF($C48=I$3,$B48,0)) -> 500 | J48: =+IF(J$3>$D$2,0,IF($C48=J$3,$B48,0)) -> 0 | K48: =+IF(K$3>$D$2,0,IF($C48=K$3,$B48,0)) -> 0 | L48: =+IF(L$3>$D$2,0,IF($C48=L$3,$B48,0)) -> 0 | M48: =+IF(M$3>$D$2,0,IF($C48=M$3,$B48,0)) -> 0 | N48: =+IF(N$3>$D$2,0,IF($C48=N$3,$B48,0)) -> 0 | O48: =+IF(O$3>$D$2,0,IF($C48=O$3,$B48,0)) -> 0 | P48: =+IF(P$3>$D$2,0,IF($C48=P$3,$B48,0)) -> 0 | ... AL48: =+IF(AL$3>$D$2,0,IF($C48=AL$3,$B48,0)) -> 0
A49: =+SUM(H49:AL49)-B49 -> 0 | B49: =+DESP_JANEIRO!B48 -> 0 | C49: =+DESP_JANEIRO!C48 -> 0 | D49: =+DESP_JANEIRO!F48 -> 0 | E49: =+SUM(H49:AL49) -> 0 | F49: =+IF(B49=0,"-",E49/B49) -> - | H49: =+IF(H$3>$D$2,0,IF(OR(C49=-1,C49=H$3),$B49,0)) -> 0 | I49: =+IF(I$3>$D$2,0,IF($C49=I$3,$B49,0)) -> 0 | J49: =+IF(J$3>$D$2,0,IF($C49=J$3,$B49,0)) -> 0 | K49: =+IF(K$3>$D$2,0,IF($C49=K$3,$B49,0)) -> 0 | L49: =+IF(L$3>$D$2,0,IF($C49=L$3,$B49,0)) -> 0 | M49: =+IF(M$3>$D$2,0,IF($C49=M$3,$B49,0)) -> 0 | N49: =+IF(N$3>$D$2,0,IF($C49=N$3,$B49,0)) -> 0 | O49: =+IF(O$3>$D$2,0,IF($C49=O$3,$B49,0)) -> 0 | P49: =+IF(P$3>$D$2,0,IF($C49=P$3,$B49,0)) -> 0 | ... AL49: =+IF(AL$3>$D$2,0,IF($C49=AL$3,$B49,0)) -> 0
A50: =+SUM(H50:AL50)-B50 -> 0 | B50: =+DESP_JANEIRO!B49 -> 0 | C50: =+DESP_JANEIRO!C49 -> 0 | D50: =+DESP_JANEIRO!F49 -> 0 | E50: =+SUM(H50:AL50) -> 0 | F50: =+IF(B50=0,"-",E50/B50) -> - | H50: =+IF(H$3>$D$2,0,IF(OR(C50=-1,C50=H$3),$B50,0)) -> 0 | I50: =+IF(I$3>$D$2,0,IF($C50=I$3,$B50,0)) -> 0 | J50: =+IF(J$3>$D$2,0,IF($C50=J$3,$B50,0)) -> 0 | K50: =+IF(K$3>$D$2,0,IF($C50=K$3,$B50,0)) -> 0 | L50: =+IF(L$3>$D$2,0,IF($C50=L$3,$B50,0)) -> 0 | M50: =+IF(M$3>$D$2,0,IF($C50=M$3,$B50,0)) -> 0 | N50: =+IF(N$3>$D$2,0,IF($C50=N$3,$B50,0)) -> 0 | O50: =+IF(O$3>$D$2,0,IF($C50=O$3,$B50,0)) -> 0 | P50: =+IF(P$3>$D$2,0,IF($C50=P$3,$B50,0)) -> 0 | ... AL50: =+IF(AL$3>$D$2,0,IF($C50=AL$3,$B50,0)) -> 0
A51: =+SUM(H51:AL51)-B51 -> 0 | B51: =+DESP_JANEIRO!B50 -> 0 | C51: =+DESP_JANEIRO!C50 -> 0 | D51: =+DESP_JANEIRO!F50 -> 0 | E51: =+SUM(H51:AL51) -> 0 | F51: =+IF(B51=0,"-",E51/B51) -> - | H51: =+IF(H$3>$D$2,0,IF(OR(C51=-1,C51=H$3),$B51,0)) -> 0 | I51: =+IF(I$3>$D$2,0,IF($C51=I$3,$B51,0)) -> 0 | J51: =+IF(J$3>$D$2,0,IF($C51=J$3,$B51,0)) -> 0 | K51: =+IF(K$3>$D$2,0,IF($C51=K$3,$B51,0)) -> 0 | L51: =+IF(L$3>$D$2,0,IF($C51=L$3,$B51,0)) -> 0 | M51: =+IF(M$3>$D$2,0,IF($C51=M$3,$B51,0)) -> 0 | N51: =+IF(N$3>$D$2,0,IF($C51=N$3,$B51,0)) -> 0 | O51: =+IF(O$3>$D$2,0,IF($C51=O$3,$B51,0)) -> 0 | P51: =+IF(P$3>$D$2,0,IF($C51=P$3,$B51,0)) -> 0 | ... AL51: =+IF(AL$3>$D$2,0,IF($C51=AL$3,$B51,0)) -> 0
A52: =+SUM(H52:AL52)-B52 -> 0 | B52: =+DESP_JANEIRO!B51 -> 0 | C52: =+DESP_JANEIRO!C51 -> 0 | D52: =+DESP_JANEIRO!F51 -> 0 | E52: =+SUM(H52:AL52) -> 0 | F52: =+IF(B52=0,"-",E52/B52) -> - | H52: =+IF(H$3>$D$2,0,IF(OR(C52=-1,C52=H$3),$B52,0)) -> 0 | I52: =+IF(I$3>$D$2,0,IF($C52=I$3,$B52,0)) -> 0 | J52: =+IF(J$3>$D$2,0,IF($C52=J$3,$B52,0)) -> 0 | K52: =+IF(K$3>$D$2,0,IF($C52=K$3,$B52,0)) -> 0 | L52: =+IF(L$3>$D$2,0,IF($C52=L$3,$B52,0)) -> 0 | M52: =+IF(M$3>$D$2,0,IF($C52=M$3,$B52,0)) -> 0 | N52: =+IF(N$3>$D$2,0,IF($C52=N$3,$B52,0)) -> 0 | O52: =+IF(O$3>$D$2,0,IF($C52=O$3,$B52,0)) -> 0 | P52: =+IF(P$3>$D$2,0,IF($C52=P$3,$B52,0)) -> 0 | ... AL52: =+IF(AL$3>$D$2,0,IF($C52=AL$3,$B52,0)) -> 0
A53: =+SUM(H53:AL53)-B53 -> 0 | B53: =+DESP_JANEIRO!B52 -> 0 | C53: =+DESP_JANEIRO!C52 -> 0 | D53: =+DESP_JANEIRO!F52 -> 0 | E53: =+SUM(H53:AL53) -> 0 | F53: =+IF(B53=0,"-",E53/B53) -> - | H53: =+IF(H$3>$D$2,0,IF(OR(C53=-1,C53=H$3),$B53,0)) -> 0 | I53: =+IF(I$3>$D$2,0,IF($C53=I$3,$B53,0)) -> 0 | J53: =+IF(J$3>$D$2,0,IF($C53=J$3,$B53,0)) -> 0 | K53: =+IF(K$3>$D$2,0,IF($C53=K$3,$B53,0)) -> 0 | L53: =+IF(L$3>$D$2,0,IF($C53=L$3,$B53,0)) -> 0 | M53: =+IF(M$3>$D$2,0,IF($C53=M$3,$B53,0)) -> 0 | N53: =+IF(N$3>$D$2,0,IF($C53=N$3,$B53,0)) -> 0 | O53: =+IF(O$3>$D$2,0,IF($C53=O$3,$B53,0)) -> 0 | P53: =+IF(P$3>$D$2,0,IF($C53=P$3,$B53,0)) -> 0 | ... AL53: =+IF(AL$3>$D$2,0,IF($C53=AL$3,$B53,0)) -> 0
A54: =+SUM(H54:AL54)-B54 -> 0 | B54: =+DESP_JANEIRO!B53 -> 0 | C54: =+DESP_JANEIRO!C53 -> 0 | D54: =+DESP_JANEIRO!F53 -> 0 | E54: =+SUM(H54:AL54) -> 0 | F54: =+IF(B54=0,"-",E54/B54) -> - | H54: =+IF(H$3>$D$2,0,IF(OR(C54=-1,C54=H$3),$B54,0)) -> 0 | I54: =+IF(I$3>$D$2,0,IF($C54=I$3,$B54,0)) -> 0 | J54: =+IF(J$3>$D$2,0,IF($C54=J$3,$B54,0)) -> 0 | K54: =+IF(K$3>$D$2,0,IF($C54=K$3,$B54,0)) -> 0 | L54: =+IF(L$3>$D$2,0,IF($C54=L$3,$B54,0)) -> 0 | M54: =+IF(M$3>$D$2,0,IF($C54=M$3,$B54,0)) -> 0 | N54: =+IF(N$3>$D$2,0,IF($C54=N$3,$B54,0)) -> 0 | O54: =+IF(O$3>$D$2,0,IF($C54=O$3,$B54,0)) -> 0 | P54: =+IF(P$3>$D$2,0,IF($C54=P$3,$B54,0)) -> 0 | ... AL54: =+IF(AL$3>$D$2,0,IF($C54=AL$3,$B54,0)) -> 0
A55: =+SUM(H55:AL55)-B55 -> 0 | B55: =+DESP_JANEIRO!B54 -> 0 | C55: =+DESP_JANEIRO!C54 -> 0 | D55: =+DESP_JANEIRO!F54 -> 0 | E55: =+SUM(H55:AL55) -> 0 | F55: =+IF(B55=0,"-",E55/B55) -> - | H55: =+IF(H$3>$D$2,0,IF(OR(C55=-1,C55=H$3),$B55,0)) -> 0 | I55: =+IF(I$3>$D$2,0,IF($C55=I$3,$B55,0)) -> 0 | J55: =+IF(J$3>$D$2,0,IF($C55=J$3,$B55,0)) -> 0 | K55: =+IF(K$3>$D$2,0,IF($C55=K$3,$B55,0)) -> 0 | L55: =+IF(L$3>$D$2,0,IF($C55=L$3,$B55,0)) -> 0 | M55: =+IF(M$3>$D$2,0,IF($C55=M$3,$B55,0)) -> 0 | N55: =+IF(N$3>$D$2,0,IF($C55=N$3,$B55,0)) -> 0 | O55: =+IF(O$3>$D$2,0,IF($C55=O$3,$B55,0)) -> 0 | P55: =+IF(P$3>$D$2,0,IF($C55=P$3,$B55,0)) -> 0 | ... AL55: =+IF(AL$3>$D$2,0,IF($C55=AL$3,$B55,0)) -> 0
A56: =+SUM(H56:AL56)-B56 -> 0 | B56: =+DESP_JANEIRO!B55 -> 0 | C56: =+DESP_JANEIRO!C55 -> 0 | D56: =+DESP_JANEIRO!F55 -> 0 | E56: =+SUM(H56:AL56) -> 0 | F56: =+IF(B56=0,"-",E56/B56) -> - | H56: =+IF(H$3>$D$2,0,IF(OR(C56=-1,C56=H$3),$B56,0)) -> 0 | I56: =+IF(I$3>$D$2,0,IF($C56=I$3,$B56,0)) -> 0 | J56: =+IF(J$3>$D$2,0,IF($C56=J$3,$B56,0)) -> 0 | K56: =+IF(K$3>$D$2,0,IF($C56=K$3,$B56,0)) -> 0 | L56: =+IF(L$3>$D$2,0,IF($C56=L$3,$B56,0)) -> 0 | M56: =+IF(M$3>$D$2,0,IF($C56=M$3,$B56,0)) -> 0 | N56: =+IF(N$3>$D$2,0,IF($C56=N$3,$B56,0)) -> 0 | O56: =+IF(O$3>$D$2,0,IF($C56=O$3,$B56,0)) -> 0 | P56: =+IF(P$3>$D$2,0,IF($C56=P$3,$B56,0)) -> 0 | ... AL56: =+IF(AL$3>$D$2,0,IF($C56=AL$3,$B56,0)) -> 0
A57: =+SUM(H57:AL57)-B57 -> 0 | B57: =+DESP_JANEIRO!B56 -> 0 | C57: =+DESP_JANEIRO!C56 -> 0 | D57: =+DESP_JANEIRO!F56 -> 0 | E57: =+SUM(H57:AL57) -> 0 | F57: =+IF(B57=0,"-",E57/B57) -> - | H57: =+IF(H$3>$D$2,0,IF(OR(C57=-1,C57=H$3),$B57,0)) -> 0 | I57: =+IF(I$3>$D$2,0,IF($C57=I$3,$B57,0)) -> 0 | J57: =+IF(J$3>$D$2,0,IF($C57=J$3,$B57,0)) -> 0 | K57: =+IF(K$3>$D$2,0,IF($C57=K$3,$B57,0)) -> 0 | L57: =+IF(L$3>$D$2,0,IF($C57=L$3,$B57,0)) -> 0 | M57: =+IF(M$3>$D$2,0,IF($C57=M$3,$B57,0)) -> 0 | N57: =+IF(N$3>$D$2,0,IF($C57=N$3,$B57,0)) -> 0 | O57: =+IF(O$3>$D$2,0,IF($C57=O$3,$B57,0)) -> 0 | P57: =+IF(P$3>$D$2,0,IF($C57=P$3,$B57,0)) -> 0 | ... AL57: =+IF(AL$3>$D$2,0,IF($C57=AL$3,$B57,0)) -> 0
A58: =+SUM(H58:AL58)-B58 -> 0 | B58: =+DESP_JANEIRO!B57 -> 0 | C58: =+DESP_JANEIRO!C57 -> 0 | D58: =+DESP_JANEIRO!F57 -> 0 | E58: =+SUM(H58:AL58) -> 0 | F58: =+IF(B58=0,"-",E58/B58) -> - | H58: =+IF(H$3>$D$2,0,IF(OR(C58=-1,C58=H$3),$B58,0)) -> 0 | I58: =+IF(I$3>$D$2,0,IF($C58=I$3,$B58,0)) -> 0 | J58: =+IF(J$3>$D$2,0,IF($C58=J$3,$B58,0)) -> 0 | K58: =+IF(K$3>$D$2,0,IF($C58=K$3,$B58,0)) -> 0 | L58: =+IF(L$3>$D$2,0,IF($C58=L$3,$B58,0)) -> 0 | M58: =+IF(M$3>$D$2,0,IF($C58=M$3,$B58,0)) -> 0 | N58: =+IF(N$3>$D$2,0,IF($C58=N$3,$B58,0)) -> 0 | O58: =+IF(O$3>$D$2,0,IF($C58=O$3,$B58,0)) -> 0 | P58: =+IF(P$3>$D$2,0,IF($C58=P$3,$B58,0)) -> 0 | ... AL58: =+IF(AL$3>$D$2,0,IF($C58=AL$3,$B58,0)) -> 0
... A67: =+SUM(H67:AL67)-B67 -> 0 | B67: =+DESP_JANEIRO!B66 -> 0 | C67: =+DESP_JANEIRO!C66 -> 0 | D67: =+DESP_JANEIRO!F66 -> 0 | E67: =+SUM(H67:AL67) -> 0 | F67: =+IF(B67=0,"-",E67/B67) -> - | H67: =+IF(H$3>$D$2,0,IF(OR(C67=-1,C67=H$3),$B67,0)) -> 0 | I67: =+IF(I$3>$D$2,0,IF($C67=I$3,$B67,0)) -> 0 | J67: =+IF(J$3>$D$2,0,IF($C67=J$3,$B67,0)) -> 0 | K67: =+IF(K$3>$D$2,0,IF($C67=K$3,$B67,0)) -> 0 | L67: =+IF(L$3>$D$2,0,IF($C67=L$3,$B67,0)) -> 0 | M67: =+IF(M$3>$D$2,0,IF($C67=M$3,$B67,0)) -> 0 | N67: =+IF(N$3>$D$2,0,IF($C67=N$3,$B67,0)) -> 0 | O67: =+IF(O$3>$D$2,0,IF($C67=O$3,$B67,0)) -> 0 | P67: =+IF(P$3>$D$2,0,IF($C67=P$3,$B67,0)) -> 0 | ... AL67: =+IF(AL$3>$D$2,0,IF($C67=AL$3,$B67,0)) -> 0
A68: Totais | B68: =+SUM(B47:B67) -> 1000 | D68: =+SUM(D47:D67) -> 500 | E68: =+SUM(E47:E67) -> 1000 | F68: =+IF(B68=0,"-",E68/B68) -> 1 | H68: =+SUM(H47:H67) -> 0 | I68: =+SUM(I47:I67) -> 500 | J68: =+SUM(J47:J67) -> 0 | K68: =+SUM(K47:K67) -> 0 | L68: =+SUM(L47:L67) -> 0 | M68: =+SUM(M47:M67) -> 0 | N68: =+SUM(N47:N67) -> 0 | O68: =+SUM(O47:O67) -> 0 | ... AL68: =+SUM(AL47:AL67) -> 0
A70: =+SUM(H70:AL70)-B70 -> 0 | B70: =+DESP_JANEIRO!B69 -> 0 | C70: =+DESP_JANEIRO!C69 -> 0 | D70: =+DESP_JANEIRO!F69 -> 0 | E70: =+SUM(H70:AL70) -> 0 | F70: =+IF(B70=0,"-",E70/B70) -> - | H70: =+IF(H$3>$D$2,0,IF(OR(C70=-1,C70=H$3),$B70,0)) -> 0 | I70: =+IF(I$3>$D$2,0,IF($C70=I$3,$B70,0)) -> 0 | J70: =+IF(J$3>$D$2,0,IF($C70=J$3,$B70,0)) -> 0 | K70: =+IF(K$3>$D$2,0,IF($C70=K$3,$B70,0)) -> 0 | L70: =+IF(L$3>$D$2,0,IF($C70=L$3,$B70,0)) -> 0 | M70: =+IF(M$3>$D$2,0,IF($C70=M$3,$B70,0)) -> 0 | N70: =+IF(N$3>$D$2,0,IF($C70=N$3,$B70,0)) -> 0 | O70: =+IF(O$3>$D$2,0,IF($C70=O$3,$B70,0)) -> 0 | P70: =+IF(P$3>$D$2,0,IF($C70=P$3,$B70,0)) -> 0 | ... AL70: =+IF(AL$3>$D$2,0,IF($C70=AL$3,$B70,0)) -> 0
A71: =+SUM(H71:AL71)-B71 -> 0 | B71: =+DESP_JANEIRO!B70 -> 524.07 | C71: =+DESP_JANEIRO!C70 -> 27 | D71: =+DESP_JANEIRO!F70 -> 0 | E71: =+SUM(H71:AL71) -> 524.07 | F71: =+IF(B71=0,"-",E71/B71) -> 1 | H71: =+IF(H$3>$D$2,0,IF(OR(C71=-1,C71=H$3),$B71,0)) -> 0 | I71: =+IF(I$3>$D$2,0,IF($C71=I$3,$B71,0)) -> 0 | J71: =+IF(J$3>$D$2,0,IF($C71=J$3,$B71,0)) -> 0 | K71: =+IF(K$3>$D$2,0,IF($C71=K$3,$B71,0)) -> 0 | L71: =+IF(L$3>$D$2,0,IF($C71=L$3,$B71,0)) -> 0 | M71: =+IF(M$3>$D$2,0,IF($C71=M$3,$B71,0)) -> 0 | N71: =+IF(N$3>$D$2,0,IF($C71=N$3,$B71,0)) -> 0 | O71: =+IF(O$3>$D$2,0,IF($C71=O$3,$B71,0)) -> 0 | P71: =+IF(P$3>$D$2,0,IF($C71=P$3,$B71,0)) -> 0 | ... AL71: =+IF(AL$3>$D$2,0,IF($C71=AL$3,$B71,0)) -> 0
A72: =+SUM(H72:AL72)-B72 -> 0 | B72: =+DESP_JANEIRO!B71 -> 1504.62 | C72: =+DESP_JANEIRO!C71 -> 10 | D72: =+DESP_JANEIRO!F71 -> 1504.62 | E72: =+SUM(H72:AL72) -> 1504.62 | F72: =+IF(B72=0,"-",E72/B72) -> 1 | H72: =+IF(H$3>$D$2,0,IF(OR(C72=-1,C72=H$3),$B72,0)) -> 0 | I72: =+IF(I$3>$D$2,0,IF($C72=I$3,$B72,0)) -> 0 | J72: =+IF(J$3>$D$2,0,IF($C72=J$3,$B72,0)) -> 0 | K72: =+IF(K$3>$D$2,0,IF($C72=K$3,$B72,0)) -> 0 | L72: =+IF(L$3>$D$2,0,IF($C72=L$3,$B72,0)) -> 0 | M72: =+IF(M$3>$D$2,0,IF($C72=M$3,$B72,0)) -> 0 | N72: =+IF(N$3>$D$2,0,IF($C72=N$3,$B72,0)) -> 0 | O72: =+IF(O$3>$D$2,0,IF($C72=O$3,$B72,0)) -> 0 | P72: =+IF(P$3>$D$2,0,IF($C72=P$3,$B72,0)) -> 0 | ... AL72: =+IF(AL$3>$D$2,0,IF($C72=AL$3,$B72,0)) -> 0
A73: =+SUM(H73:AL73)-B73 -> -6000 | B73: =+DESP_JANEIRO!B72 -> 6000 | C73: =+DESP_JANEIRO!C72 -> 0 | D73: =+DESP_JANEIRO!F72 -> 0 | E73: =+SUM(H73:AL73) -> 0 | F73: =+IF(B73=0,"-",E73/B73) -> 0 | H73: =+IF(H$3>$D$2,0,IF(OR(C73=-1,C73=H$3),$B73,0)) -> 0 | I73: =+IF(I$3>$D$2,0,IF($C73=I$3,$B73,0)) -> 0 | J73: =+IF(J$3>$D$2,0,IF($C73=J$3,$B73,0)) -> 0 | K73: =+IF(K$3>$D$2,0,IF($C73=K$3,$B73,0)) -> 0 | L73: =+IF(L$3>$D$2,0,IF($C73=L$3,$B73,0)) -> 0 | M73: =+IF(M$3>$D$2,0,IF($C73=M$3,$B73,0)) -> 0 | N73: =+IF(N$3>$D$2,0,IF($C73=N$3,$B73,0)) -> 0 | O73: =+IF(O$3>$D$2,0,IF($C73=O$3,$B73,0)) -> 0 | P73: =+IF(P$3>$D$2,0,IF($C73=P$3,$B73,0)) -> 0 | ... AL73: =+IF(AL$3>$D$2,0,IF($C73=AL$3,$B73,0)) -> 0
A74: =+SUM(H74:AL74)-B74 -> -3500 | B74: =+DESP_JANEIRO!B73 -> 3500 | C74: =+DESP_JANEIRO!C73 -> 0 | D74: =+DESP_JANEIRO!F73 -> 0 | E74: =+SUM(H74:AL74) -> 0 | F74: =+IF(B74=0,"-",E74/B74) -> 0 | H74: =+IF(H$3>$D$2,0,IF(OR(C74=-1,C74=H$3),$B74,0)) -> 0 | I74: =+IF(I$3>$D$2,0,IF($C74=I$3,$B74,0)) -> 0 | J74: =+IF(J$3>$D$2,0,IF($C74=J$3,$B74,0)) -> 0 | K74: =+IF(K$3>$D$2,0,IF($C74=K$3,$B74,0)) -> 0 | L74: =+IF(L$3>$D$2,0,IF($C74=L$3,$B74,0)) -> 0 | M74: =+IF(M$3>$D$2,0,IF($C74=M$3,$B74,0)) -> 0 | N74: =+IF(N$3>$D$2,0,IF($C74=N$3,$B74,0)) -> 0 | O74: =+IF(O$3>$D$2,0,IF($C74=O$3,$B74,0)) -> 0 | P74: =+IF(P$3>$D$2,0,IF($C74=P$3,$B74,0)) -> 0 | ... AL74: =+IF(AL$3>$D$2,0,IF($C74=AL$3,$B74,0)) -> 0
A75: =+SUM(H75:AL75)-B75 -> 0 | B75: =+DESP_JANEIRO!B74 -> 2203.91 | C75: =+DESP_JANEIRO!C74 -> -1 | D75: =+DESP_JANEIRO!F74 -> 2203.91 | E75: =+SUM(H75:AL75) -> 2203.91 | F75: =+IF(B75=0,"-",E75/B75) -> 1 | H75: =+IF(H$3>$D$2,0,IF(OR(C75=-1,C75=H$3),$B75,0)) -> 2203.91 | I75: =+IF(I$3>$D$2,0,IF($C75=I$3,$B75,0)) -> 0 | J75: =+IF(J$3>$D$2,0,IF($C75=J$3,$B75,0)) -> 0 | K75: =+IF(K$3>$D$2,0,IF($C75=K$3,$B75,0)) -> 0 | L75: =+IF(L$3>$D$2,0,IF($C75=L$3,$B75,0)) -> 0 | M75: =+IF(M$3>$D$2,0,IF($C75=M$3,$B75,0)) -> 0 | N75: =+IF(N$3>$D$2,0,IF($C75=N$3,$B75,0)) -> 0 | O75: =+IF(O$3>$D$2,0,IF($C75=O$3,$B75,0)) -> 0 | P75: =+IF(P$3>$D$2,0,IF($C75=P$3,$B75,0)) -> 0 | ... AL75: =+IF(AL$3>$D$2,0,IF($C75=AL$3,$B75,0)) -> 0
A76: =+SUM(H76:AL76)-B76 -> -2200 | B76: =+DESP_JANEIRO!B75 -> 2200 | C76: =+DESP_JANEIRO!C75 -> 0 | D76: =+DESP_JANEIRO!F75 -> 0 | E76: =+SUM(H76:AL76) -> 0 | F76: =+IF(B76=0,"-",E76/B76) -> 0 | H76: =+IF(H$3>$D$2,0,IF(OR(C76=-1,C76=H$3),$B76,0)) -> 0 | I76: =+IF(I$3>$D$2,0,IF($C76=I$3,$B76,0)) -> 0 | J76: =+IF(J$3>$D$2,0,IF($C76=J$3,$B76,0)) -> 0 | K76: =+IF(K$3>$D$2,0,IF($C76=K$3,$B76,0)) -> 0 | L76: =+IF(L$3>$D$2,0,IF($C76=L$3,$B76,0)) -> 0 | M76: =+IF(M$3>$D$2,0,IF($C76=M$3,$B76,0)) -> 0 | N76: =+IF(N$3>$D$2,0,IF($C76=N$3,$B76,0)) -> 0 | O76: =+IF(O$3>$D$2,0,IF($C76=O$3,$B76,0)) -> 0 | P76: =+IF(P$3>$D$2,0,IF($C76=P$3,$B76,0)) -> 0 | ... AL76: =+IF(AL$3>$D$2,0,IF($C76=AL$3,$B76,0)) -> 0
A77: =+SUM(H77:AL77)-B77 -> 0 | B77: =+DESP_JANEIRO!B76 -> 220 | C77: =+DESP_JANEIRO!C76 -> 15 | D77: =+DESP_JANEIRO!F76 -> 0 | E77: =+SUM(H77:AL77) -> 220 | F77: =+IF(B77=0,"-",E77/B77) -> 1 | H77: =+IF(H$3>$D$2,0,IF(OR(C77=-1,C77=H$3),$B77,0)) -> 0 | I77: =+IF(I$3>$D$2,0,IF($C77=I$3,$B77,0)) -> 0 | J77: =+IF(J$3>$D$2,0,IF($C77=J$3,$B77,0)) -> 0 | K77: =+IF(K$3>$D$2,0,IF($C77=K$3,$B77,0)) -> 0 | L77: =+IF(L$3>$D$2,0,IF($C77=L$3,$B77,0)) -> 0 | M77: =+IF(M$3>$D$2,0,IF($C77=M$3,$B77,0)) -> 0 | N77: =+IF(N$3>$D$2,0,IF($C77=N$3,$B77,0)) -> 0 | O77: =+IF(O$3>$D$2,0,IF($C77=O$3,$B77,0)) -> 0 | P77: =+IF(P$3>$D$2,0,IF($C77=P$3,$B77,0)) -> 0 | ... AL77: =+IF(AL$3>$D$2,0,IF($C77=AL$3,$B77,0)) -> 0
A78: =+SUM(H78:AL78)-B78 -> 0 | B78: =+DESP_JANEIRO!B77 -> 0 | C78: =+DESP_JANEIRO!C77 -> 0 | D78: =+DESP_JANEIRO!F77 -> 0 | E78: =+SUM(H78:AL78) -> 0 | F78: =+IF(B78=0,"-",E78/B78) -> - | H78: =+IF(H$3>$D$2,0,IF(OR(C78=-1,C78=H$3),$B78,0)) -> 0 | I78: =+IF(I$3>$D$2,0,IF($C78=I$3,$B78,0)) -> 0 | J78: =+IF(J$3>$D$2,0,IF($C78=J$3,$B78,0)) -> 0 | K78: =+IF(K$3>$D$2,0,IF($C78=K$3,$B78,0)) -> 0 | L78: =+IF(L$3>$D$2,0,IF($C78=L$3,$B78,0)) -> 0 | M78: =+IF(M$3>$D$2,0,IF($C78=M$3,$B78,0)) -> 0 | N78: =+IF(N$3>$D$2,0,IF($C78=N$3,$B78,0)) -> 0 | O78: =+IF(O$3>$D$2,0,IF($C78=O$3,$B78,0)) -> 0 | P78: =+IF(P$3>$D$2,0,IF($C78=P$3,$B78,0)) -> 0 | ... AL78: =+IF(AL$3>$D$2,0,IF($C78=AL$3,$B78,0)) -> 0
A79: =+SUM(H79:AL79)-B79 -> 0 | B79: =+DESP_JANEIRO!B78 -> 0 | C79: =+DESP_JANEIRO!C78 -> 0 | D79: =+DESP_JANEIRO!F78 -> 0 | E79: =+SUM(H79:AL79) -> 0 | F79: =+IF(B79=0,"-",E79/B79) -> - | H79: =+IF(H$3>$D$2,0,IF(OR(C79=-1,C79=H$3),$B79,0)) -> 0 | I79: =+IF(I$3>$D$2,0,IF($C79=I$3,$B79,0)) -> 0 | J79: =+IF(J$3>$D$2,0,IF($C79=J$3,$B79,0)) -> 0 | K79: =+IF(K$3>$D$2,0,IF($C79=K$3,$B79,0)) -> 0 | L79: =+IF(L$3>$D$2,0,IF($C79=L$3,$B79,0)) -> 0 | M79: =+IF(M$3>$D$2,0,IF($C79=M$3,$B79,0)) -> 0 | N79: =+IF(N$3>$D$2,0,IF($C79=N$3,$B79,0)) -> 0 | O79: =+IF(O$3>$D$2,0,IF($C79=O$3,$B79,0)) -> 0 | P79: =+IF(P$3>$D$2,0,IF($C79=P$3,$B79,0)) -> 0 | ... AL79: =+IF(AL$3>$D$2,0,IF($C79=AL$3,$B79,0)) -> 0
A80: =+SUM(H80:AL80)-B80 -> 0 | B80: =+DESP_JANEIRO!B79 -> 288.06 | C80: =+DESP_JANEIRO!C79 -> 5 | D80: =+DESP_JANEIRO!F79 -> 288.06 | E80: =+SUM(H80:AL80) -> 288.06 | F80: =+IF(B80=0,"-",E80/B80) -> 1 | H80: =+IF(H$3>$D$2,0,IF(OR(C80=-1,C80=H$3),$B80,0)) -> 0 | I80: =+IF(I$3>$D$2,0,IF($C80=I$3,$B80,0)) -> 0 | J80: =+IF(J$3>$D$2,0,IF($C80=J$3,$B80,0)) -> 0 | K80: =+IF(K$3>$D$2,0,IF($C80=K$3,$B80,0)) -> 0 | L80: =+IF(L$3>$D$2,0,IF($C80=L$3,$B80,0)) -> 288.06 | M80: =+IF(M$3>$D$2,0,IF($C80=M$3,$B80,0)) -> 0 | N80: =+IF(N$3>$D$2,0,IF($C80=N$3,$B80,0)) -> 0 | O80: =+IF(O$3>$D$2,0,IF($C80=O$3,$B80,0)) -> 0 | P80: =+IF(P$3>$D$2,0,IF($C80=P$3,$B80,0)) -> 0 | ... AL80: =+IF(AL$3>$D$2,0,IF($C80=AL$3,$B80,0)) -> 0
A81: =+SUM(H81:AL81)-B81 -> 0 | B81: =+DESP_JANEIRO!B80 -> 236.13 | C81: =+DESP_JANEIRO!C80 -> 26 | D81: =+DESP_JANEIRO!F80 -> 0 | E81: =+SUM(H81:AL81) -> 236.13 | F81: =+IF(B81=0,"-",E81/B81) -> 1 | H81: =+IF(H$3>$D$2,0,IF(OR(C81=-1,C81=H$3),$B81,0)) -> 0 | I81: =+IF(I$3>$D$2,0,IF($C81=I$3,$B81,0)) -> 0 | J81: =+IF(J$3>$D$2,0,IF($C81=J$3,$B81,0)) -> 0 | K81: =+IF(K$3>$D$2,0,IF($C81=K$3,$B81,0)) -> 0 | L81: =+IF(L$3>$D$2,0,IF($C81=L$3,$B81,0)) -> 0 | M81: =+IF(M$3>$D$2,0,IF($C81=M$3,$B81,0)) -> 0 | N81: =+IF(N$3>$D$2,0,IF($C81=N$3,$B81,0)) -> 0 | O81: =+IF(O$3>$D$2,0,IF($C81=O$3,$B81,0)) -> 0 | P81: =+IF(P$3>$D$2,0,IF($C81=P$3,$B81,0)) -> 0 | ... AL81: =+IF(AL$3>$D$2,0,IF($C81=AL$3,$B81,0)) -> 0
... A88: =+SUM(H88:AL88)-B88 -> 0 | B88: =+DESP_JANEIRO!B87 -> 0 | C88: =+DESP_JANEIRO!C87 -> 0 | D88: =+DESP_JANEIRO!F87 -> 0 | E88: =+SUM(H88:AL88) -> 0 | F88: =+IF(B88=0,"-",E88/B88) -> - | H88: =+IF(H$3>$D$2,0,IF(OR(C88=-1,C88=H$3),$B88,0)) -> 0 | I88: =+IF(I$3>$D$2,0,IF($C88=I$3,$B88,0)) -> 0 | J88: =+IF(J$3>$D$2,0,IF($C88=J$3,$B88,0)) -> 0 | K88: =+IF(K$3>$D$2,0,IF($C88=K$3,$B88,0)) -> 0 | L88: =+IF(L$3>$D$2,0,IF($C88=L$3,$B88,0)) -> 0 | M88: =+IF(M$3>$D$2,0,IF($C88=M$3,$B88,0)) -> 0 | N88: =+IF(N$3>$D$2,0,IF($C88=N$3,$B88,0)) -> 0 | O88: =+IF(O$3>$D$2,0,IF($C88=O$3,$B88,0)) -> 0 | P88: =+IF(P$3>$D$2,0,IF($C88=P$3,$B88,0)) -> 0 | ... AL88: =+IF(AL$3>$D$2,0,IF($C88=AL$3,$B88,0)) -> 0
A89: =+SUM(H89:AL89)-B89 -> 0 | B89: =+DESP_JANEIRO!B88 -> 0 | C89: =+DESP_JANEIRO!C83 -> 12 | D89: =+DESP_JANEIRO!F88 -> 0 | E89: =+SUM(H89:AL89) -> 0 | F89: =+IF(B89=0,"-",E89/B89) -> - | H89: =+IF(H$3>$D$2,0,IF(OR(C89=-1,C89=H$3),$B89,0)) -> 0 | I89: =+IF(I$3>$D$2,0,IF($C89=I$3,$B89,0)) -> 0 | J89: =+IF(J$3>$D$2,0,IF($C89=J$3,$B89,0)) -> 0 | K89: =+IF(K$3>$D$2,0,IF($C89=K$3,$B89,0)) -> 0 | L89: =+IF(L$3>$D$2,0,IF($C89=L$3,$B89,0)) -> 0 | M89: =+IF(M$3>$D$2,0,IF($C89=M$3,$B89,0)) -> 0 | N89: =+IF(N$3>$D$2,0,IF($C89=N$3,$B89,0)) -> 0 | O89: =+IF(O$3>$D$2,0,IF($C89=O$3,$B89,0)) -> 0 | P89: =+IF(P$3>$D$2,0,IF($C89=P$3,$B89,0)) -> 0 | ... AL89: =+IF(AL$3>$D$2,0,IF($C89=AL$3,$B89,0)) -> 0
A90: Totais | B90: =+SUM(B70:B89) -> 18460.94 | D90: =+SUM(D70:D89) -> 4920.82 | E90: =+SUM(E70:E89) -> 5901.02 | F90: =+IF(B90=0,"-",E90/B90) -> 0.31964895 | H90: =+SUM(H70:H89) -> 2503.91 | I90: =+SUM(I70:I89) -> 0 | J90: =+SUM(J70:J89) -> 0 | K90: =+SUM(K70:K89) -> 0 | L90: =+SUM(L70:L89) -> 288.06 | M90: =+SUM(M70:M89) -> 464.59 | N90: =+SUM(N70:N89) -> 0 | O90: =+SUM(O70:O89) -> 0 | ... AL90: =+SUM(AL70:AL89) -> 0
A92: =+SUM(H92:AL92)-B92 -> 0 | B92: =+DESP_JANEIRO!B91 -> 0 | C92: =+DESP_JANEIRO!C91 -> 0 | D92: =+DESP_JANEIRO!F91 -> 0 | E92: =+DESP_JANEIRO!D91 -> 0 | F92: =+DESP_JANEIRO!G91 -> - | G92: =+DESP_JANEIRO!H91 -> 0 | H92: =+IF(H$3>$D$2,0,IF(OR(C92=-1,C92=H$3),$B92,0)) -> 0 | I92: =+IF(I$3>$D$2,0,IF($C92=I$3,$B92,0)) -> 0 | J92: =+IF(J$3>$D$2,0,IF($C92=J$3,$B92,0)) -> 0 | K92: =+IF(K$3>$D$2,0,IF($C92=K$3,$B92,0)) -> 0 | L92: =+IF(L$3>$D$2,0,IF($C92=L$3,$B92,0)) -> 0 | M92: =+IF(M$3>$D$2,0,IF($C92=M$3,$B92,0)) -> 0 | N92: =+IF(N$3>$D$2,0,IF($C92=N$3,$B92,0)) -> 0 | O92: =+IF(O$3>$D$2,0,IF($C92=O$3,$B92,0)) -> 0 | P92: =+IF(P$3>$D$2,0,IF($C92=P$3,$B92,0)) -> 0 | ... AL92: =+IF(AL$3>$D$2,0,IF($C92=AL$3,$B92,0)) -> 0
A93: =+SUM(H93:AL93)-B93 -> 0 | B93: =+DESP_JANEIRO!B92 -> 5188 | C93: =+DESP_JANEIRO!C92 -> 5 | D93: =+DESP_JANEIRO!F92 -> 5188 | E93: =+DESP_JANEIRO!D92 -> 0 | F93: =+DESP_JANEIRO!G92 -> 0 | G93: =+DESP_JANEIRO!H92 -> 0 | H93: =+IF(H$3>$D$2,0,IF(OR(C93=-1,C93=H$3),$B93,0)) -> 0 | I93: =+IF(I$3>$D$2,0,IF($C93=I$3,$B93,0)) -> 0 | J93: =+IF(J$3>$D$2,0,IF($C93=J$3,$B93,0)) -> 0 | K93: =+IF(K$3>$D$2,0,IF($C93=K$3,$B93,0)) -> 0 | L93: =+IF(L$3>$D$2,0,IF($C93=L$3,$B93,0)) -> 5188 | M93: =+IF(M$3>$D$2,0,IF($C93=M$3,$B93,0)) -> 0 | N93: =+IF(N$3>$D$2,0,IF($C93=N$3,$B93,0)) -> 0 | O93: =+IF(O$3>$D$2,0,IF($C93=O$3,$B93,0)) -> 0 | P93: =+IF(P$3>$D$2,0,IF($C93=P$3,$B93,0)) -> 0 | ... AL93: =+IF(AL$3>$D$2,0,IF($C93=AL$3,$B93,0)) -> 0
A94: =+SUM(H94:AL94)-B94 -> -1709 | B94: =+DESP_JANEIRO!B93 -> 1709 | C94: =+DESP_JANEIRO!C93 -> 0 | D94: =+DESP_JANEIRO!F93 -> 0 | E94: =+DESP_JANEIRO!D93 -> 0 | F94: =+DESP_JANEIRO!G93 -> 0 | G94: =+DESP_JANEIRO!H93 -> 0 | H94: =+IF(H$3>$D$2,0,IF(OR(C94=-1,C94=H$3),$B94,0)) -> 0 | I94: =+IF(I$3>$D$2,0,IF($C94=I$3,$B94,0)) -> 0 | J94: =+IF(J$3>$D$2,0,IF($C94=J$3,$B94,0)) -> 0 | K94: =+IF(K$3>$D$2,0,IF($C94=K$3,$B94,0)) -> 0 | L94: =+IF(L$3>$D$2,0,IF($C94=L$3,$B94,0)) -> 0 | M94: =+IF(M$3>$D$2,0,IF($C94=M$3,$B94,0)) -> 0 | N94: =+IF(N$3>$D$2,0,IF($C94=N$3,$B94,0)) -> 0 | O94: =+IF(O$3>$D$2,0,IF($C94=O$3,$B94,0)) -> 0 | P94: =+IF(P$3>$D$2,0,IF($C94=P$3,$B94,0)) -> 0 | ... AL94: =+IF(AL$3>$D$2,0,IF($C94=AL$3,$B94,0)) -> 0
A95: =+SUM(H95:AL95)-B95 -> 0 | B95: =+DESP_JANEIRO!B94 -> 3099 | C95: =+DESP_JANEIRO!C94 -> 26 | D95: =+DESP_JANEIRO!F94 -> 0 | E95: =+DESP_JANEIRO!D94 -> 0 | F95: =+DESP_JANEIRO!G94 -> 0 | G95: =+DESP_JANEIRO!H94 -> 0 | H95: =+IF(H$3>$D$2,0,IF(OR(C95=-1,C95=H$3),$B95,0)) -> 0 | I95: =+IF(I$3>$D$2,0,IF($C95=I$3,$B95,0)) -> 0 | J95: =+IF(J$3>$D$2,0,IF($C95=J$3,$B95,0)) -> 0 | K95: =+IF(K$3>$D$2,0,IF($C95=K$3,$B95,0)) -> 0 | L95: =+IF(L$3>$D$2,0,IF($C95=L$3,$B95,0)) -> 0 | M95: =+IF(M$3>$D$2,0,IF($C95=M$3,$B95,0)) -> 0 | N95: =+IF(N$3>$D$2,0,IF($C95=N$3,$B95,0)) -> 0 | O95: =+IF(O$3>$D$2,0,IF($C95=O$3,$B95,0)) -> 0 | P95: =+IF(P$3>$D$2,0,IF($C95=P$3,$B95,0)) -> 0 | ... AL95: =+IF(AL$3>$D$2,0,IF($C95=AL$3,$B95,0)) -> 0
A96: =+SUM(H96:AL96)-B96 -> 0 | B96: =+DESP_JANEIRO!B95 -> 0 | C96: =+DESP_JANEIRO!C95 -> 0 | D96: =+DESP_JANEIRO!F95 -> 0 | E96: =+DESP_JANEIRO!D95 -> 0 | F96: =+DESP_JANEIRO!G95 -> - | G96: =+DESP_JANEIRO!H95 -> 0 | H96: =+IF(H$3>$D$2,0,IF(OR(C96=-1,C96=H$3),$B96,0)) -> 0 | I96: =+IF(I$3>$D$2,0,IF($C96=I$3,$B96,0)) -> 0 | J96: =+IF(J$3>$D$2,0,IF($C96=J$3,$B96,0)) -> 0 | K96: =+IF(K$3>$D$2,0,IF($C96=K$3,$B96,0)) -> 0 | L96: =+IF(L$3>$D$2,0,IF($C96=L$3,$B96,0)) -> 0 | M96: =+IF(M$3>$D$2,0,IF($C96=M$3,$B96,0)) -> 0 | N96: =+IF(N$3>$D$2,0,IF($C96=N$3,$B96,0)) -> 0 | O96: =+IF(O$3>$D$2,0,IF($C96=O$3,$B96,0)) -> 0 | P96: =+IF(P$3>$D$2,0,IF($C96=P$3,$B96,0)) -> 0 | ... AL96: =+IF(AL$3>$D$2,0,IF($C96=AL$3,$B96,0)) -> 0
A97: =+SUM(H97:AL97)-B97 -> 0 | B97: =+DESP_JANEIRO!B96 -> 0 | C97: =+DESP_JANEIRO!C96 -> 0 | D97: =+DESP_JANEIRO!F96 -> 0 | E97: =+DESP_JANEIRO!D96 -> 0 | F97: =+DESP_JANEIRO!G96 -> - | G97: =+DESP_JANEIRO!H96 -> 0 | H97: =+IF(H$3>$D$2,0,IF(OR(C97=-1,C97=H$3),$B97,0)) -> 0 | I97: =+IF(I$3>$D$2,0,IF($C97=I$3,$B97,0)) -> 0 | J97: =+IF(J$3>$D$2,0,IF($C97=J$3,$B97,0)) -> 0 | K97: =+IF(K$3>$D$2,0,IF($C97=K$3,$B97,0)) -> 0 | L97: =+IF(L$3>$D$2,0,IF($C97=L$3,$B97,0)) -> 0 | M97: =+IF(M$3>$D$2,0,IF($C97=M$3,$B97,0)) -> 0 | N97: =+IF(N$3>$D$2,0,IF($C97=N$3,$B97,0)) -> 0 | O97: =+IF(O$3>$D$2,0,IF($C97=O$3,$B97,0)) -> 0 | P97: =+IF(P$3>$D$2,0,IF($C97=P$3,$B97,0)) -> 0 | ... AL97: =+IF(AL$3>$D$2,0,IF($C97=AL$3,$B97,0)) -> 0
A98: =+SUM(H98:AL98)-B98 -> 0 | B98: =+DESP_JANEIRO!B97 -> 0 | C98: =+DESP_JANEIRO!C97 -> 0 | D98: =+DESP_JANEIRO!F97 -> 0 | E98: =+DESP_JANEIRO!D97 -> 0 | F98: =+DESP_JANEIRO!G97 -> - | G98: =+DESP_JANEIRO!H97 -> 0 | H98: =+IF(H$3>$D$2,0,IF(OR(C98=-1,C98=H$3),$B98,0)) -> 0 | I98: =+IF(I$3>$D$2,0,IF($C98=I$3,$B98,0)) -> 0 | J98: =+IF(J$3>$D$2,0,IF($C98=J$3,$B98,0)) -> 0 | K98: =+IF(K$3>$D$2,0,IF($C98=K$3,$B98,0)) -> 0 | L98: =+IF(L$3>$D$2,0,IF($C98=L$3,$B98,0)) -> 0 | M98: =+IF(M$3>$D$2,0,IF($C98=M$3,$B98,0)) -> 0 | N98: =+IF(N$3>$D$2,0,IF($C98=N$3,$B98,0)) -> 0 | O98: =+IF(O$3>$D$2,0,IF($C98=O$3,$B98,0)) -> 0 | P98: =+IF(P$3>$D$2,0,IF($C98=P$3,$B98,0)) -> 0 | ... AL98: =+IF(AL$3>$D$2,0,IF($C98=AL$3,$B98,0)) -> 0
A99: Totais | B99: =+SUM(B92:B98)-B95 -> 6897 | D99: =+SUM(D92:D98) -> 5188 | E99: =+SUM(E92:E98) -> 0 | F99: =+IF(B99=0,"-",E99/B99) -> 0 | H99: =+SUM(H92:H98) -> 0 | I99: =+SUM(I92:I98) -> 0 | J99: =+SUM(J92:J98) -> 0 | K99: =+SUM(K92:K98) -> 0 | L99: =+SUM(L92:L98) -> 5188 | M99: =+SUM(M92:M98) -> 0 | N99: =+SUM(N92:N98) -> 0 | O99: =+SUM(O92:O98) -> 0 | ... AL99: =+SUM(AL92:AL98) -> 0
A101: =+SUM(H101:AL101)-B101 -> 0 | B101: =+DESP_JANEIRO!B100 -> 10606.05 | C101: =+DESP_JANEIRO!C100 -> 8 | D101: =+DESP_JANEIRO!F100 -> 10606.05 | E101: =+DESP_JANEIRO!D100 -> 0 | F101: =+DESP_JANEIRO!G100 -> 0 | G101: =+DESP_JANEIRO!H100 -> 0 | H101: =+IF(H$3>$D$2,0,IF(OR(C101=-1,C101=H$3),$B101,0)) -> 0 | I101: =+IF(I$3>$D$2,0,IF($C101=I$3,$B101,0)) -> 0 | J101: =+IF(J$3>$D$2,0,IF($C101=J$3,$B101,0)) -> 0 | K101: =+IF(K$3>$D$2,0,IF($C101=K$3,$B101,0)) -> 0 | L101: =+IF(L$3>$D$2,0,IF($C101=L$3,$B101,0)) -> 0 | M101: =+IF(M$3>$D$2,0,IF($C101=M$3,$B101,0)) -> 0 | N101: =+IF(N$3>$D$2,0,IF($C101=N$3,$B101,0)) -> 0 | O101: =+IF(O$3>$D$2,0,IF($C101=O$3,$B101,0)) -> 10606.05 | P101: =+IF(P$3>$D$2,0,IF($C101=P$3,$B101,0)) -> 0 | ... AL101: =+IF(AL$3>$D$2,0,IF($C101=AL$3,$B101,0)) -> 0
A102: =+SUM(H102:AL102)-B102 -> 0 | B102: =+DESP_JANEIRO!B101 -> 3030.3 | C102: =+DESP_JANEIRO!C101 -> 11 | D102: =+DESP_JANEIRO!F101 -> 3030.3 | E102: =+DESP_JANEIRO!D101 -> 0 | F102: =+DESP_JANEIRO!G101 -> 0 | G102: =+DESP_JANEIRO!H101 -> 0 | H102: =+IF(H$3>$D$2,0,IF(OR(C102=-1,C102=H$3),$B102,0)) -> 0 | I102: =+IF(I$3>$D$2,0,IF($C102=I$3,$B102,0)) -> 0 | J102: =+IF(J$3>$D$2,0,IF($C102=J$3,$B102,0)) -> 0 | K102: =+IF(K$3>$D$2,0,IF($C102=K$3,$B102,0)) -> 0 | L102: =+IF(L$3>$D$2,0,IF($C102=L$3,$B102,0)) -> 0 | M102: =+IF(M$3>$D$2,0,IF($C102=M$3,$B102,0)) -> 0 | N102: =+IF(N$3>$D$2,0,IF($C102=N$3,$B102,0)) -> 0 | O102: =+IF(O$3>$D$2,0,IF($C102=O$3,$B102,0)) -> 0 | P102: =+IF(P$3>$D$2,0,IF($C102=P$3,$B102,0)) -> 0 | ... AL102: =+IF(AL$3>$D$2,0,IF($C102=AL$3,$B102,0)) -> 0
A103: =+SUM(H103:AL103)-B103 -> 0 | B103: =+DESP_JANEIRO!B102 -> 0 | C103: =+DESP_JANEIRO!C102 -> 0 | D103: =+DESP_JANEIRO!F102 -> 0 | E103: =+DESP_JANEIRO!D102 -> 0 | F103: =+DESP_JANEIRO!G102 -> - | G103: =+DESP_JANEIRO!H102 -> 0 | H103: =+IF(H$3>$D$2,0,IF(OR(C103=-1,C103=H$3),$B103,0)) -> 0 | I103: =+IF(I$3>$D$2,0,IF($C103=I$3,$B103,0)) -> 0 | J103: =+IF(J$3>$D$2,0,IF($C103=J$3,$B103,0)) -> 0 | K103: =+IF(K$3>$D$2,0,IF($C103=K$3,$B103,0)) -> 0 | L103: =+IF(L$3>$D$2,0,IF($C103=L$3,$B103,0)) -> 0 | M103: =+IF(M$3>$D$2,0,IF($C103=M$3,$B103,0)) -> 0 | N103: =+IF(N$3>$D$2,0,IF($C103=N$3,$B103,0)) -> 0 | O103: =+IF(O$3>$D$2,0,IF($C103=O$3,$B103,0)) -> 0 | P103: =+IF(P$3>$D$2,0,IF($C103=P$3,$B103,0)) -> 0 | ... AL103: =+IF(AL$3>$D$2,0,IF($C103=AL$3,$B103,0)) -> 0
A104: =+SUM(H104:AL104)-B104 -> 0 | B104: =+DESP_JANEIRO!B103 -> 0 | C104: =+DESP_JANEIRO!C103 -> 0 | D104: =+DESP_JANEIRO!F103 -> 0 | E104: =+DESP_JANEIRO!D103 -> 0 | F104: =+DESP_JANEIRO!G103 -> - | G104: =+DESP_JANEIRO!H103 -> 0 | H104: =+IF(H$3>$D$2,0,IF(OR(C104=-1,C104=H$3),$B104,0)) -> 0 | I104: =+IF(I$3>$D$2,0,IF($C104=I$3,$B104,0)) -> 0 | J104: =+IF(J$3>$D$2,0,IF($C104=J$3,$B104,0)) -> 0 | K104: =+IF(K$3>$D$2,0,IF($C104=K$3,$B104,0)) -> 0 | L104: =+IF(L$3>$D$2,0,IF($C104=L$3,$B104,0)) -> 0 | M104: =+IF(M$3>$D$2,0,IF($C104=M$3,$B104,0)) -> 0 | N104: =+IF(N$3>$D$2,0,IF($C104=N$3,$B104,0)) -> 0 | O104: =+IF(O$3>$D$2,0,IF($C104=O$3,$B104,0)) -> 0 | P104: =+IF(P$3>$D$2,0,IF($C104=P$3,$B104,0)) -> 0 | ... AL104: =+IF(AL$3>$D$2,0,IF($C104=AL$3,$B104,0)) -> 0
A105: Totais | B105: =+SUM(B101:B104) -> 13636.35 | D105: =+SUM(D101:D104) -> 13636.35 | E105: =+SUM(E101:E104) -> 0 | F105: =+IF(B105=0,"-",E105/B105) -> 0 | H105: =+SUM(H101:H104) -> 0 | I105: =+SUM(I101:I104) -> 0 | J105: =+SUM(J101:J104) -> 0 | K105: =+SUM(K101:K104) -> 0 | L105: =+SUM(L101:L104) -> 0 | M105: =+SUM(M101:M104) -> 0 | N105: =+SUM(N101:N104) -> 0 | O105: =+SUM(O101:O104) -> 10606.05 | ... AL105: =+SUM(AL101:AL104) -> 0
A107: =+SUM(H107:AL107)-B107 -> 0 | B107: =+DESP_JANEIRO!B106 -> 931.52 | C107: =+DESP_JANEIRO!C106 -> 9 | D107: =+DESP_JANEIRO!F106 -> 931.52 | E107: =+DESP_JANEIRO!D106 -> 0 | F107: =+DESP_JANEIRO!G106 -> 0 | G107: =+DESP_JANEIRO!H106 -> 0 | H107: =+IF(H$3>$D$2,0,IF(OR(C107=-1,C107=H$3),$B107,0)) -> 0 | I107: =+IF(I$3>$D$2,0,IF($C107=I$3,$B107,0)) -> 0 | J107: =+IF(J$3>$D$2,0,IF($C107=J$3,$B107,0)) -> 0 | K107: =+IF(K$3>$D$2,0,IF($C107=K$3,$B107,0)) -> 0 | L107: =+IF(L$3>$D$2,0,IF($C107=L$3,$B107,0)) -> 0 | M107: =+IF(M$3>$D$2,0,IF($C107=M$3,$B107,0)) -> 0 | N107: =+IF(N$3>$D$2,0,IF($C107=N$3,$B107,0)) -> 0 | O107: =+IF(O$3>$D$2,0,IF($C107=O$3,$B107,0)) -> 0 | P107: =+IF(P$3>$D$2,0,IF($C107=P$3,$B107,0)) -> 931.52 | ... AL107: =+IF(AL$3>$D$2,0,IF($C107=AL$3,$B107,0)) -> 0
A108: =+SUM(H108:AL108)-B108 -> 0 | B108: =+DESP_JANEIRO!B107 -> 2221.74 | C108: =+DESP_JANEIRO!C107 -> 13 | D108: =+DESP_JANEIRO!F107 -> 0 | E108: =+DESP_JANEIRO!D107 -> 0 | F108: =+DESP_JANEIRO!G107 -> 0 | G108: =+DESP_JANEIRO!H107 -> 0 | H108: =+IF(H$3>$D$2,0,IF(OR(C108=-1,C108=H$3),$B108,0)) -> 0 | I108: =+IF(I$3>$D$2,0,IF($C108=I$3,$B108,0)) -> 0 | J108: =+IF(J$3>$D$2,0,IF($C108=J$3,$B108,0)) -> 0 | K108: =+IF(K$3>$D$2,0,IF($C108=K$3,$B108,0)) -> 0 | L108: =+IF(L$3>$D$2,0,IF($C108=L$3,$B108,0)) -> 0 | M108: =+IF(M$3>$D$2,0,IF($C108=M$3,$B108,0)) -> 0 | N108: =+IF(N$3>$D$2,0,IF($C108=N$3,$B108,0)) -> 0 | O108: =+IF(O$3>$D$2,0,IF($C108=O$3,$B108,0)) -> 0 | P108: =+IF(P$3>$D$2,0,IF($C108=P$3,$B108,0)) -> 0 | ... AL108: =+IF(AL$3>$D$2,0,IF($C108=AL$3,$B108,0)) -> 0
A109: =+SUM(H109:AL109)-B109 -> 0 | B109: =+DESP_JANEIRO!B108 -> 0 | C109: =+DESP_JANEIRO!C108 -> 0 | D109: =+DESP_JANEIRO!F108 -> 0 | E109: =+DESP_JANEIRO!D108 -> 0 | F109: =+DESP_JANEIRO!G108 -> - | G109: =+DESP_JANEIRO!H108 -> 0 | H109: =+IF(H$3>$D$2,0,IF(OR(C109=-1,C109=H$3),$B109,0)) -> 0 | I109: =+IF(I$3>$D$2,0,IF($C109=I$3,$B109,0)) -> 0 | J109: =+IF(J$3>$D$2,0,IF($C109=J$3,$B109,0)) -> 0 | K109: =+IF(K$3>$D$2,0,IF($C109=K$3,$B109,0)) -> 0 | L109: =+IF(L$3>$D$2,0,IF($C109=L$3,$B109,0)) -> 0 | M109: =+IF(M$3>$D$2,0,IF($C109=M$3,$B109,0)) -> 0 | N109: =+IF(N$3>$D$2,0,IF($C109=N$3,$B109,0)) -> 0 | O109: =+IF(O$3>$D$2,0,IF($C109=O$3,$B109,0)) -> 0 | P109: =+IF(P$3>$D$2,0,IF($C109=P$3,$B109,0)) -> 0 | ... AL109: =+IF(AL$3>$D$2,0,IF($C109=AL$3,$B109,0)) -> 0
A110: =+SUM(H110:AL110)-B110 -> 0 | B110: =+DESP_JANEIRO!B109 -> 0 | C110: =+DESP_JANEIRO!C109 -> 0 | D110: =+DESP_JANEIRO!F109 -> 0 | E110: =+DESP_JANEIRO!D109 -> 0 | F110: =+DESP_JANEIRO!G109 -> - | G110: =+DESP_JANEIRO!H109 -> 0 | H110: =+IF(H$3>$D$2,0,IF(OR(C110=-1,C110=H$3),$B110,0)) -> 0 | I110: =+IF(I$3>$D$2,0,IF($C110=I$3,$B110,0)) -> 0 | J110: =+IF(J$3>$D$2,0,IF($C110=J$3,$B110,0)) -> 0 | K110: =+IF(K$3>$D$2,0,IF($C110=K$3,$B110,0)) -> 0 | L110: =+IF(L$3>$D$2,0,IF($C110=L$3,$B110,0)) -> 0 | M110: =+IF(M$3>$D$2,0,IF($C110=M$3,$B110,0)) -> 0 | N110: =+IF(N$3>$D$2,0,IF($C110=N$3,$B110,0)) -> 0 | O110: =+IF(O$3>$D$2,0,IF($C110=O$3,$B110,0)) -> 0 | P110: =+IF(P$3>$D$2,0,IF($C110=P$3,$B110,0)) -> 0 | ... AL110: =+IF(AL$3>$D$2,0,IF($C110=AL$3,$B110,0)) -> 0
A111: =+SUM(H111:AL111)-B111 -> 0 | B111: =+DESP_JANEIRO!B110 -> 0 | C111: =+DESP_JANEIRO!C110 -> 0 | D111: =+DESP_JANEIRO!F110 -> 0 | E111: =+DESP_JANEIRO!D110 -> 0 | F111: =+DESP_JANEIRO!G110 -> - | G111: =+DESP_JANEIRO!H110 -> 0 | H111: =+IF(H$3>$D$2,0,IF(OR(C111=-1,C111=H$3),$B111,0)) -> 0 | I111: =+IF(I$3>$D$2,0,IF($C111=I$3,$B111,0)) -> 0 | J111: =+IF(J$3>$D$2,0,IF($C111=J$3,$B111,0)) -> 0 | K111: =+IF(K$3>$D$2,0,IF($C111=K$3,$B111,0)) -> 0 | L111: =+IF(L$3>$D$2,0,IF($C111=L$3,$B111,0)) -> 0 | M111: =+IF(M$3>$D$2,0,IF($C111=M$3,$B111,0)) -> 0 | N111: =+IF(N$3>$D$2,0,IF($C111=N$3,$B111,0)) -> 0 | O111: =+IF(O$3>$D$2,0,IF($C111=O$3,$B111,0)) -> 0 | P111: =+IF(P$3>$D$2,0,IF($C111=P$3,$B111,0)) -> 0 | ... AL111: =+IF(AL$3>$D$2,0,IF($C111=AL$3,$B111,0)) -> 0
A112: =+SUM(H112:AL112)-B112 -> 0 | B112: =+DESP_JANEIRO!B111 -> 0 | C112: =+DESP_JANEIRO!C111 -> 0 | D112: =+DESP_JANEIRO!F111 -> 0 | E112: =+DESP_JANEIRO!D111 -> 0 | F112: =+DESP_JANEIRO!G111 -> - | G112: =+DESP_JANEIRO!H111 -> 0 | H112: =+IF(H$3>$D$2,0,IF(OR(C112=-1,C112=H$3),$B112,0)) -> 0 | I112: =+IF(I$3>$D$2,0,IF($C112=I$3,$B112,0)) -> 0 | J112: =+IF(J$3>$D$2,0,IF($C112=J$3,$B112,0)) -> 0 | K112: =+IF(K$3>$D$2,0,IF($C112=K$3,$B112,0)) -> 0 | L112: =+IF(L$3>$D$2,0,IF($C112=L$3,$B112,0)) -> 0 | M112: =+IF(M$3>$D$2,0,IF($C112=M$3,$B112,0)) -> 0 | N112: =+IF(N$3>$D$2,0,IF($C112=N$3,$B112,0)) -> 0 | O112: =+IF(O$3>$D$2,0,IF($C112=O$3,$B112,0)) -> 0 | P112: =+IF(P$3>$D$2,0,IF($C112=P$3,$B112,0)) -> 0 | ... AL112: =+IF(AL$3>$D$2,0,IF($C112=AL$3,$B112,0)) -> 0
A113: Totais | B113: =+SUM(B107:B112) -> 3153.26 | D113: =+SUM(D107:D112) -> 931.52 | E113: =+SUM(E107:E112) -> 0 | F113: =+IF(B113=0,"-",E113/B113) -> 0 | H113: =+SUM(H107:H112) -> 0 | I113: =+SUM(I107:I112) -> 0 | J113: =+SUM(J107:J112) -> 0 | K113: =+SUM(K107:K112) -> 0 | L113: =+SUM(L107:L112) -> 0 | M113: =+SUM(M107:M112) -> 0 | N113: =+SUM(N107:N112) -> 0 | O113: =+SUM(O107:O112) -> 0 | ... AL113: =+SUM(AL107:AL112) -> 0
A114: Advogado/Jurídico
A115: =+SUM(H115:AL115)-B115 -> 0 | B115: =+DESP_JANEIRO!B114 -> 1750 | C115: =+DESP_JANEIRO!C114 -> 1 | D115: =+DESP_JANEIRO!F114 -> 1750 | E115: =+DESP_JANEIRO!D114 -> 0 | F115: =+DESP_JANEIRO!G114 -> 0 | G115: =+DESP_JANEIRO!H114 -> 0 | H115: =+IF(H$3>$D$2,0,IF(OR(C115=-1,C115=H$3),$B115,0)) -> 1750 | I115: =+IF(I$3>$D$2,0,IF($C115=I$3,$B115,0)) -> 0 | J115: =+IF(J$3>$D$2,0,IF($C115=J$3,$B115,0)) -> 0 | K115: =+IF(K$3>$D$2,0,IF($C115=K$3,$B115,0)) -> 0 | L115: =+IF(L$3>$D$2,0,IF($C115=L$3,$B115,0)) -> 0 | M115: =+IF(M$3>$D$2,0,IF($C115=M$3,$B115,0)) -> 0 | N115: =+IF(N$3>$D$2,0,IF($C115=N$3,$B115,0)) -> 0 | O115: =+IF(O$3>$D$2,0,IF($C115=O$3,$B115,0)) -> 0 | P115: =+IF(P$3>$D$2,0,IF($C115=P$3,$B115,0)) -> 0 | ... AL115: =+IF(AL$3>$D$2,0,IF($C115=AL$3,$B115,0)) -> 0
A116: =+SUM(H116:AL116)-B116 -> 0 | B116: =+DESP_JANEIRO!B115 -> 2750 | C116: =+DESP_JANEIRO!C115 -> 15 | D116: =+DESP_JANEIRO!F115 -> 0 | E116: =+DESP_JANEIRO!D115 -> 0 | F116: =+DESP_JANEIRO!G115 -> 0 | G116: =+DESP_JANEIRO!H115 -> 0 | H116: =+IF(H$3>$D$2,0,IF(OR(C116=-1,C116=H$3),$B116,0)) -> 0 | I116: =+IF(I$3>$D$2,0,IF($C116=I$3,$B116,0)) -> 0 | J116: =+IF(J$3>$D$2,0,IF($C116=J$3,$B116,0)) -> 0 | K116: =+IF(K$3>$D$2,0,IF($C116=K$3,$B116,0)) -> 0 | L116: =+IF(L$3>$D$2,0,IF($C116=L$3,$B116,0)) -> 0 | M116: =+IF(M$3>$D$2,0,IF($C116=M$3,$B116,0)) -> 0 | N116: =+IF(N$3>$D$2,0,IF($C116=N$3,$B116,0)) -> 0 | O116: =+IF(O$3>$D$2,0,IF($C116=O$3,$B116,0)) -> 0 | P116: =+IF(P$3>$D$2,0,IF($C116=P$3,$B116,0)) -> 0 | ... AL116: =+IF(AL$3>$D$2,0,IF($C116=AL$3,$B116,0)) -> 0
A117: =+SUM(H117:AL117)-B117 -> 0 | B117: =+DESP_JANEIRO!B116 -> 0 | C117: =+DESP_JANEIRO!C116 -> 0 | D117: =+DESP_JANEIRO!F116 -> 0 | E117: =+DESP_JANEIRO!D116 -> 0 | F117: =+DESP_JANEIRO!G116 -> - | G117: =+DESP_JANEIRO!H116 -> 0 | H117: =+IF(H$3>$D$2,0,IF(OR(C117=-1,C117=H$3),$B117,0)) -> 0 | I117: =+IF(I$3>$D$2,0,IF($C117=I$3,$B117,0)) -> 0 | J117: =+IF(J$3>$D$2,0,IF($C117=J$3,$B117,0)) -> 0 | K117: =+IF(K$3>$D$2,0,IF($C117=K$3,$B117,0)) -> 0 | L117: =+IF(L$3>$D$2,0,IF($C117=L$3,$B117,0)) -> 0 | M117: =+IF(M$3>$D$2,0,IF($C117=M$3,$B117,0)) -> 0 | N117: =+IF(N$3>$D$2,0,IF($C117=N$3,$B117,0)) -> 0 | O117: =+IF(O$3>$D$2,0,IF($C117=O$3,$B117,0)) -> 0 | P117: =+IF(P$3>$D$2,0,IF($C117=P$3,$B117,0)) -> 0 | ... AL117: =+IF(AL$3>$D$2,0,IF($C117=AL$3,$B117,0)) -> 0
A118: =+SUM(H118:AL118)-B118 -> 0 | B118: =+DESP_JANEIRO!B117 -> 0 | C118: =+DESP_JANEIRO!C117 -> 0 | D118: =+DESP_JANEIRO!F117 -> 0 | E118: =+DESP_JANEIRO!D117 -> 0 | F118: =+DESP_JANEIRO!G117 -> - | G118: =+DESP_JANEIRO!H117 -> 0 | H118: =+IF(H$3>$D$2,0,IF(OR(C118=-1,C118=H$3),$B118,0)) -> 0 | I118: =+IF(I$3>$D$2,0,IF($C118=I$3,$B118,0)) -> 0 | J118: =+IF(J$3>$D$2,0,IF($C118=J$3,$B118,0)) -> 0 | K118: =+IF(K$3>$D$2,0,IF($C118=K$3,$B118,0)) -> 0 | L118: =+IF(L$3>$D$2,0,IF($C118=L$3,$B118,0)) -> 0 | M118: =+IF(M$3>$D$2,0,IF($C118=M$3,$B118,0)) -> 0 | N118: =+IF(N$3>$D$2,0,IF($C118=N$3,$B118,0)) -> 0 | O118: =+IF(O$3>$D$2,0,IF($C118=O$3,$B118,0)) -> 0 | P118: =+IF(P$3>$D$2,0,IF($C118=P$3,$B118,0)) -> 0 | ... AL118: =+IF(AL$3>$D$2,0,IF($C118=AL$3,$B118,0)) -> 0
A119: =+SUM(H119:AL119)-B119 -> 0 | B119: =+DESP_JANEIRO!B118 -> 0 | C119: =+DESP_JANEIRO!C118 -> 0 | D119: =+DESP_JANEIRO!F118 -> 0 | E119: =+DESP_JANEIRO!D118 -> 0 | F119: =+DESP_JANEIRO!G118 -> - | G119: =+DESP_JANEIRO!H118 -> 0 | H119: =+IF(H$3>$D$2,0,IF(OR(C119=-1,C119=H$3),$B119,0)) -> 0 | I119: =+IF(I$3>$D$2,0,IF($C119=I$3,$B119,0)) -> 0 | J119: =+IF(J$3>$D$2,0,IF($C119=J$3,$B119,0)) -> 0 | K119: =+IF(K$3>$D$2,0,IF($C119=K$3,$B119,0)) -> 0 | L119: =+IF(L$3>$D$2,0,IF($C119=L$3,$B119,0)) -> 0 | M119: =+IF(M$3>$D$2,0,IF($C119=M$3,$B119,0)) -> 0 | N119: =+IF(N$3>$D$2,0,IF($C119=N$3,$B119,0)) -> 0 | O119: =+IF(O$3>$D$2,0,IF($C119=O$3,$B119,0)) -> 0 | P119: =+IF(P$3>$D$2,0,IF($C119=P$3,$B119,0)) -> 0 | ... AL119: =+IF(AL$3>$D$2,0,IF($C119=AL$3,$B119,0)) -> 0
A120: =+SUM(H120:AL120)-B120 -> 0 | B120: =+DESP_JANEIRO!B119 -> 0 | C120: =+DESP_JANEIRO!C119 -> 0 | D120: =+DESP_JANEIRO!F119 -> 0 | E120: =+DESP_JANEIRO!D119 -> 0 | F120: =+DESP_JANEIRO!G119 -> - | G120: =+DESP_JANEIRO!H119 -> 0 | H120: =+IF(H$3>$D$2,0,IF(OR(C120=-1,C120=H$3),$B120,0)) -> 0 | I120: =+IF(I$3>$D$2,0,IF($C120=I$3,$B120,0)) -> 0 | J120: =+IF(J$3>$D$2,0,IF($C120=J$3,$B120,0)) -> 0 | K120: =+IF(K$3>$D$2,0,IF($C120=K$3,$B120,0)) -> 0 | L120: =+IF(L$3>$D$2,0,IF($C120=L$3,$B120,0)) -> 0 | M120: =+IF(M$3>$D$2,0,IF($C120=M$3,$B120,0)) -> 0 | N120: =+IF(N$3>$D$2,0,IF($C120=N$3,$B120,0)) -> 0 | O120: =+IF(O$3>$D$2,0,IF($C120=O$3,$B120,0)) -> 0 | P120: =+IF(P$3>$D$2,0,IF($C120=P$3,$B120,0)) -> 0 | ... AL120: =+IF(AL$3>$D$2,0,IF($C120=AL$3,$B120,0)) -> 0
A121: =+SUM(H121:AL121)-B121 -> 0 | B121: =+DESP_JANEIRO!B120 -> 0 | C121: =+DESP_JANEIRO!C120 -> 0 | D121: =+DESP_JANEIRO!F120 -> 0 | E121: =+DESP_JANEIRO!D120 -> 0 | F121: =+DESP_JANEIRO!G120 -> - | G121: =+DESP_JANEIRO!H120 -> 0 | H121: =+IF(H$3>$D$2,0,IF(OR(C121=-1,C121=H$3),$B121,0)) -> 0 | I121: =+IF(I$3>$D$2,0,IF($C121=I$3,$B121,0)) -> 0 | J121: =+IF(J$3>$D$2,0,IF($C121=J$3,$B121,0)) -> 0 | K121: =+IF(K$3>$D$2,0,IF($C121=K$3,$B121,0)) -> 0 | L121: =+IF(L$3>$D$2,0,IF($C121=L$3,$B121,0)) -> 0 | M121: =+IF(M$3>$D$2,0,IF($C121=M$3,$B121,0)) -> 0 | N121: =+IF(N$3>$D$2,0,IF($C121=N$3,$B121,0)) -> 0 | O121: =+IF(O$3>$D$2,0,IF($C121=O$3,$B121,0)) -> 0 | P121: =+IF(P$3>$D$2,0,IF($C121=P$3,$B121,0)) -> 0 | ... AL121: =+IF(AL$3>$D$2,0,IF($C121=AL$3,$B121,0)) -> 0
A122: =+SUM(H122:AL122)-B122 -> 0 | B122: =+DESP_JANEIRO!B121 -> 0 | C122: =+DESP_JANEIRO!C121 -> 0 | D122: =+DESP_JANEIRO!F121 -> 0 | E122: =+DESP_JANEIRO!D121 -> 0 | F122: =+DESP_JANEIRO!G121 -> - | G122: =+DESP_JANEIRO!H121 -> 0 | H122: =+IF(H$3>$D$2,0,IF(OR(C122=-1,C122=H$3),$B122,0)) -> 0 | I122: =+IF(I$3>$D$2,0,IF($C122=I$3,$B122,0)) -> 0 | J122: =+IF(J$3>$D$2,0,IF($C122=J$3,$B122,0)) -> 0 | K122: =+IF(K$3>$D$2,0,IF($C122=K$3,$B122,0)) -> 0 | L122: =+IF(L$3>$D$2,0,IF($C122=L$3,$B122,0)) -> 0 | M122: =+IF(M$3>$D$2,0,IF($C122=M$3,$B122,0)) -> 0 | N122: =+IF(N$3>$D$2,0,IF($C122=N$3,$B122,0)) -> 0 | O122: =+IF(O$3>$D$2,0,IF($C122=O$3,$B122,0)) -> 0 | P122: =+IF(P$3>$D$2,0,IF($C122=P$3,$B122,0)) -> 0 | ... AL122: =+IF(AL$3>$D$2,0,IF($C122=AL$3,$B122,0)) -> 0
A123: Totais | B123: =+SUM(B115:B122) -> 4500 | D123: =+SUM(D115:D122) -> 1750 | E123: =+SUM(E115:E122) -> 0 | F123: =+IF(B123=0,"-",E123/B123) -> 0 | H123: =+SUM(H115:H122) -> 1750 | I123: =+SUM(I115:I122) -> 0 | J123: =+SUM(J115:J122) -> 0 | K123: =+SUM(K115:K122) -> 0 | L123: =+SUM(L115:L122) -> 0 | M123: =+SUM(M115:M122) -> 0 | N123: =+SUM(N115:N122) -> 0 | O123: =+SUM(O115:O122) -> 0 | ... AL123: =+SUM(AL115:AL122) -> 0
A125: =+SUM(H125:AL125)-B125 -> 0 | B125: =+DESP_JANEIRO!B124 -> 6900 | C125: =+DESP_JANEIRO!C124 -> 5 | D125: =+DESP_JANEIRO!F124 -> 6900 | E125: =+DESP_JANEIRO!D124 -> 0 | F125: =+DESP_JANEIRO!G124 -> 0 | G125: =+DESP_JANEIRO!H124 -> 0 | H125: =+IF(H$3>$D$2,0,IF(OR(C125=-1,C125=H$3),$B125,0)) -> 0 | I125: =+IF(I$3>$D$2,0,IF($C125=I$3,$B125,0)) -> 0 | J125: =+IF(J$3>$D$2,0,IF($C125=J$3,$B125,0)) -> 0 | K125: =+IF(K$3>$D$2,0,IF($C125=K$3,$B125,0)) -> 0 | L125: =+IF(L$3>$D$2,0,IF($C125=L$3,$B125,0)) -> 6900 | M125: =+IF(M$3>$D$2,0,IF($C125=M$3,$B125,0)) -> 0 | N125: =+IF(N$3>$D$2,0,IF($C125=N$3,$B125,0)) -> 0 | O125: =+IF(O$3>$D$2,0,IF($C125=O$3,$B125,0)) -> 0 | P125: =+IF(P$3>$D$2,0,IF($C125=P$3,$B125,0)) -> 0 | ... AL125: =+IF(AL$3>$D$2,0,IF($C125=AL$3,$B125,0)) -> 0
A126: =+SUM(H126:AL126)-B126 -> 0 | B126: =+DESP_JANEIRO!B125 -> 6900 | C126: =+DESP_JANEIRO!C125 -> 12 | D126: =+DESP_JANEIRO!F125 -> 6900 | E126: =+DESP_JANEIRO!D125 -> 0 | F126: =+DESP_JANEIRO!G125 -> 0 | G126: =+DESP_JANEIRO!H125 -> 0 | H126: =+IF(H$3>$D$2,0,IF(OR(C126=-1,C126=H$3),$B126,0)) -> 0 | I126: =+IF(I$3>$D$2,0,IF($C126=I$3,$B126,0)) -> 0 | J126: =+IF(J$3>$D$2,0,IF($C126=J$3,$B126,0)) -> 0 | K126: =+IF(K$3>$D$2,0,IF($C126=K$3,$B126,0)) -> 0 | L126: =+IF(L$3>$D$2,0,IF($C126=L$3,$B126,0)) -> 0 | M126: =+IF(M$3>$D$2,0,IF($C126=M$3,$B126,0)) -> 0 | N126: =+IF(N$3>$D$2,0,IF($C126=N$3,$B126,0)) -> 0 | O126: =+IF(O$3>$D$2,0,IF($C126=O$3,$B126,0)) -> 0 | P126: =+IF(P$3>$D$2,0,IF($C126=P$3,$B126,0)) -> 0 | ... AL126: =+IF(AL$3>$D$2,0,IF($C126=AL$3,$B126,0)) -> 0
A127: =+SUM(H127:AL127)-B127 -> 0 | B127: =+DESP_JANEIRO!B126 -> 6900 | C127: =+DESP_JANEIRO!C126 -> 19 | D127: =+DESP_JANEIRO!F126 -> 0 | E127: =+DESP_JANEIRO!D126 -> 0 | F127: =+DESP_JANEIRO!G126 -> 0 | G127: =+DESP_JANEIRO!H126 -> 0 | H127: =+IF(H$3>$D$2,0,IF(OR(C127=-1,C127=H$3),$B127,0)) -> 0 | I127: =+IF(I$3>$D$2,0,IF($C127=I$3,$B127,0)) -> 0 | J127: =+IF(J$3>$D$2,0,IF($C127=J$3,$B127,0)) -> 0 | K127: =+IF(K$3>$D$2,0,IF($C127=K$3,$B127,0)) -> 0 | L127: =+IF(L$3>$D$2,0,IF($C127=L$3,$B127,0)) -> 0 | M127: =+IF(M$3>$D$2,0,IF($C127=M$3,$B127,0)) -> 0 | N127: =+IF(N$3>$D$2,0,IF($C127=N$3,$B127,0)) -> 0 | O127: =+IF(O$3>$D$2,0,IF($C127=O$3,$B127,0)) -> 0 | P127: =+IF(P$3>$D$2,0,IF($C127=P$3,$B127,0)) -> 0 | ... AL127: =+IF(AL$3>$D$2,0,IF($C127=AL$3,$B127,0)) -> 0
A128: =+SUM(H128:AL128)-B128 -> 0 | B128: =+DESP_JANEIRO!B127 -> 6900 | C128: =+DESP_JANEIRO!C127 -> 26 | D128: =+DESP_JANEIRO!F127 -> 0 | E128: =+DESP_JANEIRO!D127 -> 0 | F128: =+DESP_JANEIRO!G127 -> 0 | G128: =+DESP_JANEIRO!H127 -> 0 | H128: =+IF(H$3>$D$2,0,IF(OR(C128=-1,C128=H$3),$B128,0)) -> 0 | I128: =+IF(I$3>$D$2,0,IF($C128=I$3,$B128,0)) -> 0 | J128: =+IF(J$3>$D$2,0,IF($C128=J$3,$B128,0)) -> 0 | K128: =+IF(K$3>$D$2,0,IF($C128=K$3,$B128,0)) -> 0 | L128: =+IF(L$3>$D$2,0,IF($C128=L$3,$B128,0)) -> 0 | M128: =+IF(M$3>$D$2,0,IF($C128=M$3,$B128,0)) -> 0 | N128: =+IF(N$3>$D$2,0,IF($C128=N$3,$B128,0)) -> 0 | O128: =+IF(O$3>$D$2,0,IF($C128=O$3,$B128,0)) -> 0 | P128: =+IF(P$3>$D$2,0,IF($C128=P$3,$B128,0)) -> 0 | ... AL128: =+IF(AL$3>$D$2,0,IF($C128=AL$3,$B128,0)) -> 0
A129: =+SUM(H129:AL129)-B129 -> 0 | B129: =+DESP_JANEIRO!B128 -> 0 | C129: =+DESP_JANEIRO!C128 -> 0 | D129: =+DESP_JANEIRO!F128 -> 0 | E129: =+DESP_JANEIRO!D128 -> 0 | F129: =+DESP_JANEIRO!G128 -> - | G129: =+DESP_JANEIRO!H128 -> 0 | H129: =+IF(H$3>$D$2,0,IF(OR(C129=-1,C129=H$3),$B129,0)) -> 0 | I129: =+IF(I$3>$D$2,0,IF($C129=I$3,$B129,0)) -> 0 | J129: =+IF(J$3>$D$2,0,IF($C129=J$3,$B129,0)) -> 0 | K129: =+IF(K$3>$D$2,0,IF($C129=K$3,$B129,0)) -> 0 | L129: =+IF(L$3>$D$2,0,IF($C129=L$3,$B129,0)) -> 0 | M129: =+IF(M$3>$D$2,0,IF($C129=M$3,$B129,0)) -> 0 | N129: =+IF(N$3>$D$2,0,IF($C129=N$3,$B129,0)) -> 0 | O129: =+IF(O$3>$D$2,0,IF($C129=O$3,$B129,0)) -> 0 | P129: =+IF(P$3>$D$2,0,IF($C129=P$3,$B129,0)) -> 0 | ... AL129: =+IF(AL$3>$D$2,0,IF($C129=AL$3,$B129,0)) -> 0
A130: =+SUM(H130:AL130)-B130 -> 0 | B130: =+DESP_JANEIRO!B129 -> 0 | C130: =+DESP_JANEIRO!C129 -> 0 | D130: =+DESP_JANEIRO!F129 -> 0 | E130: =+DESP_JANEIRO!D129 -> 0 | F130: =+DESP_JANEIRO!G129 -> - | G130: =+DESP_JANEIRO!H129 -> 0 | H130: =+IF(H$3>$D$2,0,IF(OR(C130=-1,C130=H$3),$B130,0)) -> 0 | I130: =+IF(I$3>$D$2,0,IF($C130=I$3,$B130,0)) -> 0 | J130: =+IF(J$3>$D$2,0,IF($C130=J$3,$B130,0)) -> 0 | K130: =+IF(K$3>$D$2,0,IF($C130=K$3,$B130,0)) -> 0 | L130: =+IF(L$3>$D$2,0,IF($C130=L$3,$B130,0)) -> 0 | M130: =+IF(M$3>$D$2,0,IF($C130=M$3,$B130,0)) -> 0 | N130: =+IF(N$3>$D$2,0,IF($C130=N$3,$B130,0)) -> 0 | O130: =+IF(O$3>$D$2,0,IF($C130=O$3,$B130,0)) -> 0 | P130: =+IF(P$3>$D$2,0,IF($C130=P$3,$B130,0)) -> 0 | ... AL130: =+IF(AL$3>$D$2,0,IF($C130=AL$3,$B130,0)) -> 0
A131: =+SUM(H131:AL131)-B131 -> 0 | B131: =+DESP_JANEIRO!B130 -> 1081 | C131: =+DESP_JANEIRO!C130 -> 10 | D131: =+DESP_JANEIRO!F130 -> 1081 | E131: =+DESP_JANEIRO!D130 -> 0 | F131: =+DESP_JANEIRO!G130 -> 0 | G131: =+DESP_JANEIRO!H130 -> 0 | H131: =+IF(H$3>$D$2,0,IF(OR(C131=-1,C131=H$3),$B131,0)) -> 0 | I131: =+IF(I$3>$D$2,0,IF($C131=I$3,$B131,0)) -> 0 | J131: =+IF(J$3>$D$2,0,IF($C131=J$3,$B131,0)) -> 0 | K131: =+IF(K$3>$D$2,0,IF($C131=K$3,$B131,0)) -> 0 | L131: =+IF(L$3>$D$2,0,IF($C131=L$3,$B131,0)) -> 0 | M131: =+IF(M$3>$D$2,0,IF($C131=M$3,$B131,0)) -> 0 | N131: =+IF(N$3>$D$2,0,IF($C131=N$3,$B131,0)) -> 0 | O131: =+IF(O$3>$D$2,0,IF($C131=O$3,$B131,0)) -> 0 | P131: =+IF(P$3>$D$2,0,IF($C131=P$3,$B131,0)) -> 0 | ... AL131: =+IF(AL$3>$D$2,0,IF($C131=AL$3,$B131,0)) -> 0
A132: Totais | B132: =+SUM(B125:B131) -> 28681 | D132: =+SUM(D125:D131) -> 14881 | E132: =+SUM(E125:E131) -> 0 | F132: =+IF(B132=0,"-",E132/B132) -> 0 | H132: =+SUM(H125:H131) -> 0 | I132: =+SUM(I125:I131) -> 0 | J132: =+SUM(J125:J131) -> 0 | K132: =+SUM(K125:K131) -> 0 | L132: =+SUM(L125:L131) -> 6900 | M132: =+SUM(M125:M131) -> 0 | N132: =+SUM(N125:N131) -> 0 | O132: =+SUM(O125:O131) -> 0 | ... AL132: =+SUM(AL125:AL131) -> 0
A134: =+SUM(H134:AL134)-B134 -> 0 | B134: =+DESP_JANEIRO!B133 -> 3237.6 | C134: =+DESP_JANEIRO!C133 -> 30 | D134: =+DESP_JANEIRO!F133 -> 0 | E134: =+DESP_JANEIRO!D133 -> 0 | F134: =+DESP_JANEIRO!G133 -> 0 | G134: =+DESP_JANEIRO!H133 -> 0 | H134: =+IF(H$3>$D$2,0,IF(OR(C134=-1,C134=H$3),$B134,0)) -> 0 | I134: =+IF(I$3>$D$2,0,IF($C134=I$3,$B134,0)) -> 0 | J134: =+IF(J$3>$D$2,0,IF($C134=J$3,$B134,0)) -> 0 | K134: =+IF(K$3>$D$2,0,IF($C134=K$3,$B134,0)) -> 0 | L134: =+IF(L$3>$D$2,0,IF($C134=L$3,$B134,0)) -> 0 | M134: =+IF(M$3>$D$2,0,IF($C134=M$3,$B134,0)) -> 0 | N134: =+IF(N$3>$D$2,0,IF($C134=N$3,$B134,0)) -> 0 | O134: =+IF(O$3>$D$2,0,IF($C134=O$3,$B134,0)) -> 0 | P134: =+IF(P$3>$D$2,0,IF($C134=P$3,$B134,0)) -> 0 | ... AL134: =+IF(AL$3>$D$2,0,IF($C134=AL$3,$B134,0)) -> 0
...

Sheet TUTORIAL
A1: TUTORIAL
A3: 1. A planilha oculta PLAN2 não deve ser alterada, é apenas suporte de cálculos da planilha DESP_XXX(MÊS) -- exceto se adicionadas ou subtraídas linhas de DESP__XXX(MÊS). Vide (18) e (19)
A4: 2. Somente as células com fundo azul podem ser preenchidas.
A5: 3. Insira o mês e ano. A planilha calcula o total de "DIAS MÊS" e apresenta o dia de "HOJE".
A6: 4. Com mês e ano inseridos, a planilha automaticamente indica os dias da semana e colore de rosa os fins de semana na grade de dias do mês, à direita.
A7: 5. Insira a descrição desejada da categoria de gastos na célula azul escuro, neste exemplo "GRUPO 1", "GRUPO 2", "GRUPO 3", etc.
A8: 6. Insira a descrição da despesa, o valor do mês a ser pago na coluna "'A PAGAR", seu vencimento em "DIA" e, após o pagamento, o valor pago em "PAGO"e respectiva data em "DIA".
A9: 7. A planilha alerta na grade de dias, nas datas de vencimento, que o pagamento deve ser feito -- "PAGAR XXXX".
A10: PREENCHER APENAS CÉLULAS COM FUNDO AZUL | D10: JUNHO | E10: 2024 | F10: DIAS MÊS >>> | G10: 30 | I10: 7 | J10: 1 | K10: 2 | L10: 3
A11: DESCRIÇÃO | B11: DESPESAS | D11: PAGAMENTOS | F11: HOJE >>>>>>> | G11: 15 | I11: 1 | J11: 2 | K11: 3 | L11: 4
F12: e acumulado
A13: PESSOAL | B13: A PAGAR | C13: DIA | D13: PAGO | E13: DIA | F13: ATRASO | G13: P/AP
A14: Seguro Médico | B14: 500 | C14: 3 | D14: 400 | E14: 4 | F14: 100 | G14: 0.8 | I14: 0 | J14: 0 | K14: PAGAR 500,00 | L14: 400
A15: Seguro carro | B15: 200 | C15: 4 | F15: 200 | G15: 0 | I15: 0 | J15: 0 | K15: 0 | L15: PAGAR 200,00
F16: 0 | G16: - | I16: 0 | J16: 0 | K16: 0 | L16: 0
A17: 8. No dia 4, quando o pagamento é realizado e inserido na coluna "PAGO", o valor é automaticamente inserido na grade de dias do mês, no dia e linha correspondentes.
A18: 9. Como o pagamento de R$ 400,00 foi a menor, o valor R$ 100,00 aparece na coluna "ATRASO".
A19: 10. Com isso a porcentagem na coluna P/AP (PAGO/A PAGAR) fica em 80% e a célula fica rosada para alertar atraso / pagamento a menor / erro de inserção.
A20: 11. O aviso "PAGAR 500" no dia de vencimento permanece, mesmo com o pagamento de R$ 400,00 no dia 4, evidenciando o pagamento adiantado ou atrasado na grade de dias.
A21: 12. Em caso de pagamento na data de vencimento, o aviso de "PAGAR 500" é sobreposto pelo do valor do pagamento (R$ 400,00).
F22: 0 | G22: - | I22: 0 | J22: 0 | K22: 0 | L22: 0
F23: 0 | G23: - | I23: 0 | J23: 0 | K23: 0 | L23: 0
F24: 0 | G24: - | I24: 0 | J24: 0 | K24: 0 | L24: 0
F25: 0 | G25: - | I25: 0 | J25: 0 | K25: 0 | L25: 0
A26: Totais (Plan2) | B26: 700 | D26: 400 | F26: 300 | G26: 0.57142857 | I26: 0 | J26: 0 | K26: 500 | L26: 200
A27: 13. Para fins dos gráficos de previsão de despesas, o valor de R$ 500,00 é somado na na linha "Totais (Plan2)" na data de vencimento. A soma das despesas nos totais diários
A28: tem por base as datas de vencimento e não as datas dos pagamentos, mantendo fixa a visualização das obrigações (ou recebíveis) nas datas planejadas.
A30: RECEBÍVEIS | B30: A RECEBER | C30: D+1? S/N | D30: A RECEBER/DIA | E30: 0.5 | F30: <<< SÁB..DOM >>> | G30: 0
A31: TOTAL MENSAL >>>>>>>>>>>>>>>>>>>>>> | B31: 45000 | C31: N | D31: 2000 | E31: <<<<<<< | F31: MÉDIA RECEBÍVEIS SEG-SEX | I31: 1000 | J31: 0 | K31: 2000 | L31: 2000
F32: 0 | I32: 0 | J32: 0 | K32: 0 | L32: 0
F33: 0 | I33: 0 | J33: 0 | K33: 0 | L33: 0
A34: 14. A antepenúltima linha "Rendas efetivas em conta"se refere a recebíveis variados diários, como vendas, e uma média diária pode ser usada (ex.: R$2.000,00 por dia na coluna "A RECEBER/DIA").
A35: 15. Os recebíveis variados diários mencionados no item (14) estão assumidos nos sábados como sendo metade dos valores de segunda a sexta e como sendo zero nos domingos.
A36: 16. Caso os valores efetivamente pagos sejam inseridos, nos casos de pagamentos com atraso, os acréscimos de juros e multa aparecerão na última coluna.
A37: 17. PASSOS INICIAIS: (16A) Alterar as categorias de custos conforme mais adequado para cada usuário;
A38: (16B) Salvar uma cópia do arquivo sem dados de despesas, como backup;
A39: 18. MÊS SEGUINTE: (17A) Uma vez findo o mês, salvar adicionalmente a planilha do mês presente (DESP_JUNHO) como a do mês seguinte (DESP_JULHO);
A40: (17B) Alterar o mês nessa nova planilha e adicionar ou retirar dados / despesas / datas conforme necessário, mantendo as despesas recorrentes;
A41: (17C) Repetir o item (17) a cada fim de mês.
A42: 18. Para adição de linhas internas às categorias, a mesma linha deve ser copiada igualmente nas duas planilhas "DESP_XXX(MÊS)" e "PLAN2".
A43: 19. Em caso de subtração de linhas, as mesmas linhas devem ser subtraídas igualmente nas duas planilhas "DESP_MODELO" e "PLAN2" (senha para desbloqueio das planilhas: 123456).
A44: PRESTAÇÕES
A45: Compra do carro | B45: 500 | C45: 18 | F45: 0 | G45: 0 | I45: 0 | J45: 0 | K45: 0 | L45: 0
A46: Compra do carro (maio - atraso) | B46: 500 | C46: 1 | F46: 500 | G46: 0 | I46: PAGAR 500,00 | J46: 0 | K46: 0 | L46: 0
F47: 0 | G47: - | I47: 0 | J47: 0 | K47: 0 | L47: 0
A48: 20. Em caso de pagamentos em atraso de meses anteriores, adicionar linha com a mesma descrição, com texto (atraso - mês xxxx) e data como dia 1 do mês. Dessa forma o valor aparecerá
A49: como atraso já no dia 1 do mês, alertando o atraso desde o início do mês e adicionando essa despesa na carga do mês presente. Dia "0" é descrição/valor futuro apenas para conhecimento.
B50: O RESUMO MENSAL
B51: O acompanhamento dos pagamentos do mês pode ser feito por partes, semanalmente, para categorias específicas de despesas, não sendo
B52: possível visualizar todas as categorias ou todos os dias do mês simultaneamente, devido ao extenso número de linhas e todas as 31
B53: colunas dos dias do mês. Para uma visão geral resumida dos pagamentos do mês, a planilha resume todos os pagamentos de cada dia
B54: nas células AP2 a AU58, dia a dia.
B56: ADICIONANDO OU RETIRANDO LINHAS DA PLANILHA
B57: 1. Apenas as células com fundo azul podem ter inserções de dados, as restantes estão
B58: protegidas, por incluírem fórmulas.
B59: 2. Para desproteger a planilha, se necessário aumentar ou retirar linhas, a senha é 123456.
B60: 3. Para aumentar ou retirar linhas, altere apenas as linhas internas de cada categoria. Para
B61: adicionar linhas basta copiar uma linha completa, com fórmulas e formatos, mas isso deve ser .
B62: feito igualmente nas planilhas DESP_XXX(MÊS) e PLAN2, nas mesmas posições.
... B114: cada categoria com uma cor específica, em gráfico de barras empilhadas.
